Workbook

Sheet CIERRE
A1: FECHA | B1: ID TIENDA | C1: NOMBRE | D1: TOTAL VENTA | E1: VISA | F1: EFECTIVO | G1: MASTERCARD | H1: DIFERENCIA | I1: AMERICAN EXPRESS | J1: DIFERENCIA | K1: DINERS | L1: DIFERENCIA | M1: LUKITA (BBVA) | N1: TUNKY (INTERBANK) | O1: WALI (INTERBANK) | P1: YAPE (BCP) | Q1: MILLAS INTERBANK | R1: PUNTOS VIDA (BBVA) | S1: TRANSFERENCIA MALVITEC | T1: RAPPI | U1: ADELANTO (PRE-VENTA) | V1: YAPE (BCP) - 2 | W1: YAPE (BCP) - 3 | X1: SANTANDER | Y1: MIS CUOTAS | Z1: CUOTEALO | AA1: POWERPAY | AB1: CÁLIDDA | AC1: NOTA CREDITO | AD1: TOTAL
A2: 46113 | B2: MIS.MI01 | C2: MI STORE SHELL MIRAFLORES | D2: 30436.42 | E2: 0 | F2: 340.9 | G2: 21110.42 | H2: =SUM(G2-(_xlfn.XLOOKUP(A2,MASTERCARD!AI:AI,MASTERCARD!AJ:AJ))) -> -3.6379788e-12 | I2: 2971 | J2: =SUM(I2-(_xlfn.XLOOKUP(A2,AMEX!Z:Z,AMEX!AA:AA))) -> 0 | K2: 1253.9 | L2: =SUM(K2-(_xlfn.XLOOKUP(A2,DINERS!B:B,DINERS!C:C))) -> 0 | M2: 0 | N2: 0 | O2: 0 | P2: 0 | Q2: 79 | R2: 489 | S2: 0 | T2: 0 | U2: 0 | V2: 0 | W2: 0 | X2: 0 | Y2: 0 | Z2: 0 | AA2: 2425 | AB2: 0 | AC2: 1767.2 | AD2: 60531.94
A3: 46114 | B3: MIS.MI01 | C3: MI STORE SHELL MIRAFLORES | D3: 36549.6 | E3: 0 | F3: 2058.8 | G3: 30496.8 | H3: =SUM(G3-(_xlfn.XLOOKUP(A3,MASTERCARD!AI:AI,MASTERCARD!AJ:AJ))) -> -3.6379788e-12 | I3: 0 | J3: =SUM(I3-(_xlfn.XLOOKUP(A3,AMEX!Z:Z,AMEX!AA:AA))) -> #N/A | K3: 0 | L3: =SUM(K3-(_xlfn.XLOOKUP(A3,DINERS!B:B,DINERS!C:C))) -> #N/A | M3: 0 | N3: 0 | O3: 0 | P3: 0 | Q3: 140 | R3: 1137 | S3: 0 | T3: 0 | U3: 0 | V3: 0 | W3: 0 | X3: 0 | Y3: 0 | Z3: 0 | AA3: 1699 | AB3: 0 | AC3: 849 | AD3: 70702.4
A4: 46115 | B4: MIS.MI01 | C4: MI STORE SHELL MIRAFLORES | D4: 17255.6 | E4: 0 | F4: 1864.8 | G4: 10037.9 | H4: =SUM(G4-(_xlfn.XLOOKUP(A4,MASTERCARD!AI:AI,MASTERCARD!AJ:AJ))) -> 0 | I4: 632.1 | J4: =SUM(I4-(_xlfn.XLOOKUP(A4,AMEX!Z:Z,AMEX!AA:AA))) -> 0 | K4: 408 | L4: =SUM(K4-(_xlfn.XLOOKUP(A4,DINERS!B:B,DINERS!C:C))) -> 0 | M4: 0 | N4: 0 | O4: 0 | P4: 0 | Q4: 114.8 | R4: 0 | S4: 0 | T4: 0 | U4: 0 | V4: 0 | W4: 0 | X4: 0 | Y4: 0 | Z4: 0 | AA4: 4198 | AB4: 0 | AC4: 0 | AD4: 32646.4
A5: 46116 | B5: MIS.MI01 | C5: MI STORE SHELL MIRAFLORES | D5: 32244.22 | E5: 0 | F5: 567.75 | G5: 28652.22 | H5: =SUM(G5-(_xlfn.XLOOKUP(A5,MASTERCARD!AI:AI,MASTERCARD!AJ:AJ))) -> -7.2759576e-12 | I5: 1537 | J5: =SUM(I5-(_xlfn.XLOOKUP(A5,AMEX!Z:Z,AMEX!AA:AA))) -> 0 | K5: 0 | L5: =SUM(K5-(_xlfn.XLOOKUP(A5,DINERS!B:B,DINERS!C:C))) -> #N/A | M5: 0 | N5: 0 | O5: 0 | P5: 0 | Q5: 1050 | R5: 299 | S5: 0 | T5: 0 | U5: 0 | V5: 0 | W5: 0 | X5: 0 | Y5: 149.25 | Z5: 0 | AA5: 0 | AB5: 0 | AC5: 189 | AD5: 64131.69
A6: 46117 | B6: MIS.MI01 | C6: MI STORE SHELL MIRAFLORES | D6: 23136.55 | E6: 0 | F6: 507.9 | G6: 16469.6 | H6: =SUM(G6-(_xlfn.XLOOKUP(A6,MASTERCARD!AI:AI,MASTERCARD!AJ:AJ))) -> 0 | I6: 149 | J6: =SUM(I6-(_xlfn.XLOOKUP(A6,AMEX!Z:Z,AMEX!AA:AA))) -> 0 | K6: 1008 | L6: =SUM(K6-(_xlfn.XLOOKUP(A6,DINERS!B:B,DINERS!C:C))) -> 0 | M6: 0 | N6: 0 | O6: 0 | P6: 0 | Q6: 0 | R6: 768 | S6: 0 | T6: 0 | U6: 0 | V6: 0 | W6: 0 | X6: 0 | Y6: 0 | Z6: 0 | AA6: 2525 | AB6: 0 | AC6: 0 | AD6: 42347.1
A7: 46118 | B7: MIS.MI01 | C7: MI STORE SHELL MIRAFLORES | D7: 21052.3 | E7: 0 | F7: 1014 | G7: 15675.3 | H7: =SUM(G7-(_xlfn.XLOOKUP(A7,MASTERCARD!AI:AI,MASTERCARD!AJ:AJ))) -> 586 | I7: 1851 | J7: =SUM(I7-(_xlfn.XLOOKUP(A7,AMEX!Z:Z,AMEX!AA:AA))) -> -586 | K7: 1799 | L7: =SUM(K7-(_xlfn.XLOOKUP(A7,DINERS!B:B,DINERS!C:C))) -> 0 | M7: 0 | N7: 0 | O7: 0 | P7: 0 | Q7: 627 | R7: 0 | S7: 0 | T7: 0 | U7: 0 | V7: 0 | W7: 0 | X7: 0 | Y7: 0 | Z7: 0 | AA7: 0 | AB7: 0 | AC7: 0 | AD7: 40918.6
A8: 46119 | B8: MIS.MI01 | C8: MI STORE SHELL MIRAFLORES | D8: 30724 | E8: 0 | F8: 1759.9 | G8: 20674.1 | H8: =SUM(G8-(_xlfn.XLOOKUP(A8,MASTERCARD!AI:AI,MASTERCARD!AJ:AJ))) -> 0 | I8: 549 | J8: =SUM(I8-(_xlfn.XLOOKUP(A8,AMEX!Z:Z,AMEX!AA:AA))) -> 0 | K8: 0 | L8: =SUM(K8-(_xlfn.XLOOKUP(A8,DINERS!B:B,DINERS!C:C))) -> #N/A | M8: 0 | N8: 0 | O8: 0 | P8: 0 | Q8: 0 | R8: 0 | S8: 0 | T8: 0 | U8: 0 | V8: 0 | W8: 0 | X8: 0 | Y8: 388 | Z8: 0 | AA8: 150 | AB8: 0 | AC8: 2423 | AD8: 50128.1
A9: 46120 | B9: MIS.MI01 | C9: MI STORE SHELL MIRAFLORES | D9: 26796.3 | E9: 0 | F9: 3775.9 | G9: 15624.75 | H9: =SUM(G9-(_xlfn.XLOOKUP(A9,MASTERCARD!AI:AI,MASTERCARD!AJ:AJ))) -> 1.8189894e-12 | I9: 269 | J9: =SUM(I9-(_xlfn.XLOOKUP(A9,AMEX!Z:Z,AMEX!AA:AA))) -> 0 | K9: 0 | L9: =SUM(K9-(_xlfn.XLOOKUP(A9,DINERS!B:B,DINERS!C:C))) -> #N/A | M9: 0 | N9: 0 | O9: 0 | P9: 0 | Q9: 847 | R9: 0 | S9: 0 | T9: 0 | U9: 0 | V9: 0 | W9: 0 | X9: 0 | Y9: 786.75 | Z9: 0 | AA9: 0 | AB9: 0 | AC9: 2014.9 | AD9: 42860.7
A10: 46121 | B10: MIS.MI01 | C10: MI STORE SHELL MIRAFLORES | D10: 19119.1 | E10: 0 | F10: 452 | G10: 10614.75 | H10: =SUM(G10-(_xlfn.XLOOKUP(A10,MASTERCARD!AI:AI,MASTERCARD!AJ:AJ))) -> 1.8189894e-12 | I10: 69 | J10: =SUM(I10-(_xlfn.XLOOKUP(A10,AMEX!Z:Z,AMEX!AA:AA))) -> 0 | K10: 0 | L10: =SUM(K10-(_xlfn.XLOOKUP(A10,DINERS!B:B,DINERS!C:C))) -> #N/A | M10: 0 | N10: 0 | O10: 0 | P10: 0 | Q10: 0 | R10: 1454 | S10: 0 | T10: 0 | U10: 0 | V10: 0 | W10: 0 | X10: 0 | Y10: 1109.25 | Z10: 0 | AA10: 1599 | AB10: 0 | AC10: 3500.2 | AD10: 37144.4
A11: 46122 | B11: MIS.MI01 | C11: MI STORE SHELL MIRAFLORES | D11: 18671.57 | E11: 0 | F11: 576 | G11: 12470.6 | H11: =SUM(G11-(_xlfn.XLOOKUP(A11,MASTERCARD!AI:AI,MASTERCARD!AJ:AJ))) -> 79.5 | I11: 1768 | J11: =SUM(I11-(_xlfn.XLOOKUP(A11,AMEX!Z:Z,AMEX!AA:AA))) -> 0 | K11: 53 | L11: =SUM(K11-(_xlfn.XLOOKUP(A11,DINERS!B:B,DINERS!C:C))) -> 0
A12: 46123 | B12: MIS.MI01 | C12: MI STORE SHELL MIRAFLORES | D12: 38579.3 | E12: 0 | F12: 2665 | G12: 25611.3 | H12: =SUM(G12-(_xlfn.XLOOKUP(A12,MASTERCARD!AI:AI,MASTERCARD!AJ:AJ))) -> 0 | I12: 0 | J12: =SUM(I12-(_xlfn.XLOOKUP(A12,AMEX!Z:Z,AMEX!AA:AA))) -> #N/A | K12: 0 | L12: =SUM(K12-(_xlfn.XLOOKUP(A12,DINERS!B:B,DINERS!C:C))) -> #N/A
A13: 46124 | B13: MIS.MI01 | C13: MI STORE SHELL MIRAFLORES | D13: 21986.8 | E13: 0 | F13: 0 | G13: 21235.8 | H13: =SUM(G13-(_xlfn.XLOOKUP(A13,MASTERCARD!AI:AI,MASTERCARD!AJ:AJ))) -> 105 | I13: 0 | J13: =SUM(I13-(_xlfn.XLOOKUP(A13,AMEX!Z:Z,AMEX!AA:AA))) -> -105 | K13: 0 | L13: =SUM(K13-(_xlfn.XLOOKUP(A13,DINERS!B:B,DINERS!C:C))) -> #N/A
A14: 46125 | B14: MIS.MI01 | C14: MI STORE SHELL MIRAFLORES | D14: 23318.4 | E14: 0 | F14: 2027.9 | G14: 15823.54 | H14: =SUM(G14-(_xlfn.XLOOKUP(A14,MASTERCARD!AI:AI,MASTERCARD!AJ:AJ))) -> 3.6379788e-12 | I14: 159 | J14: =SUM(I14-(_xlfn.XLOOKUP(A14,AMEX!Z:Z,AMEX!AA:AA))) -> 0 | K14: 1008 | L14: =SUM(K14-(_xlfn.XLOOKUP(A14,DINERS!B:B,DINERS!C:C))) -> 0
A15: 46126 | B15: MIS.MI01 | C15: MI STORE SHELL MIRAFLORES | D15: 17173.4 | E15: 0 | F15: 518.9 | G15: 11756.5 | H15: =SUM(G15-(_xlfn.XLOOKUP(A15,MASTERCARD!AI:AI,MASTERCARD!AJ:AJ))) -> 0 | I15: 0 | J15: =SUM(I15-(_xlfn.XLOOKUP(A15,AMEX!Z:Z,AMEX!AA:AA))) -> #N/A | K15: 0 | L15: =SUM(K15-(_xlfn.XLOOKUP(A15,DINERS!B:B,DINERS!C:C))) -> #N/A
A16: 46127 | B16: MIS.MI01 | C16: MI STORE SHELL MIRAFLORES | D16: 25945.5 | E16: 0 | F16: 5739.9 | G16: 12781.6 | H16: =SUM(G16-(_xlfn.XLOOKUP(A16,MASTERCARD!AI:AI,MASTERCARD!AJ:AJ))) -> 1.8189894e-12 | I16: 298 | J16: =SUM(I16-(_xlfn.XLOOKUP(A16,AMEX!Z:Z,AMEX!AA:AA))) -> 0 | K16: 0 | L16: =SUM(K16-(_xlfn.XLOOKUP(A16,DINERS!B:B,DINERS!C:C))) -> #N/A
A17: 46128 | B17: MIS.MI01 | C17: MI STORE SHELL MIRAFLORES | D17: 19497.4 | E17: 0 | F17: 369 | G17: 13522.2 | H17: =SUM(G17-(_xlfn.XLOOKUP(A17,MASTERCARD!AI:AI,MASTERCARD!AJ:AJ))) -> 3.6379788e-12 | I17: 243 | J17: =SUM(I17-(_xlfn.XLOOKUP(A17,AMEX!Z:Z,AMEX!AA:AA))) -> 0 | K17: 1299 | L17: =SUM(K17-(_xlfn.XLOOKUP(A17,DINERS!B:B,DINERS!C:C))) -> 0
A18: 46129 | B18: MIS.MI01 | C18: MI STORE SHELL MIRAFLORES | D18: 22809.14 | E18: 0 | F18: 1917 | G18: 15231.79 | H18: =SUM(G18-(_xlfn.XLOOKUP(A18,MASTERCARD!AI:AI,MASTERCARD!AJ:AJ))) -> 3.6379788e-12 | I18: 49 | J18: =SUM(I18-(_xlfn.XLOOKUP(A18,AMEX!Z:Z,AMEX!AA:AA))) -> 0 | K18: 0 | L18: =SUM(K18-(_xlfn.XLOOKUP(A18,DINERS!B:B,DINERS!C:C))) -> #N/A
A19: 46130 | B19: MIS.MI01 | C19: MI STORE SHELL MIRAFLORES | D19: 32170 | E19: 0 | F19: 272 | G19: 20935.7 | H19: =SUM(G19-(_xlfn.XLOOKUP(A19,MASTERCARD!AI:AI,MASTERCARD!AJ:AJ))) -> 0 | I19: 1687.9 | J19: =SUM(I19-(_xlfn.XLOOKUP(A19,AMEX!Z:Z,AMEX!AA:AA))) -> -450 | K19: 108.9 | L19: =SUM(K19-(_xlfn.XLOOKUP(A19,DINERS!B:B,DINERS!C:C))) -> 0
A20: 46131 | B20: MIS.MI01 | C20: MI STORE SHELL MIRAFLORES | D20: 21138.3 | E20: 0 | F20: 1148 | G20: 18685.3 | H20: =SUM(G20-(_xlfn.XLOOKUP(A20,MASTERCARD!AI:AI,MASTERCARD!AJ:AJ))) -> 0 | I20: 189 | J20: =SUM(I20-(_xlfn.XLOOKUP(A20,AMEX!Z:Z,AMEX!AA:AA))) -> 0 | K20: 178 | L20: =SUM(K20-(_xlfn.XLOOKUP(A20,DINERS!B:B,DINERS!C:C))) -> 0
A21: 46132 | B21: MIS.MI01 | C21: MI STORE SHELL MIRAFLORES | D21: 22673.5 | E21: 0 | F21: 2903.9 | G21: 11028.6 | H21: =SUM(G21-(_xlfn.XLOOKUP(A21,MASTERCARD!AI:AI,MASTERCARD!AJ:AJ))) -> 1.8189894e-12 | I21: 69 | J21: =SUM(I21-(_xlfn.XLOOKUP(A21,AMEX!Z:Z,AMEX!AA:AA))) -> 0 | K21: 849 | L21: =SUM(K21-(_xlfn.XLOOKUP(A21,DINERS!B:B,DINERS!C:C))) -> 0
A22: 46133 | B22: MIS.MI01 | C22: MI STORE SHELL MIRAFLORES | D22: 33555.8 | E22: 0 | F22: 1095.25 | G22: 19560.6 | H22: =SUM(G22-(_xlfn.XLOOKUP(A22,MASTERCARD!AI:AI,MASTERCARD!AJ:AJ))) -> 0 | I22: 17.9 | J22: =SUM(I22-(_xlfn.XLOOKUP(A22,AMEX!Z:Z,AMEX!AA:AA))) -> 0 | K22: 1399 | L22: =SUM(K22-(_xlfn.XLOOKUP(A22,DINERS!B:B,DINERS!C:C))) -> 0
... A31: 46142 | B31: MIS.MI01 | C31: MI STORE SHELL MIRAFLORES | D31: 10545.9 | E31: 0 | F31: 688 | G31: 8556.9 | H31: =SUM(G31-(_xlfn.XLOOKUP(A31,MASTERCARD!AI:AI,MASTERCARD!AJ:AJ))) -> 69 | I31: 138.9 | J31: =SUM(I31-(_xlfn.XLOOKUP(A31,AMEX!Z:Z,AMEX!AA:AA))) -> #N/A | K31: 159 | L31: =SUM(K31-(_xlfn.XLOOKUP(A31,DINERS!B:B,DINERS!C:C))) -> 0

Sheet MASTERCARD
A1: Codigo | B1: Producto | C1: Tipo_Mov | D1: Fecha_Proceso | E1: Fecha_Lote | F1: Lote_Manual | G1: Lote_Pos | H1: Terminal | I1: Voucher | J1: Autorizacion | K1: Cuotas | L1: Tarjeta | M1: Origen | N1: Transaccion | O1: Fecha_Consumo | P1: Importe | Q1: Status | R1: Comision | S1: Comision_Afecta | T1: IGV | U1: Neto_Parcial | V1: Neto_Total | W1: Fecha_Abono | X1: Fecha_Abono_8Dig | Y1: Observaciones | Z1: Tipo_Tarjeta | AA1: Serie_Terminal | AB1: Banco_Emisor | AC1: Cuota sin interes | AD1: Entidad | AE1: Hora TRX | AF1: Nombre comercial | AI1: Etiquetas de fila | AJ1: Suma de Importe | AM1: VALIDACION DE DEPOSITOS
A2: 1023366 | B2: MC | C2: A | D2: 46113 | E2: 46113 | G2: 348 | H2: PS0005 | I2: 6444 | J2: 76379 | L2: 511842******2868 | M2: Nac | N2: COM | O2: 46113 | P2: 150 | Q2: Abonado | R2: 4.34 | S2: 1.71 | T2: 0.31 | U2: 145.35 | V2: 0 | X2: 20260406 | Z2: DEBITO | AA2: 3974527 | AB2: SCOTIA DEBIT | AE2: 0.62358796 | AF2: XIAOMI SCHELL | AI2: Abonado | AJ2: 507377.37
A3: 1023366 | B3: MC | C3: A | D3: 46113 | E3: 46113 | G3: 348 | H3: PS0005 | I3: 6474 | J3: 438970 | K3: 2 | L3: 525435******3245 | M3: Nac | N3: COM | O3: 46113 | P3: 179 | Q3: Abonado | R3: 5.17 | S3: 1.41 | T3: 0.25 | U3: 173.58 | V3: 318.93 | W3: 46118 | X3: 20260406 | Z3: CREDITO | AA3: 3974527 | AB3: BRIPLEY | AC3: NO | AE3: 0.73394676 | AF3: XIAOMI SCHELL | AI3: 46113 | AJ3: 21110.42 | AL3: 104107 | AM3: =+V3 -> 318.93 | AN3: =_xlfn.XLOOKUP(V3,Bancos!H:H,Bancos!C:C) -> 8224818 | AO3: =_xlfn.XLOOKUP(AN3,Bancos!C:C,Bancos!A:A) -> 06/04/2026 | AP3: =+AO3-W3 -> 0
A4: 1023366 | B4: VA | C4: A | D4: 46113 | E4: 46113 | G4: 348 | H4: PS0005 | I4: 6393 | J4: 758103 | L4: 421355******0350 | M4: Nac | N4: COM | O4: 46113 | P4: 2199 | Q4: Abonado | R4: 63.55 | S4: 28.37 | T4: 5.11 | U4: 2130.34 | V4: 0 | X4: 20260406 | Z4: DEBITO | AA4: 3974527 | AB4: IBK PRIVADA | AE4: 0.49068287 | AF4: XIAOMI SCHELL | AI4: 46114 | AJ4: 30496.8
A5: 1023366 | B5: VA | C5: A | D5: 46113 | E5: 46113 | G5: 348 | H5: PS0005 | I5: 6395 | J5: 89014 | L5: 491257******5249 | M5: Nac | N5: COM | O5: 46113 | P5: 149 | Q5: Abonado | R5: 4.31 | S5: 1.93 | T5: 0.35 | U5: 144.34 | V5: 0 | X5: 20260406 | Z5: DEBITO | AA5: 3974527 | AB5: BCP | AE5: 0.49327546 | AF5: XIAOMI SCHELL | AI5: 46115 | AJ5: 10037.9
A6: 1023366 | B6: VA | C6: A | D6: 46113 | E6: 46113 | G6: 348 | H6: PS0005 | I6: 6397 | J6: 175017 | L6: 455788******2961 | M6: Nac | N6: COM | O6: 46113 | P6: 29.9 | Q6: Abonado | R6: 0.86 | S6: 0.38 | T6: 0.07 | U6: 28.97 | V6: 0 | X6: 20260406 | Z6: DEBITO | AA6: 3974527 | AB6: VISA LOC | AE6: 0.49722222 | AF6: XIAOMI SCHELL | AI6: 46116 | AJ6: 28652.22
A7: 1023366 | B7: VA | C7: A | D7: 46113 | E7: 46113 | G7: 348 | H7: PS0005 | I7: 6399 | J7: 81178 | L7: 421355******4374 | M7: Nac | N7: COM | O7: 46113 | P7: 124 | Q7: Abonado | R7: 3.58 | S7: 1.6 | T7: 0.29 | U7: 120.13 | V7: 0 | X7: 20260406 | Z7: DEBITO | AA7: 3974527 | AB7: IBK PRIVADA | AE7: 0.50665509 | AF7: XIAOMI SCHELL | AI7: 46117 | AJ7: 16469.6
A8: 1023366 | B8: VA | C8: A | D8: 46113 | E8: 46113 | G8: 348 | H8: PS0005 | I8: 6401 | J8: 46291 | L8: 428581******6107 | M8: Nac | N8: COM | O8: 46113 | P8: 129 | Q8: Abonado | R8: 3.73 | S8: 1.67 | T8: 0.3 | U8: 124.97 | V8: 0 | X8: 20260406 | Z8: DEBITO | AA8: 3974527 | AB8: SCOTIABANK | AE8: 0.50984954 | AF8: XIAOMI SCHELL | AI8: 46118 | AJ8: 15089.3
A9: 1023366 | B9: VA | C9: A | D9: 46113 | E9: 46113 | G9: 348 | H9: PS0005 | I9: 6403 | J9: 720339 | L9: 491246******6814 | M9: Nac | N9: COM | O9: 46113 | P9: 1014 | Q9: Abonado | R9: 29.3 | S9: 8.01 | T9: 1.44 | U9: 983.26 | V9: 0 | X9: 20260406 | Z9: DEBITO | AA9: 3974527 | AB9: BCP | AE9: 0.51152778 | AF9: XIAOMI SCHELL | AI9: 46119 | AJ9: 20674.1
A10: 1023366 | B10: VA | C10: A | D10: 46113 | E10: 46113 | G10: 348 | H10: PS0005 | I10: 6407 | J10: 425557 | L10: 411090******4683 | M10: Nac | N10: COM | O10: 46113 | P10: 159 | Q10: Abonado | R10: 4.6 | S10: 0.94 | T10: 0.17 | U10: 154.23 | V10: 0 | X10: 20260406 | Z10: CREDITO | AA10: 3974527 | AB10: IBK PRIVADA | AE10: 0.52971065 | AF10: XIAOMI SCHELL | AI10: 46120 | AJ10: 15624.75
A11: 1023366 | B11: VA | C11: A | D11: 46113 | E11: 46113 | G11: 348 | H11: 65656565 | I11: 6411 | J11: 217463 | L11: 455788******4621 | M11: Nac | N11: COM | O11: 46113 | P11: 349 | Q11: Abonado | R11: 10.08 | S11: 4.5 | T11: 0.81 | U11: 338.11 | V11: 0 | X11: 20260406 | Z11: DEBITO | AA11: 3974527 | AB11: BCP | AD11: Yape | AE11: 0.54321759 | AF11: XIAOMI SCHELL | AI11: 46121 | AJ11: 10614.75
A12: 1023366 | B12: VA | C12: A | D12: 46113 | E12: 46113 | G12: 348 | H12: PS0005 | I12: 6415 | J12: 416838 | L12: 440355******4209 | M12: Nac | N12: COM | O12: 46113 | P12: 49 | Q12: Abonado | R12: 1.42 | S12: 0.64 | T12: 0.12 | U12: 47.46 | V12: 0 | X12: 20260406 | Z12: DEBITO | AA12: 3974527 | AB12: VISA LOC | AE12: 0.55715278 | AF12: XIAOMI SCHELL | AI12: 46122 | AJ12: 12391.1
A13: 1023366 | B13: VA | C13: A | D13: 46113 | E13: 46113 | G13: 348 | H13: PS0005 | I13: 6417 | J13: 390468 | L13: 455788******3730 | M13: Nac | N13: COM | O13: 46113 | P13: 69 | Q13: Abonado | R13: 1.99 | S13: 0.89 | T13: 0.16 | U13: 66.85 | V13: 0 | X13: 20260406 | Z13: DEBITO | AA13: 3974527 | AB13: BCP | AE13: 0.57818287 | AF13: XIAOMI SCHELL | AI13: 46123 | AJ13: 25611.3
A14: 1023366 | B14: VA | C14: A | D14: 46113 | E14: 46113 | G14: 348 | H14: PS0005 | I14: 6419 | J14: 893790 | L14: 421355******0258 | M14: Nac | N14: COM | O14: 46113 | P14: 149 | Q14: Abonado | R14: 4.31 | S14: 1.93 | T14: 0.35 | U14: 144.34 | V14: 0 | X14: 20260406 | Z14: DEBITO | AA14: 3974527 | AB14: IBK PRIVADA | AE14: 0.58396991 | AF14: XIAOMI SCHELL | AI14: 46124 | AJ14: 21130.8
A15: 1023366 | B15: VA | C15: A | D15: 46113 | E15: 46113 | G15: 348 | H15: PS0005 | I15: 6421 | J15: 295223 | L15: 455103******5157 | M15: Nac | N15: COM | O15: 46113 | P15: 105.8 | Q15: Abonado | R15: 3.06 | S15: 1.37 | T15: 0.25 | U15: 102.49 | V15: 0 | X15: 20260406 | Z15: DEBITO | AA15: 3974527 | AB15: BBVA | AE15: 0.58652778 | AF15: XIAOMI SCHELL | AI15: 46125 | AJ15: 15823.54
A16: 1023366 | B16: VA | C16: A | D16: 46113 | E16: 46113 | G16: 348 | H16: PS0005 | I16: 6423 | J16: 510308 | L16: 455788******2975 | M16: Nac | N16: COM | O16: 46113 | P16: 809 | Q16: Abonado | R16: 23.38 | S16: 10.44 | T16: 1.88 | U16: 783.74 | V16: 0 | X16: 20260406 | Z16: DEBITO | AA16: 3974527 | AB16: BCP | AE16: 0.59164352 | AF16: XIAOMI SCHELL | AI16: 46126 | AJ16: 11756.5
A17: 1023366 | B17: VA | C17: A | D17: 46113 | E17: 46113 | G17: 348 | H17: PS0005 | I17: 6426 | J17: 41659 | L17: 459954******5748 | M17: Ext | N17: COM | O17: 46113 | P17: 1499 | Q17: Abonado | R17: 58.46 | S17: 41.98 | T17: 7.56 | U17: 1432.98 | V17: 0 | X17: 20260406 | Z17: DEBITO | AA17: 3974527 | AB17: VISA INT | AE17: 0.59326389 | AF17: XIAOMI SCHELL | AI17: 46127 | AJ17: 12781.6
A18: 1023366 | B18: VA | C18: A | D18: 46113 | E18: 46113 | G18: 348 | H18: PS0005 | I18: 6429 | J18: 972013 | L18: 421355******6107 | M18: Nac | N18: COM | O18: 46113 | P18: 65 | Q18: Abonado | R18: 1.88 | S18: 0.84 | T18: 0.15 | U18: 62.97 | V18: 0 | X18: 20260406 | Z18: DEBITO | AA18: 3974527 | AB18: IBK PRIVADA | AE18: 0.60516204 | AF18: XIAOMI SCHELL | AI18: 46128 | AJ18: 13522.2
A19: 1023366 | B19: VA | C19: A | D19: 46113 | E19: 46113 | G19: 348 | H19: PS0005 | I19: 6431 | J19: 22857 | K19: 12 | L19: 494386******8454 | M19: Nac | N19: COM | O19: 46113 | P19: 2048 | Q19: Abonado | R19: 59.19 | S19: 16.18 | T19: 2.91 | U19: 1985.9 | V19: 0 | X19: 20260406 | Z19: CREDITO | AA19: 3974527 | AB19: SCOTIABANK | AC19: NO | AE19: 0.60917824 | AF19: XIAOMI SCHELL | AI19: 46129 | AJ19: 15231.79
A20: 1023366 | B20: VA | C20: A | D20: 46113 | E20: 46113 | G20: 348 | H20: 65656565 | I20: 6434 | J20: 409056 | L20: 455788******0513 | M20: Nac | N20: COM | O20: 46113 | P20: 90.8 | Q20: Abonado | R20: 2.62 | S20: 1.17 | T20: 0.21 | U20: 87.97 | V20: 0 | X20: 20260406 | Z20: DEBITO | AA20: 3974527 | AB20: BCP | AD20: Yape | AE20: 0.61487269 | AF20: XIAOMI SCHELL | AI20: 46130 | AJ20: 20935.7
A21: 1023366 | B21: VA | C21: A | D21: 46113 | E21: 46113 | G21: 348 | H21: PS0005 | I21: 6437 | J21: 3188 | L21: 455788******6991 | M21: Nac | N21: COM | O21: 46113 | P21: 105 | Q21: Abonado | R21: 3.03 | S21: 1.35 | T21: 0.24 | U21: 101.73 | V21: 0 | X21: 20260406 | Z21: DEBITO | AA21: 3974527 | AB21: BCP | AE21: 0.61605324 | AF21: XIAOMI SCHELL | AI21: 46131 | AJ21: 18685.3
A22: 1023366 | B22: VA | C22: A | D22: 46113 | E22: 46113 | G22: 348 | H22: PS0005 | I22: 6439 | J22: 480827 | L22: 491913******7170 | M22: Nac | N22: COM | O22: 46113 | P22: 139 | Q22: Abonado | R22: 4.02 | S22: 0.82 | T22: 0.15 | U22: 134.83 | V22: 0 | X22: 20260406 | Z22: CREDITO | AA22: 3974527 | AB22: BBVA | AE22: 0.61993056 | AF22: XIAOMI SCHELL | AI22: 46132 | AJ22: 11028.6
A23: 1023366 | B23: VA | C23: A | D23: 46113 | E23: 46113 | G23: 348 | H23: 65656565 | I23: 6441 | J23: 587402 | L23: 455788******0652 | M23: Nac | N23: COM | O23: 46113 | P23: 349 | Q23: Abonado | R23: 10.08 | S23: 4.5 | T23: 0.81 | U23: 338.11 | V23: 0 | X23: 20260406 | Z23: DEBITO | AA23: 3974527 | AB23: BCP | AD23: Yape | AE23: 0.62228009 | AF23: XIAOMI SCHELL | AI23: 46133 | AJ23: 19560.6
A24: 1023366 | B24: VA | C24: A | D24: 46113 | E24: 46113 | G24: 348 | H24: PS0005 | I24: 6449 | J24: 630558 | L24: 438466******8049 | M24: Nac | N24: COM | O24: 46113 | P24: 298 | Q24: Abonado | R24: 8.61 | S24: 3.84 | T24: 0.69 | U24: 288.7 | V24: 0 | X24: 20260406 | Z24: DEBITO | AA24: 3974527 | AB24: VISA LOC | AE24: 0.64946759 | AF24: XIAOMI SCHELL | AI24: 46134 | AJ24: 15922.05
A25: 1023366 | B25: VA | C25: A | D25: 46113 | E25: 46113 | G25: 348 | H25: PS0005 | I25: 6451 | J25: 682413 | L25: 447410******6998 | M25: Nac | N25: COM | O25: 46113 | P25: 89.9 | Q25: Abonado | R25: 2.6 | S25: 0.53 | T25: 0.1 | U25: 87.2 | V25: 0 | X25: 20260406 | Z25: CREDITO | AA25: 3974527 | AB25: BFALABELLA | AE25: 0.65171296 | AF25: XIAOMI SCHELL | AI25: 46135 | AJ25: 21716.9
A26: 1023366 | B26: VA | C26: A | D26: 46113 | E26: 46113 | G26: 348 | H26: PS0005 | I26: 6453 | J26: 683893 | L26: 491257******1731 | M26: Nac | N26: COM | O26: 46113 | P26: 2499 | Q26: Abonado | R26: 72.22 | S26: 32.24 | T26: 5.8 | U26: 2420.98 | V26: 0 | X26: 20260406 | Z26: DEBITO | AA26: 3974527 | AB26: BCP | AE26: 0.6615162 | AF26: XIAOMI SCHELL | AI26: 46136 | AJ26: 16286.5
A27: 1023366 | B27: VA | C27: A | D27: 46113 | E27: 46113 | G27: 348 | H27: PS0005 | I27: 6455 | J27: 544866 | K27: 2 | L27: 454775******5532 | M27: Nac | N27: COM | O27: 46113 | P27: 189 | Q27: Abonado | R27: 5.46 | S27: 1.49 | T27: 0.27 | U27: 183.27 | V27: 0 | X27: 20260406 | Z27: CREDITO | AA27: 3974527 | AB27: IBK PRIVADA | AC27: NO | AE27: 0.66295139 | AF27: XIAOMI SCHELL | AI27: 46137 | AJ27: 16298.15
A28: 1023366 | B28: VA | C28: A | D28: 46113 | E28: 46113 | G28: 348 | H28: PS0005 | I28: 6459 | J28: 754387 | L28: 455788******3122 | M28: Nac | N28: COM | O28: 46113 | P28: 149 | Q28: Abonado | R28: 4.31 | S28: 1.93 | T28: 0.35 | U28: 144.34 | V28: 0 | X28: 20260406 | Z28: DEBITO | AA28: 3974527 | AB28: VISA LOC | AE28: 0.68974537 | AF28: XIAOMI SCHELL | AI28: 46138 | AJ28: 14822.9
A29: 1023366 | B29: VA | C29: A | D29: 46113 | E29: 46113 | G29: 348 | H29: PS0005 | I29: 6461 | J29: 600890 | L29: 455788******8937 | M29: Nac | N29: COM | O29: 46113 | P29: 2923.52 | Q29: Abonado | R29: 84.49 | S29: 37.71 | T29: 6.79 | U29: 2832.24 | V29: 0 | X29: 20260406 | Z29: DEBITO | AA29: 3974527 | AB29: BCP | AE29: 0.69248843 | AF29: XIAOMI SCHELL | AI29: 46139 | AJ29: 14809.9
A30: 1023366 | B30: VA | C30: A | D30: 46113 | E30: 46113 | G30: 348 | H30: PS0005 | I30: 6464 | J30: 864187 | L30: 455170******4585 | M30: Nac | N30: COM | O30: 46113 | P30: 55 | Q30: Abonado | R30: 1.59 | S30: 0.71 | T30: 0.13 | U30: 53.28 | V30: 0 | X30: 20260406 | Z30: DEBITO | AA30: 3974527 | AB30: BBVA | AE30: 0.69460648 | AF30: XIAOMI SCHELL | AI30: 46140 | AJ30: 12249.9
A31: 1023366 | B31: VA | C31: A | D31: 46113 | E31: 46113 | G31: 348 | H31: PS0005 | I31: 6466 | J31: 4638 | L31: 445330******6783 | M31: Nac | N31: COM | O31: 46113 | P31: 79 | Q31: Abonado | R31: 2.28 | S31: 0.3 | T31: 0.05 | U31: 76.67 | V31: 0 | X31: 20260406 | Z31: CREDITO | AA31: 3974527 | AB31: BCP | AE31: 0.70923611 | AF31: XIAOMI SCHELL | AI31: 46141 | AJ31: 19554.3
A32: 1023366 | B32: VA | C32: A | D32: 46113 | E32: 46113 | G32: 348 | H32: PS0005 | I32: 6468 | J32: 990586 | L32: 455170******9348 | M32: Nac | N32: COM | O32: 46113 | P32: 65 | Q32: Abonado | R32: 1.88 | S32: 0.84 | T32: 0.15 | U32: 62.97 | V32: 0 | X32: 20260406 | Z32: DEBITO | AA32: 3974527 | AB32: BBVA | AE32: 0.71738426 | AF32: XIAOMI SCHELL | AI32: 46142 | AJ32: 8487.9
A33: 1023366 | B33: VA | C33: A | D33: 46113 | E33: 46113 | G33: 348 | H33: PS0005 | I33: 6470 | J33: 738 | L33: 444437******9429 | M33: Nac | N33: COM | O33: 46113 | P33: 159 | Q33: Abonado | R33: 4.6 | S33: 0.62 | T33: 0.11 | U33: 154.29 | V33: 0 | X33: 20260406 | Z33: CREDITO | AA33: 3974527 | AB33: BCP | AE33: 0.72591435 | AF33: XIAOMI SCHELL | AI33: Extorno | AJ33: -1296
A34: 1023366 | B34: VA | C34: A | D34: 46113 | E34: 46113 | G34: 348 | H34: PS0005 | I34: 6476 | J34: 8597 | L34: 463402******1898 | M34: Nac | N34: COM | O34: 46113 | P34: 49 | Q34: Abonado | R34: 1.42 | S34: 0.39 | T34: 0.07 | U34: 47.51 | V34: 0 | X34: 20260406 | Z34: CREDITO | AA34: 3974527 | AB34: BCP | AE34: 0.77329861 | AF34: XIAOMI SCHELL | AI34: 46121 | AJ34: -110
A35: 1023366 | B35: VA | C35: A | D35: 46113 | E35: 46113 | G35: 348 | H35: PS0005 | I35: 6478 | J35: 855916 | L35: 455788******3149 | M35: Nac | N35: COM | O35: 46113 | P35: 279 | Q35: Abonado | R35: 8.06 | S35: 3.6 | T35: 0.65 | U35: 270.29 | V35: 0 | X35: 20260406 | Z35: DEBITO | AA35: 3974527 | AB35: BCP | AE35: 0.78337963 | AF35: XIAOMI SCHELL | AI35: 46122 | AJ35: -378
A36: 1023366 | B36: VA | C36: A | D36: 46113 | E36: 46113 | G36: 348 | H36: PS0005 | I36: 6480 | J36: 743963 | L36: 447409******0803 | M36: Nac | N36: COM | O36: 46113 | P36: 269 | Q36: Abonado | R36: 7.77 | S36: 2.12 | T36: 0.38 | U36: 260.85 | V36: 0 | X36: 20260406 | Z36: CREDITO | AA36: 3974527 | AB36: BFALABELLA | AE36: 0.78413194 | AF36: XIAOMI SCHELL | AI36: 46128 | AJ36: -808
A37: 1023366 | B37: VA | C37: A | D37: 46113 | E37: 46113 | G37: 348 | H37: PS0005 | I37: 6483 | J37: 437521 | L37: 438466******9298 | M37: Nac | N37: COM | O37: 46113 | P37: 55 | Q37: Abonado | R37: 1.59 | S37: 0.43 | T37: 0.08 | U37: 53.33 | V37: 0 | X37: 20260406 | Z37: CREDITO | AA37: 3974527 | AB37: VISA LOC | AE37: 0.78842593 | AF37: XIAOMI SCHELL | AI37: (en blanco) | AJ37: 0
A38: 1023366 | B38: VA | C38: A | D38: 46113 | E38: 46113 | G38: 348 | H38: PS0005 | I38: 6485 | J38: 467118 | K38: 3 | L38: 414791******1057 | M38: Nac | N38: COM | O38: 46113 | P38: 279 | Q38: Abonado | R38: 12.94 | S38: 1.64 | T38: 0.3 | U38: 265.76 | V38: 0 | X38: 20260406 | Z38: CREDITO | AA38: 3974527 | AB38: BBVA | AC38: SI | AE38: 0.79296296 | AF38: XIAOMI SCHELL | AI38: (en blanco) | AJ38: 0
A39: 1023366 | B39: VA | C39: A | D39: 46113 | E39: 46113 | G39: 348 | H39: PS0005 | I39: 6487 | J39: 107132 | L39: 421410******3724 | M39: Nac | N39: COM | O39: 46113 | P39: 349 | Q39: Abonado | R39: 10.09 | S39: 4.51 | T39: 0.81 | U39: 338.1 | V39: 0 | X39: 20260406 | Z39: DEBITO | AA39: 3974527 | AB39: NACION | AE39: 0.79533565 | AF39: XIAOMI SCHELL | AI39: Total general | AJ39: 506081.37
A40: 1023366 | B40: VA | C40: A | D40: 46113 | E40: 46113 | G40: 348 | H40: PS0005 | I40: 6489 | J40: 529428 | K40: 3 | L40: 414791******4417 | M40: Nac | N40: COM | O40: 46113 | P40: 49 | Q40: Abonado | R40: 2.28 | S40: 0.29 | T40: 0.05 | U40: 46.67 | V40: 0 | X40: 20260406 | Z40: CREDITO | AA40: 3974527 | AB40: BBVA | AC40: SI | AE40: 0.80234954 | AF40: XIAOMI SCHELL
A41: 1023366 | B41: VA | C41: A | D41: 46113 | E41: 46113 | G41: 348 | H41: PS0005 | I41: 6491 | J41: 576766 | K41: 2 | L41: 491909******7742 | M41: Nac | N41: COM | O41: 46113 | P41: 269 | Q41: Abonado | R41: 12.48 | S41: 2.12 | T41: 0.38 | U41: 256.14 | V41: 0 | X41: 20260406 | Z41: CREDITO | AA41: 3974527 | AB41: BBVA | AC41: SI | AE41: 0.80938657 | AF41: XIAOMI SCHELL
A42: 1023366 | B42: VA | C42: A | D42: 46113 | E42: 46113 | G42: 348 | H42: PS0005 | I42: 6493 | J42: 9604 | L42: 445330******2906 | M42: Nac | N42: COM | O42: 46113 | P42: 89.9 | Q42: Abonado | R42: 2.6 | S42: 0.35 | T42: 0.06 | U42: 87.24 | V42: 0 | X42: 20260406 | Z42: CREDITO | AA42: 3974527 | AB42: BCP | AE42: 0.82226852 | AF42: XIAOMI SCHELL
A43: 1023366 | B43: VA | C43: A | D43: 46113 | E43: 46113 | G43: 348 | H43: PS0005 | I43: 6495 | J43: 10445 | K43: 2 | L43: 466721******4589 | M43: Nac | N43: COM | O43: 46113 | P43: 269 | Q43: Abonado | R43: 7.77 | S43: 2.12 | T43: 0.38 | U43: 260.85 | V43: 0 | X43: 20260406 | Z43: CREDITO | AA43: 3974527 | AB43: SCOTIABANK | AC43: NO | AE43: 0.83246528 | AF43: XIAOMI SCHELL
A44: 1023366 | B44: VA | C44: A | D44: 46113 | E44: 46113 | G44: 348 | H44: PS0005 | I44: 6501 | J44: 123937 | L44: 421355******0716 | M44: Nac | N44: COM | O44: 46113 | P44: 1899 | Q44: Abonado | R44: 54.88 | S44: 24.5 | T44: 4.41 | U44: 1839.71 | V44: 0 | X44: 20260406 | Z44: DEBITO | AA44: 3974527 | AB44: IBK PRIVADA | AE44: 0.83649306 | AF44: XIAOMI SCHELL
A45: 1023366 | B45: VA | C45: A | D45: 46113 | E45: 46113 | G45: 348 | H45: PS0005 | I45: 6503 | J45: 12262 | L45: 421918******2517 | M45: Nac | N45: COM | O45: 46113 | P45: 268.9 | Q45: Abonado | R45: 7.77 | S45: 1.05 | T45: 0.19 | U45: 260.94 | V45: 0 | X45: 20260406 | Z45: CREDITO | AA45: 3974527 | AB45: SCOTIABANK | AE45: 0.83709491 | AF45: XIAOMI SCHELL
A46: 1023366 | B46: VA | C46: A | D46: 46113 | E46: 46113 | G46: 348 | H46: PS0005 | I46: 6506 | J46: 768317 | L46: 438466******4520 | M46: Nac | N46: COM | O46: 46113 | P46: 79 | Q46: Abonado | R46: 2.28 | S46: 0.3 | T46: 0.05 | U46: 76.67 | V46: 0 | X46: 20260406 | Z46: CREDITO | AA46: 3974527 | AB46: VISA LOC | AE46: 0.83858796 | AF46: XIAOMI SCHELL
A47: 1023366 | B47: VA | C47: A | D47: 46113 | E47: 46113 | G47: 348 | H47: 65656565 | I47: 6508 | J47: 121758 | L47: 455788******7575 | M47: Nac | N47: COM | O47: 46113 | P47: 193 | Q47: Abonado | R47: 5.57 | S47: 2.48 | T47: 0.45 | U47: 186.98 | V47: 0 | X47: 20260406 | Z47: DEBITO | AA47: 3974527 | AB47: BCP | AD47: Yape | AE47: 0.84416667 | AF47: XIAOMI SCHELL
A48: 1023366 | B48: VA | C48: A | D48: 46113 | E48: 46113 | G48: 348 | H48: PS0005 | I48: 6511 | J48: 14504 | L48: 421355******7937 | M48: Nac | N48: COM | O48: 46113 | P48: 119.7 | Q48: Abonado | R48: 3.46 | S48: 1.54 | T48: 0.28 | U48: 115.96 | V48: 0 | X48: 20260406 | Z48: DEBITO | AA48: 3974527 | AB48: IBK PRIVADA | AE48: 0.84798611 | AF48: XIAOMI SCHELL
A49: 1023366 | B49: VA | C49: A | D49: 46113 | E49: 46113 | G49: 348 | H49: PS0005 | I49: 6513 | J49: 440858 | L49: 455696******3706 | M49: Nac | N49: COM | O49: 46113 | P49: 79 | Q49: Abonado | R49: 2.28 | S49: 0.46 | T49: 0.08 | U49: 76.64 | V49: 20061.3 | W49: 46118 | X49: 20260406 | Z49: CREDITO | AA49: 3974527 | AB49: IBK PRIVADA | AE49: 0.86388889 | AF49: XIAOMI SCHELL | AL49: 104107 | AM49: =+V49 -> 20061.3 | AN49: =_xlfn.XLOOKUP(V49,Bancos!H:H,Bancos!C:C) -> 8224819 | AO49: =_xlfn.XLOOKUP(AN49,Bancos!C:C,Bancos!A:A) -> 06/04/2026 | AP49: =+AO49-W49 -> 0
A50: 1023366 | B50: VX | C50: A | D50: 46113 | E50: 46113 | G50: 348 | H50: PS0005 | I50: 6446 | J50: 48843 | L50: 422829******1265 | M50: Nac | N50: COM | O50: 46113 | P50: 49 | Q50: Abonado | R50: 1.42 | S50: 1.42 | T50: 0.26 | U50: 47.32 | V50: 47.32 | W50: 46118 | X50: 20260406 | Z50: DEBITO | AA50: 3974527 | AB50: SODEXO | AE50: 0.64671296 | AF50: XIAOMI SCHELL | AL50: 104107 | AM50: =+V50 -> 47.32 | AN50: =_xlfn.XLOOKUP(V50,Bancos!H:H,Bancos!C:C) -> 8170924 | AO50: =_xlfn.XLOOKUP(AN50,Bancos!C:C,Bancos!A:A) -> 06/04/2026 | AP50: =+AO50-W50 -> 0
A51: 1023366 | B51: MC | C51: A | D51: 46114 | E51: 46114 | G51: 349 | H51: PS0005 | I51: 6560 | J51: 100970 | L51: 525435******0274 | M51: Nac | N51: COM | O51: 46114 | P51: 179.8 | Q51: Abonado | R51: 5.2 | S51: 1.42 | T51: 0.26 | U51: 174.34 | V51: 0 | X51: 20260406 | Z51: CREDITO | AA51: 3974527 | AB51: BRIPLEY | AE51: 0.59675926 | AF51: XIAOMI SCHELL
A52: 1023366 | B52: MC | C52: A | D52: 46114 | E52: 46114 | G52: 349 | H52: PS0005 | I52: 6588 | J52: R03694 | L52: 518047******1522 | M52: Nac | N52: COM | O52: 46114 | P52: 179 | Q52: Abonado | R52: 5.17 | S52: 0.61 | T52: 0.11 | U52: 173.72 | V52: 0 | X52: 20260406 | Z52: CREDITO | AA52: 3974527 | AB52: SBP | AE52: 0.67703704 | AF52: XIAOMI SCHELL
A53: 1023366 | B53: MC | C53: A | D53: 46114 | E53: 46114 | G53: 349 | H53: PS0005 | I53: 6592 | J53: R06320 | L53: 522772******0139 | M53: Nac | N53: COM | O53: 46114 | P53: 169 | Q53: Abonado | R53: 4.88 | S53: 1.25 | T53: 0.23 | U53: 163.89 | V53: 0 | X53: 20260406 | Z53: CREDITO | AA53: 3974527 | AB53: NACION | AE53: 0.6834838 | AF53: XIAOMI SCHELL
A54: 1023366 | B54: MC | C54: A | D54: 46114 | E54: 46114 | G54: 349 | H54: PS0005 | I54: 6611 | J54: 713939 | L54: 553650******9692 | M54: Nac | N54: COM | O54: 46114 | P54: 129 | Q54: Abonado | R54: 3.73 | S54: 0.44 | T54: 0.08 | U54: 125.19 | V54: 0 | X54: 20260406 | Z54: CREDITO | AA54: 3974527 | AB54: BBVA | AE54: 0.73107639 | AF54: XIAOMI SCHELL
A55: 1023366 | B55: MC | C55: A | D55: 46114 | E55: 46114 | G55: 349 | H55: PS0005 | I55: 6657 | J55: R09842 | L55: 529206******7509 | M55: Nac | N55: COM | O55: 46114 | P55: 89.9 | Q55: Abonado | R55: 2.6 | S55: 0.71 | T55: 0.13 | U55: 87.17 | V55: 724.31 | W55: 46118 | X55: 20260406 | Z55: CREDITO | AA55: 3974527 | AB55: CJ RURAL MC | AE55: 0.84127315 | AF55: XIAOMI SCHELL | AL55: 104107 | AM55: =+V55 -> 724.31 | AN55: =_xlfn.XLOOKUP(V55,Bancos!H:H,Bancos!C:C) -> 8224820 | AO55: =_xlfn.XLOOKUP(AN55,Bancos!C:C,Bancos!A:A) -> 06/04/2026 | AP55: =+AO55-W55 -> 0
A56: 1023366 | B56: MR | C56: A | D56: 46114 | E56: 46114 | G56: 349 | H56: PS0005 | I56: 6585 | J56: R08887 | L56: 233063******0870 | M56: Nac | N56: COM | O56: 46114 | P56: 149 | Q56: Abonado | R56: 4.31 | S56: 4.31 | T56: 0.78 | U56: 143.91 | V56: 143.91 | W56: 46118 | X56: 20260406 | Z56: CREDITO | AA56: 3974527 | AB56: EDENRED | AE56: 0.65482639 | AF56: XIAOMI SCHELL | AL56: 104107 | AM56: =+V56 -> 143.91 | AN56: =_xlfn.XLOOKUP(V56,Bancos!H:H,Bancos!C:C) -> 8170926 | AO56: =_xlfn.XLOOKUP(AN56,Bancos!C:C,Bancos!A:A) -> 06/04/2026 | AP56: =+AO56-W56 -> 0
A57: 1023366 | B57: VA | C57: A | D57: 46114 | E57: 46114 | G57: 349 | H57: PS0005 | I57: 6529 | J57: 543465 | L57: 455788******0695 | M57: Nac | N57: COM | O57: 46114 | P57: 69 | Q57: Abonado | R57: 1.99 | S57: 0.89 | T57: 0.16 | U57: 66.85 | V57: 0 | X57: 20260406 | Z57: DEBITO | AA57: 3974527 | AB57: BCP | AE57: 0.42228009 | AF57: XIAOMI SCHELL
A58: 1023366 | B58: VA | C58: A | D58: 46114 | E58: 46114 | G58: 349 | H58: PS0005 | I58: 6531 | J58: 207331 | K58: 3 | L58: 491914******4963 | M58: Nac | N58: COM | O58: 46114 | P58: 968 | Q58: Abonado | R58: 44.92 | S58: 5.72 | T58: 1.03 | U58: 922.05 | V58: 0 | X58: 20260406 | Z58: CREDITO | AA58: 3974527 | AB58: BBVA | AC58: SI | AE58: 0.4352662 | AF58: XIAOMI SCHELL
A59: 1023366 | B59: VA | C59: A | D59: 46114 | E59: 46114 | G59: 349 | H59: PS0005 | I59: 6533 | J59: 64601 | L59: 466721******0808 | M59: Nac | N59: COM | O59: 46114 | P59: 139 | Q59: Abonado | R59: 4.02 | S59: 1.1 | T59: 0.2 | U59: 134.78 | V59: 0 | X59: 20260406 | Z59: CREDITO | AA59: 3974527 | AB59: SCOTIABANK | AE59: 0.49638889 | AF59: XIAOMI SCHELL
A60: 1023366 | B60: VA | C60: A | D60: 46114 | E60: 46114 | G60: 349 | H60: PS0005 | I60: 6535 | J60: 39056 | L60: 421410******1979 | M60: Nac | N60: COM | O60: 46114 | P60: 39.9 | Q60: Abonado | R60: 1.15 | S60: 0.51 | T60: 0.09 | U60: 38.66 | V60: 0 | X60: 20260406 | Z60: DEBITO | AA60: 3974527 | AB60: NACION | AE60: 0.49960648 | AF60: XIAOMI SCHELL
A61: 1023366 | B61: VA | C61: A | D61: 46114 | E61: 46114 | G61: 349 | H61: 65656565 | I61: 6539 | J61: 572802 | L61: 455103******5921 | M61: Nac | N61: COM | O61: 46114 | P61: 49 | Q61: Abonado | R61: 1.41 | S61: 0.63 | T61: 0.11 | U61: 47.48 | V61: 0 | X61: 20260406 | Z61: DEBITO | AA61: 3974527 | AB61: BBVA | AD61: BBVA Plin | AE61: 0.50289352 | AF61: XIAOMI SCHELL
A62: 1023366 | B62: VA | C62: A | D62: 46114 | E62: 46114 | G62: 349 | H62: PS0005 | I62: 6542 | J62: 4133 | L62: 445330******1663 | M62: Nac | N62: COM | O62: 46114 | P62: 124 | Q62: Abonado | R62: 3.58 | S62: 0.73 | T62: 0.13 | U62: 120.29 | V62: 0 | X62: 20260406 | Z62: CREDITO | AA62: 3974527 | AB62: BCP | AE62: 0.50541667 | AF62: XIAOMI SCHELL
A63: 1023366 | B63: VA | C63: A | D63: 46114 | E63: 46114 | G63: 349 | H63: PS0005 | I63: 6544 | J63: 791443 | L63: 455788******4017 | M63: Nac | N63: COM | O63: 46114 | P63: 2998 | Q63: Abonado | R63: 86.64 | S63: 38.67 | T63: 6.96 | U63: 2904.4 | V63: 0 | X63: 20260406 | Z63: DEBITO | AA63: 3974527 | AB63: BCP | AE63: 0.53050926 | AF63: XIAOMI SCHELL
A64: 1023366 | B64: VA | C64: A | D64: 46114 | E64: 46114 | G64: 349 | H64: PS0005 | I64: 6546 | J64: 816512 | L64: 444355******6472 | M64: Nac | N64: COM | O64: 46114 | P64: 89.9 | Q64: Abonado | R64: 2.6 | S64: 1.16 | T64: 0.21 | U64: 87.09 | V64: 0 | X64: 20260406 | Z64: DEBITO | AA64: 3974527 | AB64: BBVA | AE64: 0.54489583 | AF64: XIAOMI SCHELL
A65: 1023366 | B65: VA | C65: A | D65: 46114 | E65: 46114 | G65: 349 | H65: PS0005 | I65: 6548 | J65: 695872 | L65: 421355******4524 | M65: Nac | N65: COM | O65: 46114 | P65: 1954 | Q65: Abonado | R65: 56.47 | S65: 25.21 | T65: 4.54 | U65: 1892.99 | V65: 0 | X65: 20260406 | Z65: DEBITO | AA65: 3974527 | AB65: IBK PRIVADA | AE65: 0.55974537 | AF65: XIAOMI SCHELL
A66: 1023366 | B66: VA | C66: A | D66: 46114 | E66: 46114 | G66: 349 | H66: PS0005 | I66: 6551 | J66: 885811 | L66: 455788******8503 | M66: Nac | N66: COM | O66: 46114 | P66: 40 | Q66: Abonado | R66: 1.16 | S66: 0.52 | T66: 0.09 | U66: 38.75 | V66: 0 | X66: 20260406 | Z66: DEBITO | AA66: 3974527 | AB66: BCP | AE66: 0.5684838 | AF66: XIAOMI SCHELL
A67: 1023366 | B67: VA | C67: A | D67: 46114 | E67: 46114 | G67: 349 | H67: 65656565 | I67: 6553 | J67: 917556 | L67: 455788******4205 | M67: Nac | N67: COM | O67: 46114 | P67: 89 | Q67: Abonado | R67: 2.57 | S67: 1.15 | T67: 0.21 | U67: 86.22 | V67: 0 | X67: 20260406 | Z67: DEBITO | AA67: 3974527 | AB67: BCP | AD67: Yape | AE67: 0.57271991 | AF67: XIAOMI SCHELL
A68: 1023366 | B68: VA | C68: A | D68: 46114 | E68: 46114 | G68: 349 | H68: PS0005 | I68: 6556 | J68: 5020 | L68: 428076******3845 | M68: Nac | N68: COM | O68: 46114 | P68: 1999 | Q68: Abonado | R68: 57.77 | S68: 7.79 | T68: 1.4 | U68: 1939.83 | V68: 0 | X68: 20260406 | Z68: CREDITO | AA68: 3974527 | AB68: BCP | AE68: 0.58158565 | AF68: XIAOMI SCHELL
A69: 1023366 | B69: VA | C69: A | D69: 46114 | E69: 46114 | G69: 349 | H69: PS0005 | I69: 6558 | J69: 4725 | L69: 428082******0287 | M69: Nac | N69: COM | O69: 46114 | P69: 219 | Q69: Abonado | R69: 6.33 | S69: 1.29 | T69: 0.23 | U69: 212.44 | V69: 0 | X69: 20260406 | Z69: CREDITO | AA69: 3974527 | AB69: BCP | AE69: 0.59221065 | AF69: XIAOMI SCHELL
A70: 1023366 | B70: VA | C70: A | D70: 46114 | E70: 46114 | G70: 349 | H70: PS0005 | I70: 6565 | J70: 54710 | L70: 458089******0099 | M70: Ext | N70: COM | O70: 46114 | P70: 86.9 | Q70: Abonado | R70: 3.39 | S70: 1.66 | T70: 0.3 | U70: 83.21 | V70: 0 | X70: 20260406 | Z70: CREDITO | AA70: 3974527 | AB70: VISA INT | AE70: 0.60274306 | AF70: XIAOMI SCHELL
A71: 1023366 | B71: VA | C71: A | D71: 46114 | E71: 46114 | G71: 349 | H71: PS0005 | I71: 6567 | J71: 179755 | L71: 444355******7277 | M71: Nac | N71: COM | O71: 46114 | P71: 89 | Q71: Abonado | R71: 2.57 | S71: 0.52 | T71: 0.09 | U71: 86.34 | V71: 0 | X71: 20260406 | Z71: CREDITO | AA71: 3974527 | AB71: BBVA | AE71: 0.61357639 | AF71: XIAOMI SCHELL
A72: 1023366 | B72: VA | C72: A | D72: 46114 | E72: 46114 | G72: 349 | H72: PS0005 | I72: 6569 | J72: 701441 | L72: 421355******5133 | M72: Nac | N72: COM | O72: 46114 | P72: 149 | Q72: Abonado | R72: 4.31 | S72: 1.93 | T72: 0.35 | U72: 144.34 | V72: 0 | X72: 20260406 | Z72: DEBITO | AA72: 3974527 | AB72: IBK PRIVADA | AE72: 0.61728009 | AF72: XIAOMI SCHELL
A73: 1023366 | B73: VA | C73: A | D73: 46114 | E73: 46114 | G73: 349 | H73: PS0005 | I73: 6571 | J73: 767392 | L73: 421355******5133 | M73: Nac | N73: COM | O73: 46114 | P73: 19.9 | Q73: Abonado | R73: 0.58 | S73: 0.26 | T73: 0.05 | U73: 19.27 | V73: 0 | X73: 20260406 | Z73: DEBITO | AA73: 3974527 | AB73: IBK PRIVADA | AE73: 0.62028935 | AF73: XIAOMI SCHELL
A74: 1023366 | B74: VA | C74: A | D74: 46114 | E74: 46114 | G74: 349 | H74: PS0005 | I74: 6573 | J74: 1440 | L74: 445331******4103 | M74: Nac | N74: COM | O74: 46114 | P74: 159 | Q74: Abonado | R74: 4.6 | S74: 0.94 | T74: 0.17 | U74: 154.23 | V74: 0 | X74: 20260406 | Z74: CREDITO | AA74: 3974527 | AB74: BCP | AE74: 0.62210648 | AF74: XIAOMI SCHELL
A75: 1023366 | B75: VA | C75: A | D75: 46114 | E75: 46114 | G75: 349 | H75: PS0005 | I75: 6575 | J75: 251035 | L75: 455170******3850 | M75: Nac | N75: COM | O75: 46114 | P75: 549 | Q75: Abonado | R75: 15.87 | S75: 7.09 | T75: 1.28 | U75: 531.85 | V75: 0 | X75: 20260406 | Z75: DEBITO | AA75: 3974527 | AB75: BBVA | AE75: 0.62875 | AF75: XIAOMI SCHELL
A76: 1023366 | B76: VA | C76: A | D76: 46114 | E76: 46114 | G76: 349 | H76: PS0005 | I76: 6580 | J76: 344163 | K76: 3 | L76: 491914******6425 | M76: Nac | N76: COM | O76: 46114 | P76: 349 | Q76: Abonado | R76: 16.2 | S76: 2.06 | T76: 0.37 | U76: 332.43 | V76: 0 | X76: 20260406 | Z76: CREDITO | AA76: 3974527 | AB76: BBVA | AC76: SI | AE76: 0.64902778 | AF76: XIAOMI SCHELL
A77: 1023366 | B77: VA | C77: A | D77: 46114 | E77: 46114 | G77: 349 | H77: PS0005 | I77: 6582 | J77: 9210 | L77: 444437******1541 | M77: Nac | N77: COM | O77: 46114 | P77: 179 | Q77: Abonado | R77: 5.17 | S77: 0.69 | T77: 0.12 | U77: 173.71 | V77: 0 | X77: 20260406 | Z77: CREDITO | AA77: 3974527 | AB77: BCP | AE77: 0.65365741 | AF77: XIAOMI SCHELL
A78: 1023366 | B78: VA | C78: A | D78: 46114 | E78: 46114 | G78: 349 | H78: PS0005 | I78: 6590 | J78: 160652 | L78: 455788******9346 | M78: Nac | N78: COM | O78: 46114 | P78: 269 | Q78: Abonado | R78: 7.77 | S78: 3.47 | T78: 0.62 | U78: 260.61 | V78: 0 | X78: 20260406 | Z78: DEBITO | AA78: 3974527 | AB78: BCP | AE78: 0.67828704 | AF78: XIAOMI SCHELL
A79: 1023366 | B79: VA | C79: A | D79: 46114 | E79: 46114 | G79: 349 | H79: PS0005 | I79: 6595 | J79: 171622 | L79: 411539******8357 | M79: Nac | N79: COM | O79: 46114 | P79: 69 | Q79: Abonado | R79: 1.99 | S79: 0.89 | T79: 0.16 | U79: 66.85 | V79: 0 | X79: 20260406 | Z79: DEBITO | AA79: 3974527 | AB79: VISA LOC | AE79: 0.69491898 | AF79: XIAOMI SCHELL
A80: 1023366 | B80: VA | C80: A | D80: 46114 | E80: 46114 | G80: 349 | H80: PS0005 | I80: 6597 | J80: 91598 | L80: 421410******0165 | M80: Nac | N80: COM | O80: 46114 | P80: 105 | Q80: Abonado | R80: 3.03 | S80: 1.35 | T80: 0.24 | U80: 101.73 | V80: 0 | X80: 20260406 | Z80: DEBITO | AA80: 3974527 | AB80: NACION | AE80: 0.69751157 | AF80: XIAOMI SCHELL
A81: 1023366 | B81: VA | C81: A | D81: 46114 | E81: 46114 | G81: 349 | H81: PS0005 | I81: 6599 | J81: 216602 | L81: 491246******2781 | M81: Nac | N81: COM | O81: 46114 | P81: 322 | Q81: Abonado | R81: 9.31 | S81: 2.55 | T81: 0.46 | U81: 312.23 | V81: 0 | X81: 20260406 | Z81: DEBITO | AA81: 3974527 | AB81: BCP | AE81: 0.70299769 | AF81: XIAOMI SCHELL
A82: 1023366 | B82: VA | C82: A | D82: 46114 | E82: 46114 | G82: 349 | H82: PS0005 | I82: 6601 | J82: 3907 | L82: 402161******8256 | M82: Nac | N82: COM | O82: 46114 | P82: 34.9 | Q82: Abonado | R82: 1.01 | S82: 0.28 | T82: 0.05 | U82: 33.84 | V82: 0 | X82: 20260406 | Z82: CREDITO | AA82: 3974527 | AB82: BCP | AE82: 0.70571759 | AF82: XIAOMI SCHELL
A83: 1023366 | B83: VA | C83: A | D83: 46114 | E83: 46114 | G83: 349 | H83: PS0005 | I83: 6603 | J83: 199439 | L83: 455788******5271 | M83: Nac | N83: COM | O83: 46114 | P83: 699 | Q83: Abonado | R83: 20.2 | S83: 9.02 | T83: 1.62 | U83: 677.18 | V83: 0 | X83: 20260406 | Z83: DEBITO | AA83: 3974527 | AB83: BCP | AE83: 0.70733796 | AF83: XIAOMI SCHELL
A84: 1023366 | B84: VA | C84: A | D84: 46114 | E84: 46114 | G84: 349 | H84: PS0005 | I84: 6605 | J84: 607791 | L84: 414791******5091 | M84: Nac | N84: COM | O84: 46114 | P84: 1000 | Q84: Abonado | R84: 28.9 | S84: 5.9 | T84: 1.06 | U84: 970.04 | V84: 0 | X84: 20260406 | Z84: CREDITO | AA84: 3974527 | AB84: BBVA | AE84: 0.70775463 | AF84: XIAOMI SCHELL
A85: 1023366 | B85: VA | C85: A | D85: 46114 | E85: 46114 | G85: 349 | H85: PS0005 | I85: 6607 | J85: 3217 | L85: 428082******1068 | M85: Nac | N85: COM | O85: 46114 | P85: 169 | Q85: Abonado | R85: 4.88 | S85: 0.99 | T85: 0.18 | U85: 163.94 | V85: 0 | X85: 20260406 | Z85: CREDITO | AA85: 3974527 | AB85: BCP | AE85: 0.71659722 | AF85: XIAOMI SCHELL
A86: 1023366 | B86: VA | C86: A | D86: 46114 | E86: 46114 | G86: 349 | H86: PS0005 | I86: 6609 | J86: 213054 | L86: 444697******7078 | M86: Nac | N86: COM | O86: 46114 | P86: 2499 | Q86: Abonado | R86: 72.22 | S86: 32.24 | T86: 5.8 | U86: 2420.98 | V86: 0 | X86: 20260406 | Z86: DEBITO | AA86: 3974527 | AB86: BCP | AE86: 0.72699074 | AF86: XIAOMI SCHELL
A87: 1023366 | B87: VA | C87: A | D87: 46114 | E87: 46114 | G87: 349 | H87: PS0005 | I87: 6613 | J87: 7401 | L87: 428082******2919 | M87: Nac | N87: COM | O87: 46114 | P87: 169 | Q87: Abonado | R87: 4.88 | S87: 0.99 | T87: 0.18 | U87: 163.94 | V87: 0 | X87: 20260406 | Z87: CREDITO | AA87: 3974527 | AB87: BCP | AE87: 0.73322917 | AF87: XIAOMI SCHELL
A88: 1023366 | B88: VA | C88: A | D88: 46114 | E88: 46114 | G88: 349 | H88: PS0005 | I88: 6615 | J88: 198 | L88: 428082******5325 | M88: Nac | N88: COM | O88: 46114 | P88: 1499 | Q88: Abonado | R88: 43.32 | S88: 8.84 | T88: 1.59 | U88: 1454.09 | V88: 0 | X88: 20260406 | Z88: CREDITO | AA88: 3974527 | AB88: BCP | AE88: 0.73646991 | AF88: XIAOMI SCHELL
... A92: 1023366 | B92: VA | C92: A | D92: 46114 | E92: 46114 | G92: 349 | H92: PS0005 | I92: 6624 | J92: 2881 | L92: 428076******7117 | M92: Nac | N92: COM | O92: 46114 | P92: 109 | Q92: Abonado | R92: 3.15 | S92: 0.42 | T92: 0.08 | U92: 105.77 | V92: 0 | X92: 20260406 | Z92: CREDITO | AA92: 3974527 | AB92: BCP | AE92: 0.75107639 | AF92: XIAOMI SCHELL
A93: 1023366 | B93: VA | C93: A | D93: 46114 | E93: 46114 | G93: 349 | H93: PS0005 | I93: 6628 | J93: 914465 | K93: 3 | L93: 444355******7960 | M93: Nac | N93: COM | O93: 46114 | P93: 2450 | Q93: Abonado | R93: 113.69 | S93: 14.46 | T93: 2.6 | U93: 2333.71 | V93: 0 | X93: 20260406 | Z93: CREDITO | AA93: 3974527 | AB93: BBVA | AC93: SI | AE93: 0.77269676 | AF93: XIAOMI SCHELL
A94: 1023366 | B94: VA | C94: A | D94: 46114 | E94: 46114 | G94: 349 | H94: PS0005 | I94: 6630 | J94: 953316 | K94: 3 | L94: 414075******3791 | M94: Nac | N94: COM | O94: 46114 | P94: 1326 | Q94: Abonado | R94: 61.53 | S94: 5.17 | T94: 0.93 | U94: 1263.54 | V94: 0 | X94: 20260406 | Z94: CREDITO | AA94: 3974527 | AB94: BBVA | AC94: SI | AE94: 0.7803125 | AF94: XIAOMI SCHELL
A95: 1023366 | B95: VA | C95: A | D95: 46114 | E95: 46114 | G95: 349 | H95: PS0005 | I95: 6632 | J95: 119246 | L95: 428581******8221 | M95: Nac | N95: COM | O95: 46114 | P95: 350 | Q95: Abonado | R95: 10.12 | S95: 4.52 | T95: 0.81 | U95: 339.07 | V95: 0 | X95: 20260406 | Z95: DEBITO | AA95: 3974527 | AB95: SCOTIABANK | AE95: 0.78372685 | AF95: XIAOMI SCHELL
A96: 1023366 | B96: VA | C96: A | D96: 46114 | E96: 46114 | G96: 349 | H96: PS0005 | I96: 6634 | J96: 521059 | L96: 455696******4012 | M96: Nac | N96: COM | O96: 46114 | P96: 199 | Q96: Abonado | R96: 5.75 | S96: 1.57 | T96: 0.28 | U96: 192.97 | V96: 0 | X96: 20260406 | Z96: CREDITO | AA96: 3974527 | AB96: IBK PRIVADA | AE96: 0.78613426 | AF96: XIAOMI SCHELL
A97: 1023366 | B97: VA | C97: A | D97: 46114 | E97: 46114 | G97: 349 | H97: PS0005 | I97: 6636 | J97: 7937 | L97: 491914******8156 | M97: Nac | N97: COM | O97: 46114 | P97: 17.9 | Q97: Abonado | R97: 0.52 | S97: 0.11 | T97: 0.02 | U97: 17.36 | V97: 0 | X97: 20260406 | Z97: CREDITO | AA97: 3974527 | AB97: BBVA | AE97: 0.7909375 | AF97: XIAOMI SCHELL
A98: 1023366 | B98: VA | C98: A | D98: 46114 | E98: 46114 | G98: 349 | H98: PS0005 | I98: 6638 | J98: 138263 | L98: 444355******0745 | M98: Nac | N98: COM | O98: 46114 | P98: 134 | Q98: Abonado | R98: 3.87 | S98: 1.73 | T98: 0.31 | U98: 129.82 | V98: 0 | X98: 20260406 | Z98: DEBITO | AA98: 3974527 | AB98: BBVA | AE98: 0.81619213 | AF98: XIAOMI SCHELL
A99: 1023366 | B99: VA | C99: A | D99: 46114 | E99: 46114 | G99: 349 | H99: PS0005 | I99: 6643 | J99: 483980 | L99: 455788******9512 | M99: Nac | N99: COM | O99: 46114 | P99: 1282.9 | Q99: Abonado | R99: 37.08 | S99: 16.55 | T99: 2.98 | U99: 1242.84 | V99: 0 | X99: 20260406 | Z99: DEBITO | AA99: 3974527 | AB99: BCP | AE99: 0.82127315 | AF99: XIAOMI SCHELL
A100: 1023366 | B100: VA | C100: A | D100: 46114 | E100: 46114 | G100: 349 | H100: PS0005 | I100: 6645 | J100: 82652 | K100: 2 | L100: 407876******3206 | M100: Nac | N100: COM | O100: 46114 | P100: 1964 | Q100: Abonado | R100: 56.76 | S100: 11.59 | T100: 2.09 | U100: 1905.15 | V100: 0 | X100: 20260406 | Z100: CREDITO | AA100: 3974527 | AB100: BFALABELLA | AC100: NO | AE100: 0.83123843 | AF100: XIAOMI SCHELL
A101: 1023366 | B101: VA | C101: A | D101: 46114 | E101: 46114 | G101: 349 | H101: PS0005 | I101: 6648 | J101: 8236 | L101: 438829******6221 | M101: Nac | N101: COM | O101: 46114 | P101: 55 | Q101: Abonado | R101: 1.59 | S101: 0.43 | T101: 0.08 | U101: 53.33 | V101: 0 | X101: 20260406 | Z101: CREDITO | AA101: 3974527 | AB101: VISA LOC | AE101: 0.83678241 | AF101: XIAOMI SCHELL
A102: 1023366 | B102: VA | C102: A | D102: 46114 | E102: 46114 | G102: 349 | H102: PS0005 | I102: 6650 | J102: 70645 | L102: 422224******0606 | M102: Nac | N102: COM | O102: 46114 | P102: 149 | Q102: Abonado | R102: 4.31 | S102: 0.88 | T102: 0.16 | U102: 144.53 | V102: 0 | X102: 20260406 | Z102: CREDITO | AA102: 3974527 | AB102: IBK PRIVADA | AE102: 0.8381713 | AF102: XIAOMI SCHELL
A103: 1023366 | B103: VA | C103: A | D103: 46114 | E103: 46114 | G103: 349 | H103: PS0005 | I103: 6655 | J103: 721 | L103: 445330******0512 | M103: Nac | N103: COM | O103: 46114 | P103: 1388 | Q103: Abonado | R103: 40.11 | S103: 8.19 | T103: 1.47 | U103: 1346.42 | V103: 0 | X103: 20260406 | Z103: CREDITO | AA103: 3974527 | AB103: BCP | AE103: 0.8396412 | AF103: XIAOMI SCHELL
...

Sheet AMEX
A1: Codigo | B1: Producto | C1: Tipo_Mov | D1: Fecha_Proceso | E1: Fecha_Lote | F1: Lote_Manual | G1: Lote_Pos | H1: Terminal | I1: Voucher | J1: Autorizacion | K1: Cuotas | L1: Tarjeta | M1: Origen | N1: Transaccion | O1: Fecha_Consumo | P1: Importe | Q1: Comision | R1: Comision_Merchant | S1: IGV | T1: Neto_Parcial | U1: Neto_Total | V1: Fecha_Abono | W1: Observaciones | AE1: VALIDACION DE DEPOSITOS
A2: 1023366 | C2: A | D2: 46111 | E2: 46111 | G2: 346 | H2: PS0005 | I2: 6177 | J2: 340273 | L2: 377752*****8733 | N2: COMPRA | O2: 46111 | P2: 59 | Q2: 2.35 | R2: 0.47 | S2: 0.08 | T2: 56.57 | U2: 0 | V2: 20260401 | Z2: Etiquetas de fila | AA2: Suma de Importe | AC2: 104107 | AD2: 318.93 | AE2: 8224818 | AF2: 06/04/2026 | AG2: 0
A3: 1023366 | C3: A | D3: 46111 | E3: 46111 | G3: 346 | H3: PS0005 | I3: 6241 | J3: 505968 | L3: 377754*****5358 | N3: COMPRA | O3: 46111 | P3: 149 | Q3: 5.95 | R3: 1.19 | S3: 0.21 | T3: 142.84 | U3: 0 | V3: 20260401 | Z3: 46111 | AA3: 208 | AC3: 104107 | AD3: 20061.3 | AE3: 8224819 | AF3: 06/04/2026 | AG3: 0
A4: 1023366 | C4: C | D4: 46111 | E4: 46111 | F4: 9996 | N4: S.E.A. | O4: 46111 | P4: 0 | Q4: -5 | R4: -5 | S4: -0.9 | T4: -5.9 | U4: 0 | V4: 20260401 | W4: Descuento Pendiente | Z4: 46112 | AA4: 115.48
A5: 1023366 | C5: A | D5: 46111 | P5: 0 | Q5: 0 | R5: 0 | S5: 0 | T5: -5.9 | U5: 193.51 | V5: 20260401 | W5: Descuentos Aplicados | Z5: 46113 | AA5: 2971 | AD5: 104107 | AE5: =+U5 -> 193.51 | AF5: =_xlfn.XLOOKUP(AE5,Bancos!H:H,Bancos!C:C) -> 8001422 | AG5: =_xlfn.XLOOKUP(AF5,Bancos!C:C,Bancos!A:A) -> 01/04/2026 | AH5: =+AG5-V5 -> -20214288
A6: 1023366 | C6: A | D6: 46112 | E6: 46112 | G6: 347 | H6: PS0005 | I6: 6326 | J6: 115978 | L6: 377754*****6766 | N6: COMPRA | O6: 46112 | P6: 115.48 | Q6: 4.61 | R6: 0.92 | S6: 0.17 | T6: 110.7 | U6: 110.7 | V6: 20260402 | Z6: 46115 | AA6: 632.1
A7: 1023366 | C7: A | D7: 46113 | E7: 46113 | G7: 348 | H7: PS0005 | I7: 6391 | J7: 472355 | L7: 377897*****7570 | N7: COMPRA | O7: 46113 | P7: 298 | Q7: 11.89 | R7: 2.38 | S7: 0.43 | T7: 285.68 | U7: 0 | V7: 20260407 | Z7: 46116 | AA7: 1537
A8: 1023366 | C8: A | D8: 46113 | E8: 46113 | G8: 348 | H8: PS0005 | I8: 6405 | J8: 362363 | L8: 377934*****9121 | N8: COMPRA | O8: 46113 | P8: 536 | Q8: 21.39 | R8: 4.28 | S8: 0.77 | T8: 513.84 | U8: 0 | V8: 20260407 | Z8: 46117 | AA8: 149 | AD8: 104107 | AE8: =+U8 -> 0 | AF8: =_xlfn.XLOOKUP(AE8,Bancos!H:H,Bancos!C:C) -> #N/A | AG8: =_xlfn.XLOOKUP(AF8,Bancos!C:C,Bancos!A:A) -> #N/A | AH8: =+AG8-V8 -> #N/A
A9: 1023366 | C9: A | D9: 46113 | E9: 46113 | G9: 348 | H9: PS0005 | I9: 6409 | J9: 474474 | L9: 377754*****9574 | N9: COMPRA | O9: 46113 | P9: 159 | Q9: 6.34 | R9: 1.27 | S9: 0.23 | T9: 152.43 | U9: 0 | V9: 20260407 | Z9: 46118 | AA9: 2437
A10: 1023366 | C10: A | D10: 46113 | E10: 46113 | G10: 348 | H10: PS0005 | I10: 6457 | J10: 892497 | L10: 377898*****4669 | N10: COMPRA | O10: 46113 | P10: 1978 | Q10: 78.92 | R10: 15.78 | S10: 2.84 | T10: 1896.24 | U10: 2848.19 | V10: 20260407 | Z10: 46119 | AA10: 549
A11: 1023366 | C11: A | D11: 46115 | E11: 46115 | G11: 350 | H11: PS0005 | I11: 6695 | J11: 181364 | L11: 377752*****3042 | N11: COMPRA | O11: 46115 | P11: 139 | Q11: 5.55 | R11: 1.11 | S11: 0.2 | T11: 133.25 | U11: 0 | V11: 20260407 | Z11: 46120 | AA11: 269 | AD11: 104107 | AE11: =+U11 -> 0 | AF11: =_xlfn.XLOOKUP(AE11,Bancos!H:H,Bancos!C:C) -> #N/A | AG11: =_xlfn.XLOOKUP(AF11,Bancos!C:C,Bancos!A:A) -> #N/A | AH11: =+AG11-V11 -> #N/A
A12: 1023366 | C12: A | D12: 46115 | E12: 46115 | G12: 350 | H12: PS0005 | I12: 6729 | J12: 523862 | L12: 377934*****1628 | N12: COMPRA | O12: 46115 | P12: 224.1 | Q12: 8.94 | R12: 1.79 | S12: 0.32 | T12: 214.84 | U12: 0 | V12: 20260407 | Z12: (en blanco) | AA12: 0 | AD12: 104107 | AE12: =+U12 -> 0 | AF12: =_xlfn.XLOOKUP(AE12,Bancos!H:H,Bancos!C:C) -> #N/A | AG12: =_xlfn.XLOOKUP(AF12,Bancos!C:C,Bancos!A:A) -> #N/A | AH12: =+AG12-V12 -> #N/A
A13: 1023366 | C13: A | D13: 46115 | E13: 46115 | G13: 350 | H13: PS0005 | I13: 6735 | J13: 470758 | L13: 377752*****7034 | N13: COMPRA | O13: 46115 | P13: 269 | Q13: 10.73 | R13: 2.15 | S13: 0.39 | T13: 257.88 | U13: 605.97 | V13: 20260407 | Z13: 46121 | AA13: 69
A14: 1023366 | C14: A | D14: 46116 | E14: 46116 | G14: 351 | H14: PS0005 | I14: 6779 | J14: 564657 | L14: 377934*****8500 | N14: COMPRA | O14: 46116 | P14: 79 | Q14: 3.15 | R14: 0.63 | S14: 0.11 | T14: 75.74 | U14: 0 | V14: 20260407 | Z14: 46122 | AA14: 1768
A15: 1023366 | C15: A | D15: 46116 | E15: 46116 | G15: 351 | H15: PS0005 | I15: 6803 | J15: 593726 | L15: 377892*****4091 | N15: COMPRA | O15: 46116 | P15: 159 | Q15: 6.34 | R15: 1.27 | S15: 0.23 | T15: 152.43 | U15: 0 | V15: 20260407 | Z15: 46124 | AA15: 105
A16: 1023366 | C16: A | D16: 46116 | E16: 46116 | G16: 351 | H16: PS0005 | I16: 6818 | J16: 524864 | L16: 377934*****7945 | N16: COMPRA | O16: 46116 | P16: 1299 | Q16: 51.83 | R16: 10.37 | S16: 1.87 | T16: 1245.3 | U16: 1473.47 | V16: 20260407 | Z16: 46125 | AA16: 159 | AD16: 104107 | AE16: =+U16 -> 1473.47 | AF16: =_xlfn.XLOOKUP(AE16,Bancos!H:H,Bancos!C:C) -> 8002676 | AG16: =_xlfn.XLOOKUP(AF16,Bancos!C:C,Bancos!A:A) -> 07/04/2026 | AH16: =+AG16-V16 -> -20214288
A17: 1023366 | C17: A | D17: 46117 | E17: 46117 | G17: 352 | H17: PS0005 | I17: 6967 | J17: 361778 | L17: 377934*****5142 | N17: COMPRA | O17: 46117 | P17: 149 | Q17: 5.95 | R17: 1.19 | S17: 0.21 | T17: 142.84 | U17: 142.84 | V17: 20260407 | Z17: 46127 | AA17: 298 | AD17: 104107 | AE17: =+U17 -> 142.84 | AF17: =_xlfn.XLOOKUP(AE17,Bancos!H:H,Bancos!C:C) -> 8002677 | AG17: =_xlfn.XLOOKUP(AF17,Bancos!C:C,Bancos!A:A) -> 07/04/2026 | AH17: =+AG17-V17 -> -20214288
A18: 1023366 | C18: A | D18: 46118 | E18: 46118 | G18: 353 | H18: PS0005 | I18: 7046 | J18: 541161 | L18: 377934*****2685 | N18: COMPRA | O18: 46118 | P18: 1547 | Q18: 61.73 | R18: 12.35 | S18: 2.22 | T18: 1483.05 | U18: 0 | V18: 20260408 | Z18: 46128 | AA18: 243 | AD18: 104107 | AE18: =+U18 -> 0 | AF18: 8000955 | AG18: =_xlfn.XLOOKUP(AF18,Bancos!C:C,Bancos!A:A) -> 10/04/2026 | AH18: =+AG18-V18 -> -20214286
A19: 1023366 | C19: A | D19: 46118 | E19: 46118 | G19: 353 | H19: PS0005 | I19: 7048 | J19: 560361 | L19: 377934*****2685 | N19: COMPRA | O19: 46118 | P19: 249 | Q19: 9.94 | R19: 1.99 | S19: 0.36 | T19: 238.7 | U19: 0 | V19: 20260408 | Z19: 46129 | AA19: 49
A20: 1023366 | C20: A | D20: 46118 | E20: 46118 | G20: 353 | H20: PS0005 | I20: 7053 | J20: 270761 | K20: 2 | L20: 377754*****8110 | N20: COMPRA | O20: 46118 | P20: 55 | Q20: 2.19 | R20: 0.44 | S20: 0.08 | T20: 52.73 | U20: 0 | V20: 20260408 | Z20: 46130 | AA20: 2137.9
A21: 1023366 | C21: A | D21: 46118 | E21: 46118 | G21: 353 | H21: PS0005 | I21: 7077 | J21: 544665 | L21: 377934*****3743 | N21: COMPRA | O21: 46118 | P21: 586 | Q21: 23.38 | R21: 4.68 | S21: 0.84 | T21: 561.78 | U21: 2336.26 | V21: 20260408 | Z21: 46131 | AA21: 189
A22: 1023366 | C22: A | D22: 46119 | E22: 46119 | G22: 354 | H22: PS0005 | I22: 7121 | J22: 82568 | L22: 377752*****9701 | N22: COMPRA | O22: 46119 | P22: 549 | Q22: 21.91 | R22: 4.38 | S22: 0.79 | T22: 526.3 | U22: 526.3 | V22: 20260409 | Z22: 46132 | AA22: 69
A23: 1023366 | C23: A | D23: 46120 | E23: 46120 | G23: 355 | H23: PS0005 | I23: 7251 | J23: 421180 | L23: 377934*****9425 | N23: COMPRA | O23: 46120 | P23: 269 | Q23: 10.73 | R23: 2.15 | S23: 0.39 | T23: 257.88 | U23: 257.88 | V23: 20260410 | Z23: 46133 | AA23: 17.9
A24: 1023366 | C24: A | D24: 46121 | E24: 46121 | G24: 356 | H24: PS0005 | I24: 7320 | J24: 431859 | L24: 377752*****3405 | N24: COMPRA | O24: 46121 | P24: 69 | Q24: 2.75 | R24: 0.55 | S24: 0.1 | T24: 66.15 | U24: 66.15 | V24: 20260411 | Z24: 46135 | AA24: 178
A25: 1023366 | C25: A | D25: 46122 | E25: 46122 | G25: 357 | H25: PS0005 | I25: 7434 | J25: 441774 | L25: 377934*****3942 | N25: COMPRA | O25: 46122 | P25: 69 | Q25: 2.75 | R25: 0.55 | S25: 0.1 | T25: 66.15 | U25: 0 | V25: 20260414 | Z25: 46136 | AA25: 408
A26: 1023366 | C26: A | D26: 46122 | E26: 46122 | G26: 357 | H26: PS0005 | I26: 7439 | J26: 819740 | L26: 377934*****3942 | N26: COMPRA | O26: 46122 | P26: 1699 | Q26: 67.79 | R26: 13.56 | S26: 2.44 | T26: 1628.77 | U26: 1694.92 | V26: 20260414 | Z26: 46137 | AA26: 1448
A27: 1023366 | C27: A | D27: 46124 | E27: 46124 | G27: 359 | H27: PS0005 | I27: 7631 | J27: 976921 | L27: 377890*****1783 | N27: COMPRA | O27: 46124 | P27: 105 | Q27: 4.19 | R27: 0.84 | S27: 0.15 | T27: 100.66 | U27: 100.66 | V27: 20260414 | Z27: 46139 | AA27: 567
A28: 1023366 | C28: A | D28: 46125 | E28: 46125 | G28: 360 | H28: PS0005 | I28: 7736 | J28: 427368 | L28: 377898*****4530 | N28: COMPRA | O28: 46125 | P28: 159 | Q28: 6.34 | R28: 1.27 | S28: 0.23 | T28: 152.43 | U28: 152.43 | V28: 20260415 | Z28: 46140 | AA28: 207
A29: 1023366 | C29: A | D29: 46127 | E29: 46127 | G29: 362 | H29: PS0005 | I29: 7860 | J29: 887943 | L29: 377890*****8249 | N29: COMPRA | O29: 46127 | P29: 298 | Q29: 11.89 | R29: 2.38 | S29: 0.43 | T29: 285.68 | U29: 285.68 | V29: 20260417 | Z29: Total general | AA29: 16780.38
A30: 1023366 | C30: A | D30: 46128 | E30: 46128 | G30: 363 | H30: PS0005 | I30: 7988 | J30: 290373 | L30: 377753*****9672 | N30: COMPRA | O30: 46128 | P30: 154 | Q30: 6.14 | R30: 1.23 | S30: 0.22 | T30: 147.64 | U30: 0 | V30: 20260418
A31: 1023366 | C31: A | D31: 46128 | E31: 46128 | G31: 363 | H31: PS0005 | I31: 7990 | J31: 304673 | L31: 377753*****9672 | N31: COMPRA | O31: 46128 | P31: 89 | Q31: 3.55 | R31: 0.71 | S31: 0.13 | T31: 85.32 | U31: 232.96 | V31: 20260418
A32: 1023366 | C32: A | D32: 46129 | E32: 46129 | G32: 364 | H32: PS0005 | I32: 8085 | J32: 312468 | L32: 377754*****6761 | N32: COMPRA | O32: 46129 | P32: 49 | Q32: 1.96 | R32: 0.39 | S32: 0.07 | T32: 46.97 | U32: 46.97 | V32: 20260421
A33: 1023366 | C33: A | D33: 46130 | E33: 46130 | G33: 665 | H33: PS0003 | I33: 9188 | J33: 134868 | L33: 377934*****5626 | N33: COMPRA | O33: 46130 | P33: 450 | Q33: 17.96 | R33: 3.59 | S33: 0.65 | T33: 431.39 | U33: 0 | V33: 20260421
A34: 1023366 | C34: A | D34: 46130 | E34: 46130 | G34: 365 | H34: PS0005 | I34: 8202 | J34: 182273 | L34: 377753*****6689 | N34: COMPRA | O34: 46130 | P34: 1598 | Q34: 63.76 | R34: 12.75 | S34: 2.3 | T34: 1531.94 | U34: 0 | V34: 20260421
A35: 1023366 | C35: A | D35: 46130 | E35: 46130 | G35: 365 | H35: PS0005 | I35: 8224 | J35: 309386 | L35: 377897*****7768 | N35: COMPRA | O35: 46130 | P35: 89.9 | Q35: 3.59 | R35: 0.72 | S35: 0.13 | T35: 86.18 | U35: 2049.51 | V35: 20260421
A36: 1023366 | C36: A | D36: 46131 | E36: 46131 | G36: 366 | H36: PS0005 | I36: 8284 | J36: 359652 | L36: 377890*****1400 | N36: COMPRA | O36: 46131 | P36: 189 | Q36: 7.54 | R36: 1.51 | S36: 0.27 | T36: 181.19 | U36: 181.19 | V36: 20260421
A37: 1023366 | C37: A | D37: 46132 | E37: 46132 | G37: 367 | H37: PS0005 | I37: 8426 | J37: 463362 | L37: 377934*****9752 | N37: COMPRA | O37: 46132 | P37: 69 | Q37: 2.75 | R37: 0.55 | S37: 0.1 | T37: 66.15 | U37: 66.15 | V37: 20260422
A38: 1023366 | C38: A | D38: 46133 | E38: 46133 | G38: 368 | H38: PS0005 | I38: 8491 | J38: 560760 | L38: 377890*****8735 | N38: COMPRA | O38: 46133 | P38: 17.9 | Q38: 0.71 | R38: 0.14 | S38: 0.03 | T38: 17.16 | U38: 17.16 | V38: 20260423
A39: 1023366 | C39: A | D39: 46135 | E39: 46135 | G39: 370 | H39: PS0005 | I39: 8630 | J39: 395464 | L39: 377934*****8638 | N39: COMPRA | O39: 46135 | P39: 178 | Q39: 7.1 | R39: 1.42 | S39: 0.26 | T39: 170.64 | U39: 170.64 | V39: 20260425
A40: 1023366 | C40: A | D40: 46136 | E40: 46136 | G40: 371 | H40: PS0005 | I40: 8796 | J40: 532965 | L40: 377752*****5644 | N40: COMPRA | O40: 46136 | P40: 408 | Q40: 16.28 | R40: 3.26 | S40: 0.59 | T40: 391.13 | U40: 391.13 | V40: 20260428
A41: 1023366 | C41: A | D41: 46137 | E41: 46137 | G41: 372 | H41: PS0005 | I41: 8836 | J41: 352486 | L41: 377890*****4050 | N41: COMPRA | O41: 46137 | P41: 1399 | Q41: 55.82 | R41: 11.16 | S41: 2.01 | T41: 1341.17 | U41: 0 | V41: 20260428
... A45: 1023366 | C45: A | D45: 46140 | E45: 46140 | G45: 375 | H45: PS0005 | I45: 9131 | J45: 513373 | L45: 377934*****2797 | N45: COMPRA | O45: 46140 | P45: 207 | Q45: 8.26 | R45: 1.65 | S45: 0.3 | T45: 198.44 | U45: 198.44 | V45: 20260430

Sheet Bancos
A1: Fecha de operación | B1: Fecha de proceso | C1: Nro. de operación | D1: Movimiento | E1: Descripción | F1: Canal | G1: Cargo | H1: Abono | L1: F. Operación | M1: F. Valor | N1: Código | O1: Nº. Doc. | P1: Concepto | Q1: Importe | R1: Oficina
A2: 08/04/2026 | B2: 08/04/2026 | C2: 8014234 | D2: PAGO PMP | E2: 001023366 | F2: INTERNO | H2: 18246.3 | L2: 46113 | M2: 46113 | N2: 118 | O2: 0000338475 | P2: R20100118760DINERS CLUB PERU | Q2: 256.11 | R2: 0814
A3: 08/04/2026 | B3: 08/04/2026 | C3: 8014233 | D3: PAGO PMP | E3: 001023366 | F3: INTERNO | H3: 1753.22 | L3: 46113 | M3: 46113 | N3: 118 | O3: 0000338472 | P3: R20100118760DINERS CLUB PERU | Q3: 431.71 | R3: 0814
A4: 07/04/2026 | B4: 07/04/2026 | C4: 8061392 | D4: PAGO PMP | E4: 001023366 | F4: INTERNO | H4: 14136.73 | L4: 46113 | M4: 46113 | N4: 118 | O4: 0000338487 | P4: R20100118760DINERS CLUB PERU | Q4: 447.55 | R4: 0814
A5: 07/04/2026 | B5: 07/04/2026 | C5: 8061391 | D5: PAGO PMP | E5: 001023366 | F5: INTERNO | H5: 422.19 | L5: 46113 | M5: 46113 | N5: 118 | O5: 0000338478 | P5: R20100118760DINERS CLUB PERU | Q5: 554.9 | R5: 0814
A6: 06/04/2026 | B6: 06/04/2026 | C6: 8224821 | D6: PAGO PMP | E6: 001023366 | F6: INTERNO | H6: 28523.09 | L6: 46113 | M6: 46113 | N6: 118 | O6: 0000338485 | P6: R20100118760DINERS CLUB PERU | Q6: 1179.5 | R6: 0814
A7: 06/04/2026 | B7: 06/04/2026 | C7: 8224826 | D7: PAGO PMP | E7: 001023366 | F7: INTERNO | H7: 21024.16 | L7: 46113 | M7: 46113 | N7: 118 | O7: 0000338481 | P7: R20100118760DINERS CLUB PERU | Q7: 1648.99 | R7: 0814
A8: 06/04/2026 | B8: 06/04/2026 | C8: 8224819 | D8: PAGO PMP | E8: 001023366 | F8: INTERNO | H8: 20061.3 | L8: 46113 | M8: 46113 | N8: 118 | O8: 0000338479 | P8: R20100118760DINERS CLUB PERU | Q8: 2138.27 | R8: 0814
A9: 06/04/2026 | B9: 06/04/2026 | C9: 8224829 | D9: PAGO PMP | E9: 001023366 | F9: INTERNO | H9: 14463.68 | L9: 46113 | M9: 46113 | N9: 118 | O9: 0000338476 | P9: R20100118760DINERS CLUB PERU | Q9: 2805.64 | R9: 0814
A10: 06/04/2026 | B10: 06/04/2026 | C10: 8224824 | D10: PAGO PMP | E10: 001023366 | F10: INTERNO | H10: 9582.85 | L10: 46113 | M10: 46113 | N10: 118 | O10: 0000338473 | P10: R20100118760DINERS CLUB PERU | Q10: 2994.41 | R10: 0814
A11: 06/04/2026 | B11: 06/04/2026 | C11: 8224825 | D11: PAGO PMP | E11: 001023366 | F11: INTERNO | H11: 4849.17 | L11: 46113 | M11: 46113 | N11: 118 | O11: 0000338483 | P11: R20100118760DINERS CLUB PERU | Q11: 3233.72 | R11: 0814
A12: 06/04/2026 | B12: 06/04/2026 | C12: 8224827 | D12: PAGO PMP | E12: 001023366 | F12: INTERNO | H12: 1744.45 | L12: 46113 | M12: 46113 | N12: 118 | O12: 0000338488 | P12: R20100118760DINERS CLUB PERU | Q12: 3823.96 | R12: 0814
A13: 06/04/2026 | B13: 06/04/2026 | C13: 8224828 | D13: PAGO PMP | E13: 001023366 | F13: INTERNO | H13: 1338.33 | L13: 46118 | M13: 46118 | N13: 118 | O13: 0000339061 | P13: R20100118760DINERS CLUB PERU | Q13: 86.69 | R13: 0814
... A27: 10/04/2026 | B27: 10/04/2026 | C27: 8012514 | D27: PAGO PMP | E27: 001023366 | F27: INTERNO | H27: 152.14 | L27: 46118 | M27: 46118 | N27: 118 | O27: 0000339054 | P27: R20100118760DINERS CLUB PERU | Q27: 857.1 | R27: 0814
A28: Fecha de operación | B28: Fecha de proceso | C28: Nro. de operación | D28: Movimiento | E28: Descripción | F28: Canal | G28: Cargo | H28: Abono | L28: 46118 | M28: 46118 | N28: 118 | O28: 0000339032 | P28: R20100118760DINERS CLUB PERU | Q28: 857.1 | R28: 0814
A29: 08/04/2026 | B29: 08/04/2026 | C29: 8000662 | D29: PAGO ESTABLECIMENTOS | E29: AMEX | F29: WEB | H29: 2336.26 | L29: 46118 | M29: 46118 | N29: 118 | O29: 0000339048 | P29: R20100118760DINERS CLUB PERU | Q29: 904.76 | R29: 0814
A30: 07/04/2026 | B30: 07/04/2026 | C30: 8009720 | D30: PAGO ESTABLECIMENTOS | E30: AMEX | F30: WEB | H30: 4595.83 | L30: 46118 | M30: 46118 | N30: 118 | O30: 0000339051 | P30: R20100118760DINERS CLUB PERU | Q30: 953.39 | R30: 0814
A31: 07/04/2026 | B31: 07/04/2026 | C31: 8009719 | D31: PAGO ESTABLECIMENTOS | E31: AMEX | F31: WEB | H31: 3174.13 | L31: 46118 | M31: 46118 | N31: 118 | O31: 0000339013 | P31: R20100118760DINERS CLUB PERU | Q31: 1414.25 | R31: 0814
A32: 07/04/2026 | B32: 07/04/2026 | C32: 8002921 | D32: PAGO ESTABLECIMENTOS | E32: AMEX | F32: WEB | H32: 3158.78 | L32: 46118 | M32: 46118 | N32: 118 | O32: 0000339038 | P32: R20100118760DINERS CLUB PERU | Q32: 1525.37 | R32: 0814
A33: 07/04/2026 | B33: 07/04/2026 | C33: 8002674 | D33: PAGO ESTABLECIMENTOS | E33: AMEX | F33: WEB | H33: 2848.19 | L33: 46118 | M33: 46118 | N33: 118 | O33: 0000339021 | P33: R20100118760DINERS CLUB PERU | Q33: 1616.18 | R33: 0814
A34: 07/04/2026 | B34: 07/04/2026 | C34: 8009721 | D34: PAGO ESTABLECIMENTOS | E34: AMEX | F34: WEB | H34: 2064.86 | L34: 46118 | M34: 46118 | N34: 118 | O34: 0000339023 | P34: R20100118760DINERS CLUB PERU | Q34: 1638.14 | R34: 0814
A35: 07/04/2026 | B35: 07/04/2026 | C35: 8002920 | D35: PAGO ESTABLECIMENTOS | E35: AMEX | F35: WEB | H35: 1724.64 | L35: 46118 | M35: 46118 | N35: 118 | O35: 0000339040 | P35: R20100118760DINERS CLUB PERU | Q35: 1642.23 | R35: 0814
A36: 07/04/2026 | B36: 07/04/2026 | C36: 8002676 | D36: PAGO ESTABLECIMENTOS | E36: AMEX | F36: WEB | H36: 1473.47 | L36: 46118 | M36: 46118 | N36: 118 | O36: 0000339019 | P36: R20100118760DINERS CLUB PERU | Q36: 1654.89 | R36: 0814
A37: 07/04/2026 | B37: 07/04/2026 | C37: 8002675 | D37: PAGO ESTABLECIMENTOS | E37: AMEX | F37: WEB | H37: 605.97 | L37: 46118 | M37: 46118 | N37: 118 | O37: 0000339028 | P37: R20100118760DINERS CLUB PERU | Q37: 1752.3 | R37: 0814
A38: 07/04/2026 | B38: 07/04/2026 | C38: 8009724 | D38: PAGO ESTABLECIMENTOS | E38: AMEX | F38: WEB | H38: 597.1 | L38: 46118 | M38: 46118 | N38: 118 | O38: 0000339043 | P38: R20100118760DINERS CLUB PERU | Q38: 1994.83 | R38: 0814
A39: 07/04/2026 | B39: 07/04/2026 | C39: 8009723 | D39: PAGO ESTABLECIMENTOS | E39: AMEX | F39: WEB | H39: 410.07 | L39: 46118 | M39: 46118 | N39: 118 | O39: 0000339017 | P39: R20100118760DINERS CLUB PERU | Q39: 2190.89 | R39: 0814
A40: 07/04/2026 | B40: 07/04/2026 | C40: 8002919 | D40: PAGO ESTABLECIMENTOS | E40: AMEX | F40: WEB | H40: 334.57 | L40: 46118 | M40: 46118 | N40: 118 | O40: 0000339033 | P40: R20100118760DINERS CLUB PERU | Q40: 2194.27 | R40: 0814
... A52: 10/04/2026 | B52: 10/04/2026 | C52: 8000955 | D52: PAGO ESTABLECIMENTOS | E52: AMEX | F52: WEB | H52: 257.88 | L52: 46119 | M52: 46119 | N52: 118 | O52: 0000339333 | P52: R20100118760DINERS CLUB PERU | Q52: 170.66 | R52: 0814
L53: 46119 | M53: 46119 | N53: 118 | O53: 0000339319 | P53: R20100118760DINERS CLUB PERU | Q53: 218.32 | R53: 0814
L54: 46119 | M54: 46119 | N54: 118 | O54: 0000339326 | P54: R20100118760DINERS CLUB PERU | Q54: 223.05 | R54: 0814
L55: 46119 | M55: 46119 | N55: 118 | O55: 0000339325 | P55: R20100118760DINERS CLUB PERU | Q55: 256.46 | R55: 0814
L56: 46119 | M56: 46119 | N56: 118 | O56: 0000339323 | P56: R20100118760DINERS CLUB PERU | Q56: 523.41 | R56: 0814
L57: 46119 | M57: 46119 | N57: 118 | O57: 0000339327 | P57: R20100118760DINERS CLUB PERU | Q57: 859.84 | R57: 0814
L58: 46119 | M58: 46119 | N58: 118 | O58: 0000339328 | P58: R20100118760DINERS CLUB PERU | Q58: 1237.5 | R58: 0814
L59: 46119 | M59: 46119 | N59: 118 | O59: 0000339331 | P59: R20100118760DINERS CLUB PERU | Q59: 1414.83 | R59: 0814
L60: 46120 | M60: 46120 | N60: 118 | O60: 0000339538 | P60: R20100118760DINERS CLUB PERU | Q60: 599.68 | R60: 0814
L61: 46120 | M61: 46120 | N61: 118 | O61: 0000339541 | P61: R20100118760DINERS CLUB PERU | Q61: 714.08 | R61: 0814
L62: 46120 | M62: 46120 | N62: 118 | O62: 0000339531 | P62: R20100118760DINERS CLUB PERU | Q62: 961.01 | R62: 0814
L63: 46120 | M63: 46120 | N63: 118 | O63: 0000339539 | P63: R20100118760DINERS CLUB PERU | Q63: 1264.3 | R63: 0814
L64: 46120 | M64: 46120 | N64: 118 | O64: 0000339534 | P64: R20100118760DINERS CLUB PERU | Q64: 1429.13 | R64: 0814
... L76: 46121 | M76: 46121 | N76: 118 | O76: 0000339808 | P76: R20100118760DINERS CLUB PERU | Q76: 2024.05 | R76: 0814

Sheet DINERS
A1: Código de comercio | B1: Nombre del comercio | C1: Red | D1: Origen | E1: Tipo de transacción | F1: Fecha de recepción | G1: Fecha de proceso | H1: Marca | I1: N° de tarjeta | J1: Tipo de tarjeta | K1: Código de autorización | L1: Orden de pago | M1: Moneda | N1: Fecha de ticket | O1: N° ticket | P1: Estado de ticket | Q1: N° de cuotas | R1: Plazo de pago | S1: Fecha de pago | T1: Tipo de comisión | U1: Valor de comisión | V1: Importe del consumo | W1: Comisión del consumo | X1: IGV del consumo | Y1: Importe neto de pago | Z1: Producto
A2: 1001299773 | B2: XIAOMI SCHELL | C2: IZIPAY | E2: CONSUMO | F2: 01-05-2026 | G2: 01-05-2026 | H2: DINERS | I2: **** ****** 1866 | J2: LOCAL | K2: 043082 | L2: 2605030016368559 | M2: SOLES | N2: 46142 | O2: 0009325 | P2: PENDIENTE | Q2: 0 | R2: 2 días | S2: 03-05-2026 | T2: PORCENTUAL | U2: 2.2 | V2: 159 | W2: 3.5 | X2: 0.63 | Y2: 154.87 | Z2: CONSUMOS CORRIENTES
A3: 1001299773 | B3: XIAOMI SCHELL | C3: IZIPAY | E3: CONSUMO | F3: 29-04-2026 | G3: 29-04-2026 | H3: DINERS | I3: **** ****** 8785 | J3: LOCAL | K3: 092942 | L3: 2605020016319026 | M3: SOLES | N3: 46140 | O3: 0009142 | P3: PENDIENTE | Q3: 0 | R3: 3 días | S3: 02-05-2026 | T3: PORCENTUAL | U3: 2.2 | V3: 229 | W3: 5.04 | X3: 0.91 | Y3: 223.05 | Z3: CONSUMOS CORRIENTES
A4: 1001299773 | B4: XIAOMI SCHELL | C4: IZIPAY | E4: CONSUMO | F4: 28-04-2026 | G4: 28-04-2026 | H4: DINERS | I4: **** ****** 9792 | J4: LOCAL | K4: 090611 | L4: 2604300016308275 | M4: SOLES | N4: 46139 | O4: 0009058 | P4: PROCESADO | Q4: 3 | R4: 2 días | S4: 30-04-2026 | T4: PORCENTUAL | U4: 3.95 | V4: 899 | W4: 35.51 | X4: 6.39 | Y4: 857.1 | Z4: CUOTAS SIN INTERESES
A5: 1001299773 | B5: XIAOMI SCHELL | C5: IZIPAY | E5: CONSUMO | F5: 28-04-2026 | G5: 28-04-2026 | H5: DINERS | I5: **** ****** 2654 | J5: LOCAL | K5: 067205 | L5: 2604300016308275 | M5: SOLES | N5: 46139 | O5: 0009101 | P5: PROCESADO | Q5: 2 | R5: 2 días | S5: 30-04-2026 | T5: PORCENTUAL | U5: 3.95 | V5: 139 | W5: 5.49 | X5: 0.99 | Y5: 132.52 | Z5: CUOTAS SIN INTERESES
A6: 1001299773 | B6: XIAOMI SCHELL | C6: IZIPAY | E6: CONSUMO | F6: 27-04-2026 | G6: 27-04-2026 | H6: DINERS | I6: **** ****** 7244 | J6: LOCAL | K6: 061928 | L6: 2604290016296904 | M6: SOLES | N6: 46138 | O6: 0008949 | P6: PROCESADO | Q6: 3 | R6: 2 días | S6: 29-04-2026 | T6: PORCENTUAL | U6: 3.95 | V6: 299 | W6: 11.81 | X6: 2.13 | Y6: 285.06 | Z6: CUOTAS SIN INTERESES
A7: 1001299773 | B7: XIAOMI SCHELL | C7: IZIPAY | E7: CONSUMO | F7: 26-04-2026 | G7: 26-04-2026 | H7: DINERS | I7: **** ****** 1931 | J7: LOCAL | K7: 092653 | L7: 2604280016282816 | M7: SOLES | N7: 46137 | O7: 0008848 | P7: PROCESADO | Q7: 3 | R7: 2 días | S7: 28-04-2026 | T7: PORCENTUAL | U7: 3.95 | V7: 259 | W7: 10.23 | X7: 1.84 | Y7: 246.93 | Z7: CUOTAS SIN INTERESES
A8: 1001299773 | B8: XIAOMI SCHELL | C8: IZIPAY | E8: CONSUMO | F8: 26-04-2026 | G8: 26-04-2026 | H8: DINERS | I8: **** ****** 5951 | J8: LOCAL | K8: 004055 | L8: 2604280016282816 | M8: SOLES | N8: 46137 | O8: 0008852 | P8: PROCESADO | Q8: 0 | R8: 2 días | S8: 28-04-2026 | T8: PORCENTUAL | U8: 2.2 | V8: 35 | W8: 0.77 | X8: 0.14 | Y8: 34.09 | Z8: CONSUMOS CORRIENTES
A9: 1001299773 | B9: XIAOMI SCHELL | C9: IZIPAY | E9: CONSUMO | F9: 26-04-2026 | G9: 26-04-2026 | H9: DINERS | I9: **** ****** 8937 | J9: LOCAL | K9: 019113 | L9: 2604280016282816 | M9: SOLES | N9: 46137 | O9: 0008860 | P9: PROCESADO | Q9: 3 | R9: 2 días | S9: 28-04-2026 | T9: PORCENTUAL | U9: 3.95 | V9: 229 | W9: 9.05 | X9: 1.63 | Y9: 218.32 | Z9: CUOTAS SIN INTERESES
A10: 1001299773 | B10: XIAOMI SCHELL | C10: IZIPAY | E10: CONSUMO | F10: 26-04-2026 | G10: 26-04-2026 | H10: DINERS | I10: **** ****** 5615 | J10: LOCAL | K10: 045960 | L10: 2604280016282816 | M10: SOLES | N10: 46137 | O10: 0008903 | P10: PROCESADO | Q10: 3 | R10: 2 días | S10: 28-04-2026 | T10: PORCENTUAL | U10: 3.95 | V10: 1699 | W10: 67.11 | X10: 12.08 | Y10: 1619.81 | Z10: CUOTAS SIN INTERESES
A11: 1001299773 | B11: XIAOMI SCHELL | C11: IZIPAY | D11: POS CHIP | E11: CONSUMO | F11: 22-04-2026 | G11: 22-04-2026 | H11: DINERS | I11: **** ****** 4544 | J11: LOCAL | K11: 013287 | L11: 2604240016238292 | M11: SOLES | N11: 46133 | O11: 0008475 | P11: PROCESADO | Q11: 2 | R11: 2 días | S11: 24-04-2026 | T11: PORCENTUAL | U11: 3.95 | V11: 1399 | W11: 55.26 | X11: 9.95 | Y11: 1333.79 | Z11: CUOTAS SIN INTERESES
A12: 1001299773 | B12: XIAOMI SCHELL | C12: IZIPAY | E12: CONSUMO | F12: 21-04-2026 | G12: 21-04-2026 | H12: DINERS | I12: **** ****** 5384 | J12: LOCAL | K12: 014888 | L12: 2604230016227197 | M12: SOLES | N12: 46132 | O12: 0008390 | P12: PROCESADO | Q12: 3 | R12: 2 días | S12: 23-04-2026 | T12: PORCENTUAL | U12: 3.95 | V12: 849 | W12: 33.54 | X12: 6.04 | Y12: 809.42 | Z12: CUOTAS SIN INTERESES
A13: 1001299773 | B13: XIAOMI SCHELL | C13: IZIPAY | E13: CONSUMO | F13: 20-04-2026 | G13: 20-04-2026 | H13: DINERS | I13: **** ****** 5503 | J13: LOCAL | K13: 052548 | L13: 2604220016215255 | M13: SOLES | N13: 46131 | O13: 0008274 | P13: PROCESADO | Q13: 3 | R13: 2 días | S13: 22-04-2026 | T13: PORCENTUAL | U13: 3.95 | V13: 89 | W13: 3.52 | X13: 0.63 | Y13: 84.85 | Z13: CUOTAS SIN INTERESES
A14: 1001299773 | B14: XIAOMI SCHELL | C14: IZIPAY | E14: CONSUMO | F14: 20-04-2026 | G14: 20-04-2026 | H14: DINERS | I14: **** ****** 1209 | J14: LOCAL | K14: 021661 | L14: 2604220016215255 | M14: SOLES | N14: 46131 | O14: 0008335 | P14: PROCESADO | Q14: 3 | R14: 2 días | S14: 22-04-2026 | T14: PORCENTUAL | U14: 3.95 | V14: 89 | W14: 3.52 | X14: 0.63 | Y14: 84.85 | Z14: CUOTAS SIN INTERESES
A15: 1001299773 | B15: XIAOMI SCHELL | C15: IZIPAY | E15: CONSUMO | F15: 19-04-2026 | G15: 19-04-2026 | H15: DINERS | I15: **** ****** 1770 | J15: LOCAL | K15: 072948 | L15: 2604210016201646 | M15: SOLES | N15: 46130 | O15: 0008167 | P15: PROCESADO | Q15: 3 | R15: 2 días | S15: 21-04-2026 | T15: PORCENTUAL | U15: 3.95 | V15: 108.9 | W15: 4.3 | X15: 0.77 | Y15: 103.83 | Z15: CUOTAS SIN INTERESES
A16: 1001299773 | B16: XIAOMI SCHELL | C16: IZIPAY | E16: CONSUMO | F16: 17-04-2026 | G16: 17-04-2026 | H16: DINERS | I16: **** ****** 7203 | J16: LOCAL | K16: 091025 | L16: 2604190016179109 | M16: SOLES | N16: 46128 | O16: 0007976 | P16: PROCESADO | Q16: 3 | R16: 2 días | S16: 20-04-2026 | T16: PORCENTUAL | U16: 3.95 | V16: 1299 | W16: 51.31 | X16: 9.24 | Y16: 1238.45 | Z16: CUOTAS SIN INTERESES
A17: 1001299773 | B17: XIAOMI SCHELL | C17: IZIPAY | E17: CONSUMO | F17: 14-04-2026 | G17: 14-04-2026 | H17: DINERS | I17: **** ****** 4202 | J17: LOCAL | K17: 049755 | L17: 2604160016146799 | M17: SOLES | N17: 46125 | O17: 0007719 | P17: PROCESADO | Q17: 3 | R17: 2 días | S17: 16-04-2026 | T17: PORCENTUAL | U17: 3.95 | V17: 1008 | W17: 39.82 | X17: 7.17 | Y17: 961.01 | Z17: CUOTAS SIN INTERESES
A18: 1001299773 | B18: XIAOMI SCHELL | C18: IZIPAY | E18: CONSUMO | F18: 11-04-2026 | G18: 11-04-2026 | H18: DINERS | I18: **** ****** 0449 | J18: LOCAL | K18: 068396 | L18: 2604130016110779 | M18: SOLES | N18: 46122 | O18: 0007441 | P18: PROCESADO | Q18: 0 | R18: 2 días | S18: 13-04-2026 | T18: PORCENTUAL | U18: 2.2 | V18: 53 | W18: 1.17 | X18: 0.21 | Y18: 51.62 | Z18: CONSUMOS CORRIENTES
A19: 1001299773 | B19: XIAOMI SCHELL | C19: IZIPAY | E19: CONSUMO | F19: 07-04-2026 | G19: 07-04-2026 | H19: DINERS | I19: **** ****** 0205 | J19: LOCAL | K19: 088125 | L19: 2604090016067585 | M19: SOLES | N19: 46118 | O19: 0007069 | P19: PROCESADO | Q19: 3 | R19: 2 días | S19: 09-04-2026 | T19: PORCENTUAL | U19: 3.95 | V19: 1799 | W19: 71.06 | X19: 12.79 | Y19: 1715.15 | Z19: CUOTAS SIN INTERESES
A20: 1001299773 | B20: XIAOMI SCHELL | C20: IZIPAY | E20: CONSUMO | F20: 06-04-2026 | G20: 06-04-2026 | H20: DINERS | I20: **** ****** 1781 | J20: LOCAL | K20: 037610 | L20: 2604080016055852 | M20: SOLES | N20: 46117 | O20: 0006965 | P20: PROCESADO | Q20: 3 | R20: 2 días | S20: 08-04-2026 | T20: PORCENTUAL | U20: 3.95 | V20: 1008 | W20: 39.82 | X20: 7.17 | Y20: 961.01 | Z20: CUOTAS SIN INTERESES
A21: 1001299773 | B21: XIAOMI SCHELL | C21: IZIPAY | E21: CONSUMO | F21: 04-04-2026 | G21: 04-04-2026 | H21: DINERS | I21: **** ****** 8450 | J21: LOCAL | K21: 071528 | L21: 2604060016032224 | M21: SOLES | N21: 46115 | O21: 0006706 | P21: PROCESADO | Q21: 3 | R21: 2 días | S21: 06-04-2026 | T21: PORCENTUAL | U21: 3.95 | V21: 209 | W21: 8.26 | X21: 1.49 | Y21: 199.25 | Z21: CUOTAS SIN INTERESES
A22: 1001299773 | B22: XIAOMI SCHELL | C22: IZIPAY | E22: CONSUMO | F22: 04-04-2026 | G22: 04-04-2026 | H22: DINERS | I22: **** ****** 3101 | J22: LOCAL | K22: 095454 | L22: 2604060016032224 | M22: SOLES | N22: 46115 | O22: 0006722 | P22: PROCESADO | Q22: 0 | R22: 2 días | S22: 06-04-2026 | T22: PORCENTUAL | U22: 2.2 | V22: 199 | W22: 4.38 | X22: 0.79 | Y22: 193.83 | Z22: CONSUMOS CORRIENTES
A23: 1001299773 | B23: XIAOMI SCHELL | C23: IZIPAY | E23: CONSUMO | F23: 02-04-2026 | G23: 02-04-2026 | H23: DINERS | I23: **** ****** 5694 | J23: LOCAL | K23: 070632 | L23: 2604040015965002 | M23: SOLES | N23: 46113 | O23: 0006472 | P23: PROCESADO | Q23: 3 | R23: 2 días | S23: 06-04-2026 | T23: PORCENTUAL | U23: 3.95 | V23: 1199 | W23: 47.36 | X23: 8.52 | Y23: 1143.12 | Z23: CUOTAS SIN INTERESES
A24: 1001299773 | B24: XIAOMI SCHELL | C24: IZIPAY | E24: CONSUMO | F24: 02-04-2026 | G24: 02-04-2026 | H24: DINERS | I24: **** ****** 1190 | J24: LOCAL | K24: 011266 | L24: 2604040015965002 | M24: SOLES | N24: 46113 | O24: 0006499 | P24: PROCESADO | Q24: 3 | R24: 2 días | S24: 06-04-2026 | T24: PORCENTUAL | U24: 3.95 | V24: 54.9 | W24: 2.17 | X24: 0.39 | Y24: 52.34 | Z24: CUOTAS SIN INTERESES
B41: Etiquetas de fila | C41: Suma de Importe del consumo
B42: 46142 | C42: 159
B43: 46140 | C43: 229
B44: 46139 | C44: 1038
B45: 46138 | C45: 299
B46: 46137 | C46: 2222
B47: 46133 | C47: 1399
B48: 46132 | C48: 849
B49: 46131 | C49: 178
B50: 46130 | C50: 108.9
B51: 46128 | C51: 1299
B52: 46125 | C52: 1008
B53: 46122 | C53: 53
... B57: 46113 | C57: 1253.9
B58: Total general | C58: 13310.8

Sheet Diners Pagos
A1: Codigo de comercio | B1: Nombre del comercio | C1: Red | D1: Orden de pago | E1: Moneda de pago | F1: Fecha de pago programada | G1: Fecha de pago efectivo | H1: Importe total de consumos | I1: Comisiones cobradas | J1: IGV | K1: Cargo | L1: Ajustes | M1: Importe neto de pago | N1: Retención | O1: Importe total de abono | P1: Estado del pago | Q1: Pago efectivo | R1: Documento autorizado | S1: Banco | T1: Tipo de cuenta | U1: N° Cuenta bancaria
A2: 1001299773 | B2: XIAOMI SCHELL | C2: IZIPAY | D2: 2604090016067585 | E2: SOLES | F2: 09-04-2026 | G2: 09-04-2026 | H2: 1799 | I2: 71.06 | J2: 12.79 | K2: 0 | L2: 0 | M2: 1715.15 | N2: 0 | O2: 1715.15 | P2: PAGADO | Q2: 09-04-2026 | R2: - | S2: BANCO CONTINENTAL | T2: CORRIENTE | U2: 0616050100012617
A3: 1001299773 | B3: XIAOMI SCHELL | C3: IZIPAY | D3: 2604080016055852 | E3: SOLES | F3: 08-04-2026 | G3: 08-04-2026 | H3: 1008 | I3: 39.82 | J3: 7.17 | K3: 0 | L3: 0 | M3: 961.01 | N3: 0 | O3: 961.01 | P3: PAGADO | Q3: 08-04-2026 | R3: - | S3: BANCO CONTINENTAL | T3: CORRIENTE | U3: 0616050100012617
A4: 1001299773 | B4: XIAOMI SCHELL | C4: IZIPAY | D4: 2604040015965002 | E4: SOLES | F4: 06-04-2026 | G4: 06-04-2026 | H4: 1691.9 | I4: 59.17 | J4: 10.65 | K4: 5.9 | L4: 0 | M4: 1616.18 | N4: 0 | O4: 1616.18 | P4: PAGADO | Q4: 06-04-2026 | R4: - | S4: BANCO CONTINENTAL | T4: CORRIENTE | U4: 0616050100012617
H7: =SUM(H2:H6) -> 4498.9
