Workbook

Sheet SAP
A1: FECHA | B1: ID TIENDA | C1: NOMBRE | D1: TOTAL VENTA | E1: VISA | F1: EFECTIVO | G1: MASTERCARD | H1: AMERICAN EXPRESS | I1: DINERS | J1: LUKITA (BBVA) | K1: TUNKY (INTERBANK) | L1: WALI (INTERBANK) | M1: YAPE (BCP) | N1: MILLAS INTERBANK | O1: PUNTOS VIDA (BBVA) | P1: TRANSFERENCIA MALVITEC | Q1: RAPPI | R1: ADELANTO (PRE-VENTA) | S1: YAPE (BCP) - 2 | T1: YAPE (BCP) - 3 | U1: SANTANDER | V1: MIS CUOTAS | W1: CUOTEALO | X1: POWERPAY | Y1: CÁLIDDA | Z1: NOTA CREDITO | AA1: TOTAL
A2: 46113 | B2: HARM.01 | C2: MODULO HONOR AREQUIPA | D2: 5591.9 | E2: 0 | F2: 0 | G2: 5591.9 | H2: 0 | I2: 0 | J2: 0 | K2: 0 | L2: 0 | M2: 0 | N2: 0 | O2: 0 | P2: 0 | Q2: 0 | R2: 0 | S2: 0 | T2: 0 | U2: 0 | V2: 0 | W2: 0 | X2: 0 | Y2: 0 | Z2: 0 | AA2: 11183.8
A3: 46114 | B3: HARM.01 | C3: MODULO HONOR AREQUIPA | D3: 6723 | E3: 0 | F3: 1098 | G3: 5325 | H3: 0 | I3: 0 | J3: 0 | K3: 0 | L3: 0 | M3: 0 | N3: 0 | O3: 0 | P3: 0 | Q3: 0 | R3: 0 | S3: 0 | T3: 0 | U3: 0 | V3: 300 | W3: 0 | X3: 0 | Y3: 0 | Z3: 0 | AA3: 12348
A4: 46115 | B4: HARM.01 | C4: MODULO HONOR AREQUIPA | D4: 608 | E4: 0 | F4: 459 | G4: 149 | H4: 0 | I4: 0 | J4: 0 | K4: 0 | L4: 0 | M4: 0 | N4: 0 | O4: 0 | P4: 0 | Q4: 0 | R4: 0 | S4: 0 | T4: 0 | U4: 0 | V4: 0 | W4: 0 | X4: 0 | Y4: 0 | Z4: 0 | AA4: 757
A5: 46116 | B5: HARM.01 | C5: MODULO HONOR AREQUIPA | D5: 10380 | E5: 0 | F5: 89 | G5: 10291 | H5: 0 | I5: 0 | J5: 0 | K5: 0 | L5: 0 | M5: 0 | N5: 0 | O5: 0 | P5: 0 | Q5: 0 | R5: 0 | S5: 0 | T5: 0 | U5: 0 | V5: 0 | W5: 0 | X5: 0 | Y5: 0 | Z5: 0 | AA5: 20671
A6: 46117 | B6: HARM.01 | C6: MODULO HONOR AREQUIPA | D6: 3166 | E6: 0 | F6: 1000 | G6: 2166 | H6: 0 | I6: 0 | J6: 0 | K6: 0 | L6: 0 | M6: 0 | N6: 0 | O6: 0 | P6: 0 | Q6: 0 | R6: 0 | S6: 0 | T6: 0 | U6: 0 | V6: 0 | W6: 0 | X6: 0 | Y6: 0 | Z6: 0 | AA6: 5332
A7: 46118 | B7: HARM.01 | C7: MODULO HONOR AREQUIPA | D7: 3475 | E7: 0 | F7: 629 | G7: 2846 | H7: 0 | I7: 0 | J7: 0 | K7: 0 | L7: 0 | M7: 0 | N7: 0 | O7: 0 | P7: 0 | Q7: 0 | R7: 0 | S7: 0 | T7: 0 | U7: 0 | V7: 0 | W7: 0 | X7: 0 | Y7: 0 | Z7: 0 | AA7: 6321
A8: 46119 | B8: HARM.01 | C8: MODULO HONOR AREQUIPA | D8: 3366 | E8: 0 | F8: 1079 | G8: 2287 | H8: 0 | I8: 0 | J8: 0 | K8: 0 | L8: 0 | M8: 0 | N8: 0 | O8: 0 | P8: 0 | Q8: 0 | R8: 0 | S8: 0 | T8: 0 | U8: 0 | V8: 0 | W8: 0 | X8: 0 | Y8: 0 | Z8: 0 | AA8: 5653
A9: 46120 | B9: HARM.01 | C9: MODULO HONOR AREQUIPA | D9: 1524 | E9: 0 | F9: 1027 | G9: 355.25 | H9: 0 | I9: 0 | J9: 0 | K9: 0 | L9: 0 | M9: 0 | N9: 0 | O9: 0 | P9: 0 | Q9: 0 | R9: 0 | S9: 0 | T9: 0 | U9: 0 | V9: 141.75 | W9: 0 | X9: 0 | Y9: 0 | Z9: 0 | AA9: 2021
A10: 46121 | B10: HARM.01 | C10: MODULO HONOR AREQUIPA | D10: 2727 | E10: 0 | F10: 949 | G10: 1778 | H10: 0 | I10: 0 | J10: 0 | K10: 0 | L10: 0 | M10: 0 | N10: 0 | O10: 0 | P10: 0 | Q10: 0 | R10: 0 | S10: 0 | T10: 0 | U10: 0 | V10: 0 | W10: 0 | X10: 0 | Y10: 0 | Z10: 0 | AA10: 4505
A11: 46122 | B11: HARM.01 | C11: MODULO HONOR AREQUIPA | D11: 4259 | E11: 0 | F11: 1424 | G11: 2535 | H11: 0 | I11: 0 | J11: 0 | K11: 0 | L11: 0 | M11: 0 | N11: 0 | O11: 0 | P11: 0 | Q11: 0 | R11: 0 | S11: 0 | T11: 0 | U11: 0 | V11: 300 | W11: 0 | X11: 0 | Y11: 0 | Z11: 0 | AA11: 7094
A12: 46123 | B12: HARM.01 | C12: MODULO HONOR AREQUIPA | D12: 5963 | E12: 0 | F12: 1238 | G12: 3316.9 | H12: 0 | I12: 149 | J12: 0 | K12: 0 | L12: 0 | M12: 0 | N12: 0 | O12: 0 | P12: 0 | Q12: 0 | R12: 0 | S12: 0 | T12: 0 | U12: 0 | V12: 1259.1 | W12: 0 | X12: 0 | Y12: 0 | Z12: 0 | AA12: 10688
A13: 46124 | B13: HARM.01 | C13: MODULO HONOR AREQUIPA | D13: 7632 | E13: 0 | F13: 1279 | G13: 6353 | H13: 0 | I13: 0 | J13: 0 | K13: 0 | L13: 0 | M13: 0 | N13: 0 | O13: 0 | P13: 0 | Q13: 0 | R13: 0 | S13: 0 | T13: 0 | U13: 0 | V13: 0 | W13: 0 | X13: 0 | Y13: 0 | Z13: 0 | AA13: 13985
... A31: 46142 | B31: HARM.01 | C31: MODULO HONOR AREQUIPA | D31: 3445 | E31: 0 | F31: 515 | G31: 1130.9 | H31: 0 | I31: 0 | J31: 0 | K31: 0 | L31: 0 | M31: 0 | N31: 0 | O31: 0 | P31: 0 | Q31: 0 | R31: 0 | S31: 0 | T31: 0 | U31: 0 | V31: 1799.1 | W31: 0 | X31: 0 | Y31: 0 | Z31: 0 | AA31: 6375

Sheet REPORTE
A1: FECHA | B1: ID TIENDA | C1: NOMBRE | D1: TOTAL VENTA | E1: VISA | F1: EFECTIVO | G1: DIFERENCIA | H1: MASTERCAD | I1: DIFERENCIA | J1: AMERICAN EXPRESS | K1: DIFERENCIA | L1: DINNERS | M1: DIFERENCIA | N1: LUKITA (BBVA) | O1: TUNKY (INTERBANK) | P1: WALI (INTERBANK) | Q1: YAPE (BCP) | R1: MILLAS INTERBANK | S1: PUNTOS VIDA (BBVA) | T1: TRANSFERENCIA MALVITEC | U1: RAPPI | V1: ADELANTO (PRE-VENTA) | W1: YAPE (BCP) - 2 | X1: YAPE (BCP) - 3 | Y1: SANTANDER | Z1: MIS CUOTAS | AA1: CÁLIDDA | AB1: CUOTEALO | AC1: TOTAL | AD1: NOTA CREDITO
A2: =+SAP!A2 -> 46113 | B2: =+SAP!B2 -> HARM.01 | C2: =+SAP!C2 -> MODULO HONOR AREQUIPA | D2: =+SAP!D2 -> 5591.9 | E2: =+SAP!E2 -> 0 | F2: =+SAP!F2 -> 0 | G2: =+F2-EFECTIVO!C9 -> 0 | H2: =+SAP!G2 -> 5591.9 | I2: =+H2-MC!AP2 -> 0 | J2: =+SAP!H2 -> 0 | K2: =+J2-AMEX!AG2 -> 0 | L2: =+SAP!I2 -> 0 | M2: =+L2-DINNERS!AG2 -> 0 | N2: =+SAP!J2 -> 0 | O2: =+SAP!K2 -> 0 | P2: =+SAP!L2 -> 0 | Q2: =+SAP!M2 -> 0 | R2: =+SAP!N2 -> 0 | S2: =+SAP!O2 -> 0 | T2: =+SAP!P2 -> 0 | U2: =+SAP!Q2 -> 0 | ... AD2: =+SAP!Z2 -> 0
A3: =+SAP!A3 -> 46114 | B3: =+SAP!B3 -> HARM.01 | C3: =+SAP!C3 -> MODULO HONOR AREQUIPA | D3: =+SAP!D3 -> 6723 | E3: =+SAP!E3 -> 0 | F3: =+SAP!F3 -> 1098 | G3: =+F3-EFECTIVO!C10 -> 0 | H3: =+SAP!G3 -> 5325 | I3: =+H3-MC!AP3 -> 0 | J3: =+SAP!H3 -> 0 | K3: =+J3-AMEX!AG3 -> 0 | L3: =+SAP!I3 -> 0 | M3: =+L3-DINNERS!AG3 -> 0 | N3: =+SAP!J3 -> 0 | O3: =+SAP!K3 -> 0 | P3: =+SAP!L3 -> 0 | Q3: =+SAP!M3 -> 0 | R3: =+SAP!N3 -> 0 | S3: =+SAP!O3 -> 0 | T3: =+SAP!P3 -> 0 | U3: =+SAP!Q3 -> 0 | ... AD3: =+SAP!Z3 -> 0
A4: =+SAP!A4 -> 46115 | B4: =+SAP!B4 -> HARM.01 | C4: =+SAP!C4 -> MODULO HONOR AREQUIPA | D4: =+SAP!D4 -> 608 | E4: =+SAP!E4 -> 0 | F4: =+SAP!F4 -> 459 | G4: =+F4-EFECTIVO!C11 -> 0 | H4: =+SAP!G4 -> 149 | I4: =+H4-MC!AP4 -> 0 | J4: =+SAP!H4 -> 0 | K4: =+J4-AMEX!AG4 -> 0 | L4: =+SAP!I4 -> 0 | M4: =+L4-DINNERS!AG4 -> 0 | N4: =+SAP!J4 -> 0 | O4: =+SAP!K4 -> 0 | P4: =+SAP!L4 -> 0 | Q4: =+SAP!M4 -> 0 | R4: =+SAP!N4 -> 0 | S4: =+SAP!O4 -> 0 | T4: =+SAP!P4 -> 0 | U4: =+SAP!Q4 -> 0 | ... AD4: =+SAP!Z4 -> 0
A5: =+SAP!A5 -> 46116 | B5: =+SAP!B5 -> HARM.01 | C5: =+SAP!C5 -> MODULO HONOR AREQUIPA | D5: =+SAP!D5 -> 10380 | E5: =+SAP!E5 -> 0 | F5: =+SAP!F5 -> 89 | G5: =+F5-EFECTIVO!C12 -> 0 | H5: =+SAP!G5 -> 10291 | I5: =+H5-MC!AP5 -> 0 | J5: =+SAP!H5 -> 0 | K5: =+J5-AMEX!AG5 -> 0 | L5: =+SAP!I5 -> 0 | M5: =+L5-DINNERS!AG5 -> 0 | N5: =+SAP!J5 -> 0 | O5: =+SAP!K5 -> 0 | P5: =+SAP!L5 -> 0 | Q5: =+SAP!M5 -> 0 | R5: =+SAP!N5 -> 0 | S5: =+SAP!O5 -> 0 | T5: =+SAP!P5 -> 0 | U5: =+SAP!Q5 -> 0 | ... AD5: =+SAP!Z5 -> 0
A6: =+SAP!A6 -> 46117 | B6: =+SAP!B6 -> HARM.01 | C6: =+SAP!C6 -> MODULO HONOR AREQUIPA | D6: =+SAP!D6 -> 3166 | E6: =+SAP!E6 -> 0 | F6: =+SAP!F6 -> 1000 | G6: =+F6-EFECTIVO!C13 -> 0 | H6: =+SAP!G6 -> 2166 | I6: =+H6-MC!AP6 -> 0 | J6: =+SAP!H6 -> 0 | K6: =+J6-AMEX!AG6 -> 0 | L6: =+SAP!I6 -> 0 | M6: =+L6-DINNERS!AG6 -> 0 | N6: =+SAP!J6 -> 0 | O6: =+SAP!K6 -> 0 | P6: =+SAP!L6 -> 0 | Q6: =+SAP!M6 -> 0 | R6: =+SAP!N6 -> 0 | S6: =+SAP!O6 -> 0 | T6: =+SAP!P6 -> 0 | U6: =+SAP!Q6 -> 0 | ... AD6: =+SAP!Z6 -> 0
A7: =+SAP!A7 -> 46118 | B7: =+SAP!B7 -> HARM.01 | C7: =+SAP!C7 -> MODULO HONOR AREQUIPA | D7: =+SAP!D7 -> 3475 | E7: =+SAP!E7 -> 0 | F7: =+SAP!F7 -> 629 | G7: =+F7-EFECTIVO!C14 -> 0 | H7: =+SAP!G7 -> 2846 | I7: =+H7-MC!AP7 -> 0 | J7: =+SAP!H7 -> 0 | K7: =+J7-AMEX!AG7 -> 0 | L7: =+SAP!I7 -> 0 | M7: =+L7-DINNERS!AG7 -> 0 | N7: =+SAP!J7 -> 0 | O7: =+SAP!K7 -> 0 | P7: =+SAP!L7 -> 0 | Q7: =+SAP!M7 -> 0 | R7: =+SAP!N7 -> 0 | S7: =+SAP!O7 -> 0 | T7: =+SAP!P7 -> 0 | U7: =+SAP!Q7 -> 0 | ... AD7: =+SAP!Z7 -> 0
A8: =+SAP!A8 -> 46119 | B8: =+SAP!B8 -> HARM.01 | C8: =+SAP!C8 -> MODULO HONOR AREQUIPA | D8: =+SAP!D8 -> 3366 | E8: =+SAP!E8 -> 0 | F8: =+SAP!F8 -> 1079 | G8: =+F8-EFECTIVO!C15 -> 0 | H8: =+SAP!G8 -> 2287 | I8: =+H8-MC!AP8 -> 0 | J8: =+SAP!H8 -> 0 | K8: =+J8-AMEX!AG8 -> 0 | L8: =+SAP!I8 -> 0 | M8: =+L8-DINNERS!AG8 -> 0 | N8: =+SAP!J8 -> 0 | O8: =+SAP!K8 -> 0 | P8: =+SAP!L8 -> 0 | Q8: =+SAP!M8 -> 0 | R8: =+SAP!N8 -> 0 | S8: =+SAP!O8 -> 0 | T8: =+SAP!P8 -> 0 | U8: =+SAP!Q8 -> 0 | ... AD8: =+SAP!Z8 -> 0
A9: =+SAP!A9 -> 46120 | B9: =+SAP!B9 -> HARM.01 | C9: =+SAP!C9 -> MODULO HONOR AREQUIPA | D9: =+SAP!D9 -> 1524 | E9: =+SAP!E9 -> 0 | F9: =+SAP!F9 -> 1027 | G9: =+F9-EFECTIVO!C16 -> 0 | H9: =+SAP!G9 -> 355.25 | I9: =+H9-MC!AP9 -> 0 | J9: =+SAP!H9 -> 0 | K9: =+J9-AMEX!AG9 -> 0 | L9: =+SAP!I9 -> 0 | M9: =+L9-DINNERS!AG9 -> 0 | N9: =+SAP!J9 -> 0 | O9: =+SAP!K9 -> 0 | P9: =+SAP!L9 -> 0 | Q9: =+SAP!M9 -> 0 | R9: =+SAP!N9 -> 0 | S9: =+SAP!O9 -> 0 | T9: =+SAP!P9 -> 0 | U9: =+SAP!Q9 -> 0 | ... AD9: =+SAP!Z9 -> 0
A10: =+SAP!A10 -> 46121 | B10: =+SAP!B10 -> HARM.01 | C10: =+SAP!C10 -> MODULO HONOR AREQUIPA | D10: =+SAP!D10 -> 2727 | E10: =+SAP!E10 -> 0 | F10: =+SAP!F10 -> 949 | G10: =+F10-EFECTIVO!C17 -> 0 | H10: =+SAP!G10 -> 1778 | I10: =+H10-MC!AP10 -> 0 | J10: =+SAP!H10 -> 0 | K10: =+J10-AMEX!AG10 -> 0 | L10: =+SAP!I10 -> 0 | M10: =+L10-DINNERS!AG10 -> 0 | N10: =+SAP!J10 -> 0 | O10: =+SAP!K10 -> 0 | P10: =+SAP!L10 -> 0 | Q10: =+SAP!M10 -> 0 | R10: =+SAP!N10 -> 0 | S10: =+SAP!O10 -> 0 | T10: =+SAP!P10 -> 0 | U10: =+SAP!Q10 -> 0 | ... AD10: =+SAP!Z10 -> 0
A11: =+SAP!A11 -> 46122 | B11: =+SAP!B11 -> HARM.01 | C11: =+SAP!C11 -> MODULO HONOR AREQUIPA | D11: =+SAP!D11 -> 4259 | E11: =+SAP!E11 -> 0 | F11: =+SAP!F11 -> 1424 | G11: =+F11-EFECTIVO!C18 -> 0 | H11: =+SAP!G11 -> 2535 | I11: =+H11-MC!AP11 -> 0 | J11: =+SAP!H11 -> 0 | K11: =+J11-AMEX!AG11 -> 0 | L11: =+SAP!I11 -> 0 | M11: =+L11-DINNERS!AG11 -> 0 | N11: =+SAP!J11 -> 0 | O11: =+SAP!K11 -> 0 | P11: =+SAP!L11 -> 0 | Q11: =+SAP!M11 -> 0 | R11: =+SAP!N11 -> 0 | S11: =+SAP!O11 -> 0 | T11: =+SAP!P11 -> 0 | U11: =+SAP!Q11 -> 0 | ... AD11: =+SAP!Z11 -> 0
A12: =+SAP!A12 -> 46123 | B12: =+SAP!B12 -> HARM.01 | C12: =+SAP!C12 -> MODULO HONOR AREQUIPA | D12: =+SAP!D12 -> 5963 | E12: =+SAP!E12 -> 0 | F12: =+SAP!F12 -> 1238 | G12: =+F12-EFECTIVO!C19 -> 0 | H12: =+SAP!G12 -> 3316.9 | I12: =+H12-MC!AP12 -> 0 | J12: =+SAP!H12 -> 0 | K12: =+J12-AMEX!AG12 -> 0 | L12: =+SAP!I12 -> 149 | M12: =+L12-DINNERS!AG12 -> 0 | N12: =+SAP!J12 -> 0 | O12: =+SAP!K12 -> 0 | P12: =+SAP!L12 -> 0 | Q12: =+SAP!M12 -> 0 | R12: =+SAP!N12 -> 0 | S12: =+SAP!O12 -> 0 | T12: =+SAP!P12 -> 0 | U12: =+SAP!Q12 -> 0 | ... AD12: =+SAP!Z12 -> 0
A13: =+SAP!A13 -> 46124 | B13: =+SAP!B13 -> HARM.01 | C13: =+SAP!C13 -> MODULO HONOR AREQUIPA | D13: =+SAP!D13 -> 7632 | E13: =+SAP!E13 -> 0 | F13: =+SAP!F13 -> 1279 | G13: =+F13-EFECTIVO!C20 -> 0 | H13: =+SAP!G13 -> 6353 | I13: =+H13-MC!AP13 -> 0 | J13: =+SAP!H13 -> 0 | K13: =+J13-AMEX!AG13 -> 0 | L13: =+SAP!I13 -> 0 | M13: =+L13-DINNERS!AG13 -> 0 | N13: =+SAP!J13 -> 0 | O13: =+SAP!K13 -> 0 | P13: =+SAP!L13 -> 0 | Q13: =+SAP!M13 -> 0 | R13: =+SAP!N13 -> 0 | S13: =+SAP!O13 -> 0 | T13: =+SAP!P13 -> 0 | U13: =+SAP!Q13 -> 0 | ... AD13: =+SAP!Z13 -> 0
... A32: =+SAP!A32 -> 0 | B32: =+SAP!B32 -> 0 | C32: =+SAP!C32 -> 0 | D32: =+SAP!D32 -> 0 | E32: =+SAP!E32 -> 0 | F32: =+SAP!F32 -> 0 | G32: =+F32-EFECTIVO!C39 -> 0 | H32: =+SAP!G32 -> 0 | I32: =+H32-MC!AP32 -> 0 | J32: =+SAP!H32 -> 0 | K32: =+J32-AMEX!AG32 -> 0 | L32: =+SAP!I32 -> 0 | M32: =+L32-DINNERS!AG32 -> 0 | N32: =+SAP!J32 -> 0 | O32: =+SAP!K32 -> 0 | P32: =+SAP!L32 -> 0 | Q32: =+SAP!M32 -> 0 | R32: =+SAP!N32 -> 0 | S32: =+SAP!O32 -> 0 | T32: =+SAP!P32 -> 0 | U32: =+SAP!Q32 -> 0 | ... AD32: =+SAP!Z32 -> 0

Sheet EFECTIVO
E4: codigo comercio: | F4: 1044162
B8: FECHA | C8: EFECTIVO | H8: DIFERENCIA | I8: BANCO | J8: ESTADO | K8: CONTAB. | M8: FECHA | N8: EFECTIVO
B9: =+SAP!A2 -> 46113 | C9: =+SAP!F2 -> 0 | D9: 45810 | E9: 0000277958 | F9: INGRESO EN EFECTIVO | G9: 15551.16 | H9: =+C9-G9 -> -15551.16 | I9: 104101 | J9: OK | K9: OK | M9: =+B9 -> 46113 | N9: =+C9 -> 0
B10: =+SAP!A3 -> 46114 | C10: =+SAP!F3 -> 1098 | D10: 45811 | E10: 0000278357 | F10: INGRESO EN EFECTIVO | G10: 1685.1 | H10: =+C10-G10 -> -587.1 | I10: 104101 | J10: MASTERCARD | K10: OK | M10: =+B10 -> 46114 | N10: =+C10 -> 1098
B11: =+SAP!A4 -> 46115 | C11: =+SAP!F4 -> 459 | D11: 45812 | E11: 0000278615 | F11: INGRESO EN EFECTIVO | G11: 2798 | H11: =+C11-G11 -> -2339 | I11: 104101 | J11: OK | K11: OK | M11: =+B11 -> 46115 | N11: =+C11 -> 459
B12: =+SAP!A5 -> 46116 | C12: =+SAP!F5 -> 89 | D12: 45813 | E12: 0000278799 | F12: INGRESO EN EFECTIVO | G12: 3047 | H12: =+C12-G12 -> -2958 | I12: 104101 | J12: OK | K12: OK | M12: =+B12 -> 46116 | N12: =+C12 -> 89
B13: =+SAP!A6 -> 46117 | C13: =+SAP!F6 -> 1000 | D13: 45814 | E13: 278998 | F13: INGRESO EN EFECTIVO | G13: 6153.9 | H13: =+C13-G13 -> -5153.9 | I13: 104101 | J13: OK | K13: OK | M13: =+B13 -> 46117 | N13: =+C13 -> 1000
B14: =+SAP!A7 -> 46118 | C14: =+SAP!F7 -> 629 | D14: 45817 | E14: 279497 | F14: INGRESO EN EFECTIVO | G14: 17124.6 | H14: =+C14+C15+C16-G14 -> -14389.6 | I14: 104101 | J14: OK | K14: OK | M14: =+B14 -> 46118 | N14: =+C14 -> 629
B15: =+SAP!A8 -> 46119 | C15: =+SAP!F8 -> 1079 | J15: OK | K15: OK | M15: =+B15 -> 46119 | N15: =+C15 -> 1079
B16: =+SAP!A9 -> 46120 | C16: =+SAP!F9 -> 1027 | J16: OK | K16: OK | M16: =+B16 -> 46120 | N16: =+C16 -> 1027
B17: =+SAP!A10 -> 46121 | C17: =+SAP!F10 -> 949 | D17: 45818 | E17: 0000279832 | F17: INGRESO EN EFECTIVO | G17: 5845.9 | H17: =+C17-G17 -> -4896.9 | I17: 104101 | J17: OK | K17: OK | M17: =+B17 -> 46121 | N17: =+C17 -> 949
B18: =+SAP!A11 -> 46122 | C18: =+SAP!F11 -> 1424 | D18: 45819 | E18: 0000280080 | F18: INGRESO EN EFECTIVO | G18: 8435.8 | H18: =+C18-G18 -> -7011.8 | I18: 104101 | J18: OK | K18: OK | M18: =+B18 -> 46122 | N18: =+C18 -> 1424
B19: =+SAP!A12 -> 46123 | C19: =+SAP!F12 -> 1238 | D19: 45821 | E19: 0000280520 | F19: INGRESO EN EFECTIVO | G19: 10277.6 | H19: =+C19+C20-G19 -> -7760.6 | I19: 104101 | J19: OK | K19: OK | M19: =+B19 -> 46123 | N19: =+C19 -> 1238
B20: =+SAP!A13 -> 46124 | C20: =+SAP!F13 -> 1279 | J20: OK | K20: OK | M20: =+B20 -> 46124 | N20: =+C20 -> 1279
B21: =+SAP!A14 -> 46125 | C21: =+SAP!F14 -> 229 | D21: 45822 | E21: 0000280576 | F21: INGRESO EN EFECTIVO | G21: 3895.8 | H21: =+C21-G21 -> -3666.8 | I21: 104101 | J21: OK | K21: OK | M21: =+B21 -> 46125 | N21: =+C21 -> 229
B22: =+SAP!A15 -> 46126 | C22: =+SAP!F15 -> 0 | D22: 45824 | E22: 0000281053 | F22: INGRESO EN EFECTIVO | G22: 16211.2 | H22: =+C22+C23-G22 -> -16158.3 | I22: 104101 | J22: OK | K22: OK | M22: =+B22 -> 46126 | N22: =+C22 -> 0
B23: =+SAP!A16 -> 46127 | C23: =+SAP!F16 -> 52.9 | J23: OK | K23: OK | M23: =+B23 -> 46127 | N23: =+C23 -> 52.9
B24: =+SAP!A17 -> 46128 | C24: =+SAP!F17 -> 125.8 | D24: 45826 | E24: 0000281597 | F24: INGRESO EN EFECTIVO | G24: 4681.8 | H24: =+C24+C25-G24 -> -4391.2 | I24: 104101 | J24: OK | K24: OK | M24: =+B24 -> 46128 | N24: =+C24 -> 125.8
B25: =+SAP!A18 -> 46129 | C25: =+SAP!F18 -> 164.8 | J25: OK | K25: OK | M25: =+B25 -> 46129 | N25: =+C25 -> 164.8
B26: =+SAP!A19 -> 46130 | C26: =+SAP!F19 -> 949 | H26: =+C26-G26 -> 949 | J26: PENDIENTE | M26: =+B26 -> 46130 | N26: =+C26 -> 949
B27: =+SAP!A20 -> 46131 | C27: =+SAP!F20 -> 645.8 | H27: =+C27-G27 -> 645.8 | J27: PENDIENTE | M27: =+B27 -> 46131 | N27: =+C27 -> 645.8
B28: =+SAP!A21 -> 46132 | C28: =+SAP!F21 -> 3222.9 | H28: =+C28-G28 -> 3222.9 | J28: PENDIENTE | M28: =+B28 -> 46132 | N28: =+C28 -> 3222.9
B29: =+SAP!A22 -> 46133 | C29: =+SAP!F22 -> 0 | H29: =+C29-G29 -> 0 | J29: PENDIENTE | M29: =+B29 -> 46133 | N29: =+C29 -> 0
B30: =+SAP!A23 -> 46134 | C30: =+SAP!F23 -> 478.9 | H30: =+C30-G30 -> 478.9 | J30: PENDIENTE | M30: =+B30 -> 46134 | N30: =+C30 -> 478.9
B31: =+SAP!A24 -> 46135 | C31: =+SAP!F24 -> 459 | H31: =+C31-G31 -> 459 | J31: PENDIENTE | M31: =+B31 -> 46135 | N31: =+C31 -> 459
B32: =+SAP!A25 -> 46136 | C32: =+SAP!F25 -> 158 | H32: =+C32-G32 -> 158 | J32: PENDIENTE | M32: =+B32 -> 46136 | N32: =+C32 -> 158
B33: =+SAP!A26 -> 46137 | C33: =+SAP!F26 -> 2636 | H33: =+C33-G33 -> 2636 | J33: PENDIENTE | M33: =+B33 -> 46137 | N33: =+C33 -> 2636
B34: =+SAP!A27 -> 46138 | C34: =+SAP!F27 -> 1079.5 | H34: =+C34-G34 -> 1079.5 | J34: PENDIENTE | M34: =+B34 -> 46138 | N34: =+C34 -> 1079.5
B35: =+SAP!A28 -> 46139 | C35: =+SAP!F28 -> 2447.8 | H35: =+C35-G35 -> 2447.8 | J35: PENDIENTE | M35: =+B35 -> 46139 | N35: =+C35 -> 2447.8
B36: =+SAP!A29 -> 46140 | C36: =+SAP!F29 -> 925.9 | H36: =+C36-G36 -> 925.9 | J36: PENDIENTE | M36: =+B36 -> 46140 | N36: =+C36 -> 925.9
B37: =+SAP!A30 -> 46141 | C37: =+SAP!F30 -> 598 | H37: =+C37-G37 -> 598 | J37: PENDIENTE | M37: =+B37 -> 46141 | N37: =+C37 -> 598
... B39: =+SAP!A32 -> 0 | C39: =+SAP!F32 -> 0 | H39: =+C39-G39 -> 0 | J39: PENDIENTE | M39: =+B39 -> 0 | N39: =+C39 -> 0
F42: TOTAL PENDIENTE | G42: =SUMIF(J9:J40,"PENDIENTE",C9:C40) -> 14115.8
E50: F. Operación | F50: Nº. Doc. | G50: Concepto | H50: Importe | I50: TIENDA | J50: FECHA
D51: 104101 | E51: 45779 | F51: 0000271546 | G51: INGRESO EN EFECTIVO | H51: 9005.8 | I51: EFECTIVO HON MS | J51: 30-01.05
D52: 104101 | E52: 45783 | F52: 0000272395 | G52: INGRESO EN EFECTIVO | H52: 16049.65 | I52: EFECTIVO HON MS | J52: 02-04.05
D53: 104101 | E53: 45784 | F53: 0000272628 | G53: INGRESO EN EFECTIVO | H53: 8395.4 | I53: EFECTIVO HON MS | J53: 05-06.05
D54: 104101 | E54: 45786 | F54: 0000273104 | G54: INGRESO EN EFECTIVO - MONEDA | H54: 7388.9 | I54: EFECTIVO HON MS | J54: 07-08.05
E55: 45789 | F55: 0000273658 | G55: INGRESO EN EFECTIVO | H55: 26802.23 | I55: EFECTIVO HON MS | J55: 09-11.05
E56: 45791 | F56: 0000274191 | G56: INGRESO EN EFECTIVO | H56: 11232.05 | I56: EFECTIVO HON MS | J56: 12-13.05
E57: 45793 | F57: 0000274648 | G57: INGRESO EN EFECTIVO | H57: 8100.7 | I57: EFECTIVO HON MS | J57: 14-15.05
E58: 45796 | F58: 0000275109 | G58: INGRESO EN EFECTIVO | H58: 15781.22 | I58: EFECTIVO HON MS | J58: 16-18.05
E59: 45798 | F59: 0000275579 | G59: INGRESO EN EFECTIVO | H59: 8384.9 | I59: EFECTIVO HON MS | J59: 19-20.05
E60: 45801 | F60: 0000276050 | G60: INGRESO EN EFECTIVO | H60: 11656.1 | I60: EFECTIVO HON MS | J60: 21-22.05
E61: 45803 | F61: 0000276458 | G61: INGRESO EN EFECTIVO | H61: 15704.3 | I61: EFECTIVO HON MS | J61: 23-25.05

Sheet MC
A1: Codigo | B1: Producto | C1: Tipo_Mov | D1: Fecha_Proceso | E1: Fecha_Lote | F1: Lote_Manual | G1: Lote_Pos | H1: Terminal | I1: Voucher | J1: Autorizacion | K1: Cuotas | L1: Tarjeta | M1: Origen | N1: Transaccion | O1: Fecha_Consumo | P1: Importe | Q1: Status | R1: Comision | S1: Comision_Afecta | T1: IGV | U1: Neto_Parcial | V1: Neto_Total | W1: Fecha_Abono | X1: Fecha_Abono_8Dig | Y1: Observaciones | Z1: Tipo_Tarjeta | AA1: Serie_Terminal | AB1: Banco_Emisor | AC1: Cuota sin interes | AD1: Entidad | AE1: Hora TRX | AF1: Nombre comercial | AG1: BANCO | AJ1: Etiquetas de fila | AK1: Suma de Importe
A2: 1045649 | B2: VA | C2: A | D2: 46113 | E2: 46113 | G2: 673 | H2: PS0001 | I2: 1078 | J2: 42067 | L2: 421410******4615 | M2: Nac | N2: COM | O2: 46113 | P2: 629 | Q2: Abonado | R2: 18.18 | S2: 8.12 | T2: 1.46 | U2: 609.36 | V2: 0 | X2: 20260406 | Z2: DEBITO | AA2: 52P20548 | AB2: NACION | AE2: 0.51173611 | AF2: HONOR MODULO AREQUIPA | AG2: SCOTIABANK | AJ2: 46113 | AK2: 5591.9 | AO2: 46082 | AP2: 5591.9
A3: 1045649 | B3: VA | C3: A | D3: 46113 | E3: 46113 | G3: 673 | H3: PS0001 | I3: 1080 | J3: 80066 | L3: 455696******1576 | M3: Nac | N3: COM | O3: 46113 | P3: 1699 | Q3: Abonado | R3: 49.1 | S3: 6.62 | T3: 1.19 | U3: 1648.71 | V3: 0 | X3: 20260406 | Z3: CREDITO | AA3: 52P20548 | AB3: IBK PRIVADA | AE3: 0.63046296 | AF3: HONOR MODULO AREQUIPA | AG3: SCOTIABANK | AJ3: 46114 | AK3: 5325 | AO3: =+AO2+1 -> 46083 | AP3: 5325
A4: 1045649 | B4: VA | C4: A | D4: 46113 | E4: 46113 | G4: 673 | H4: PS0001 | I4: 1082 | J4: 576035 | L4: 438466******8008 | M4: Nac | N4: COM | O4: 46113 | P4: 89 | Q4: Abonado | R4: 2.57 | S4: 1.15 | T4: 0.21 | U4: 86.22 | V4: 0 | X4: 20260406 | Z4: DEBITO | AA4: 52P20548 | AB4: VISA LOC | AE4: 0.63863426 | AF4: HONOR MODULO AREQUIPA | AG4: SCOTIABANK | AJ4: 46115 | AK4: 149 | AO4: =+AO3+1 -> 46084 | AP4: 149
A5: 1045649 | B5: VA | C5: A | D5: 46113 | E5: 46113 | G5: 673 | H5: 65656565 | I5: 1084 | J5: 387953 | L5: 421355******8671 | M5: Nac | N5: COM | O5: 46113 | P5: 629 | Q5: Abonado | R5: 18.17 | S5: 8.11 | T5: 1.46 | U5: 609.37 | V5: 0 | X5: 20260406 | Z5: DEBITO | AA5: 52P20548 | AB5: IBK PRIVADA | AD5: IBK Plin | AE5: 0.75484954 | AF5: HONOR MODULO AREQUIPA | AG5: SCOTIABANK | AJ5: 46116 | AK5: 10291 | AO5: =+AO4+1 -> 46085 | AP5: 10291
A6: 1045649 | B6: VA | C6: A | D6: 46113 | E6: 46113 | G6: 673 | H6: PS0001 | I6: 1087 | J6: 731617 | L6: 407876******8129 | M6: Nac | N6: COM | O6: 46113 | P6: 298 | Q6: Abonado | R6: 8.61 | S6: 1.76 | T6: 0.32 | U6: 289.07 | V6: 0 | X6: 20260406 | Z6: CREDITO | AA6: 52P20548 | AB6: BFALABELLA | AE6: 0.75721065 | AF6: HONOR MODULO AREQUIPA | AG6: SCOTIABANK | AJ6: 46117 | AK6: 2166 | AO6: =+AO5+1 -> 46086 | AP6: 2166
A7: 1045649 | B7: VA | C7: A | D7: 46113 | E7: 46113 | G7: 673 | H7: PS0001 | I7: 1090 | J7: 942234 | L7: 455788******1522 | M7: Nac | N7: COM | O7: 46113 | P7: 19.9 | Q7: Abonado | R7: 0.58 | S7: 0.26 | T7: 0.05 | U7: 19.27 | V7: 0 | X7: 20260406 | Z7: DEBITO | AA7: 52P20548 | AB7: BCP | AE7: 0.78641204 | AF7: HONOR MODULO AREQUIPA | AG7: SCOTIABANK | AJ7: 46118 | AK7: 2846 | AO7: =+AO6+1 -> 46087 | AP7: 2846
A8: 1045649 | B8: VA | C8: A | D8: 46113 | E8: 46113 | G8: 673 | H8: PS0001 | I8: 1092 | J8: 950491 | L8: 455788******0725 | M8: Nac | N8: COM | O8: 46113 | P8: 529 | Q8: Abonado | R8: 15.29 | S8: 6.83 | T8: 1.23 | U8: 512.48 | V8: 0 | X8: 20260406 | Z8: DEBITO | AA8: 52P20548 | AB8: BCP | AE8: 0.81364583 | AF8: HONOR MODULO AREQUIPA | AG8: SCOTIABANK | AJ8: 46119 | AK8: 2287 | AO8: =+AO7+1 -> 46088 | AP8: 2287
A9: 1045649 | B9: VA | C9: A | D9: 46113 | E9: 46113 | G9: 673 | H9: 65656565 | I9: 1094 | J9: 293274 | L9: 421355******6998 | M9: Nac | N9: COM | O9: 46113 | P9: 1699 | Q9: Abonado | R9: 49.1 | S9: 21.92 | T9: 3.95 | U9: 1645.95 | V9: 5420.43 | W9: 46118 | X9: 20260406 | Z9: DEBITO | AA9: 52P20548 | AB9: IBK PRIVADA | AD9: IBK Plin | AE9: 0.82357639 | AF9: HONOR MODULO AREQUIPA | AG9: SCOTIABANK | AJ9: 46120 | AK9: 355.25 | AO9: =+AO8+1 -> 46089 | AP9: 355.25
A10: 1045649 | B10: VA | C10: A | D10: 46114 | E10: 46114 | G10: 674 | H10: 65656565 | I10: 1103 | J10: 761667 | L10: 455788******3226 | M10: Nac | N10: COM | O10: 46114 | P10: 499 | Q10: Abonado | R10: 14.42 | S10: 6.44 | T10: 1.16 | U10: 483.42 | V10: 0 | X10: 20260406 | Z10: DEBITO | AA10: 52P20548 | AB10: BCP | AD10: Yape | AE10: 0.52359954 | AF10: HONOR MODULO AREQUIPA | AG10: SCOTIABANK | AJ10: 46121 | AK10: 1778 | AO10: =+AO9+1 -> 46090 | AP10: 1778
A11: 1045649 | B11: VA | C11: A | D11: 46114 | E11: 46114 | G11: 674 | H11: PS0001 | I11: 1107 | J11: 4810 | L11: 463402******8027 | M11: Nac | N11: COM | O11: 46114 | P11: 1149 | Q11: Abonado | R11: 33.21 | S11: 9.08 | T11: 1.63 | U11: 1114.16 | V11: 0 | X11: 20260406 | Z11: CREDITO | AA11: 52P20548 | AB11: BCP | AE11: 0.54902778 | AF11: HONOR MODULO AREQUIPA | AG11: SCOTIABANK | AJ11: 46122 | AK11: 2535 | AO11: =+AO10+1 -> 46091 | AP11: 2535
A12: 1045649 | B12: VA | C12: A | D12: 46114 | E12: 46114 | G12: 674 | H12: PS0001 | I12: 1109 | J12: 887826 | K12: 3 | L12: 491909******5165 | M12: Nac | N12: COM | O12: 46114 | P12: 1049 | Q12: Abonado | R12: 48.68 | S12: 8.29 | T12: 1.49 | U12: 998.83 | V12: 0 | X12: 20260406 | Z12: CREDITO | AA12: 52P20548 | AB12: BBVA | AC12: SI | AE12: 0.55737269 | AF12: HONOR MODULO AREQUIPA | AG12: SCOTIABANK | AJ12: 46123 | AK12: 3316.9 | AO12: =+AO11+1 -> 46092 | AP12: 3316.9
A13: 1045649 | B13: VA | C13: A | D13: 46114 | E13: 46114 | G13: 674 | H13: PS0001 | I13: 1111 | J13: 134436 | L13: 483039******5882 | M13: Nac | N13: COM | O13: 46114 | P13: 1000 | Q13: Abonado | R13: 28.9 | S13: 7.9 | T13: 1.42 | U13: 969.68 | V13: 0 | X13: 20260406 | Z13: DEBITO | AA13: 52P20548 | AB13: IBK PRIVADA | AE13: 0.57188657 | AF13: HONOR MODULO AREQUIPA | AG13: SCOTIABANK | AJ13: 46124 | AK13: 6353 | AO13: =+AO12+1 -> 46093 | AP13: 6353
A14: 1045649 | B14: VA | C14: A | D14: 46114 | E14: 46114 | G14: 674 | H14: PS0001 | I14: 1113 | J14: 971091 | L14: 414075******8545 | M14: Nac | N14: COM | O14: 46114 | P14: 999 | Q14: Abonado | R14: 28.87 | S14: 3.89 | T14: 0.7 | U14: 969.43 | V14: 0 | X14: 20260406 | Z14: CREDITO | AA14: 52P20548 | AB14: BBVA | AE14: 0.57238426 | AF14: HONOR MODULO AREQUIPA | AG14: SCOTIABANK | AJ14: 46125 | AK14: 6374 | AO14: =+AO13+1 -> 46094 | AP14: 6374
A15: 1045649 | B15: VA | C15: A | D15: 46114 | E15: 46114 | G15: 674 | H15: PS0001 | I15: 1125 | J15: 642569 | L15: 455788******6857 | M15: Nac | N15: COM | O15: 46114 | P15: 629 | Q15: Abonado | R15: 18.18 | S15: 8.12 | T15: 1.46 | U15: 609.36 | V15: 5144.88 | W15: 46118 | X15: 20260406 | Z15: DEBITO | AA15: 52P20548 | AB15: BCP | AE15: 0.8844213 | AF15: HONOR MODULO AREQUIPA | AG15: SCOTIABANK | AJ15: 46126 | AK15: 2775 | AO15: =+AO14+1 -> 46095 | AP15: 2775
A16: 1045649 | B16: VA | C16: A | D16: 46115 | E16: 46115 | G16: 675 | H16: 65656565 | I16: 1131 | J16: 304469 | L16: 455788******6834 | M16: Nac | N16: COM | O16: 46115 | P16: 149 | Q16: Abonado | R16: 4.3 | S16: 1.92 | T16: 0.35 | U16: 144.35 | V16: 144.35 | W16: 46118 | X16: 20260406 | Z16: DEBITO | AA16: 52P20548 | AB16: VISA LOC | AD16: Yape | AE16: 0.49797454 | AF16: HONOR MODULO AREQUIPA | AG16: SCOTIABANK | AJ16: 46127 | AK16: 2047.9 | AO16: =+AO15+1 -> 46096 | AP16: 2047.9
A17: 1045649 | B17: VA | C17: A | D17: 46116 | E17: 46116 | G17: 676 | H17: PS0001 | I17: 1139 | J17: 509113 | L17: 455788******3381 | M17: Nac | N17: COM | O17: 46116 | P17: 1699 | Q17: Abonado | R17: 49.1 | S17: 21.92 | T17: 3.95 | U17: 1645.95 | V17: 0 | X17: 20260406 | Z17: DEBITO | AA17: 52P20548 | AB17: BCP | AE17: 0.42944444 | AF17: HONOR MODULO AREQUIPA | AG17: SCOTIABANK | AJ17: 46128 | AK17: 3705 | AO17: =+AO16+1 -> 46097 | AP17: 3705
A18: 1045649 | B18: VA | C18: A | D18: 46116 | E18: 46116 | G18: 676 | H18: PS0001 | I18: 1142 | J18: 196227 | L18: 414791******5996 | M18: Nac | N18: COM | O18: 46116 | P18: 659 | Q18: Abonado | R18: 19.05 | S18: 3.89 | T18: 0.7 | U18: 639.25 | V18: 0 | X18: 20260406 | Z18: CREDITO | AA18: 52P20548 | AB18: BBVA | AE18: 0.45778935 | AF18: HONOR MODULO AREQUIPA | AG18: SCOTIABANK | AJ18: 46130 | AK18: 4524 | AO18: =+AO17+1 -> 46098
A19: 1045649 | B19: VA | C19: A | D19: 46116 | E19: 46116 | G19: 676 | H19: PS0001 | I19: 1144 | J19: 481126 | L19: 447410******4840 | M19: Nac | N19: COM | O19: 46116 | P19: 3097 | Q19: Abonado | R19: 89.5 | S19: 18.27 | T19: 3.29 | U19: 3004.21 | V19: 0 | X19: 20260406 | Z19: CREDITO | AA19: 52P20548 | AB19: BFALABELLA | AE19: 0.51107639 | AF19: HONOR MODULO AREQUIPA | AG19: SCOTIABANK | AJ19: 46131 | AK19: 6258.8 | AO19: =+AO18+1 -> 46099 | AP19: 4524
A20: 1045649 | B20: VA | C20: A | D20: 46116 | E20: 46116 | G20: 676 | H20: PS0001 | I20: 1147 | J20: 983088 | L20: 455788******0605 | M20: Nac | N20: COM | O20: 46116 | P20: 949 | Q20: Abonado | R20: 27.43 | S20: 12.25 | T20: 2.21 | U20: 919.36 | V20: 0 | X20: 20260406 | Z20: DEBITO | AA20: 52P20548 | AB20: BCP | AE20: 0.61105324 | AF20: HONOR MODULO AREQUIPA | AG20: SCOTIABANK | AJ20: 46132 | AK20: 3035.9 | AO20: =+AO19+1 -> 46100 | AP20: 6258.8
A21: 1045649 | B21: VA | C21: A | D21: 46116 | E21: 46116 | G21: 676 | H21: PS0001 | I21: 1150 | J21: 192071 | L21: 455788******6654 | M21: Nac | N21: COM | O21: 46116 | P21: 3798 | Q21: Abonado | R21: 109.76 | S21: 48.99 | T21: 8.82 | U21: 3679.42 | V21: 0 | X21: 20260406 | Z21: DEBITO | AA21: 52P20548 | AB21: VISA LOC | AE21: 0.68743056 | AF21: HONOR MODULO AREQUIPA | AG21: SCOTIABANK | AJ21: Total general | AK21: 71714.65 | AO21: =+AO20+1 -> 46101 | AP21: 3035.9
A22: 1045649 | B22: VA | C22: A | D22: 46116 | E22: 46116 | G22: 676 | H22: PS0001 | I22: 1153 | J22: 347609 | L22: 455788******1099 | M22: Nac | N22: COM | O22: 46116 | P22: 89 | Q22: Abonado | R22: 2.57 | S22: 1.15 | T22: 0.21 | U22: 86.22 | V22: 9974.41 | W22: 46118 | X22: 20260406 | Z22: DEBITO | AA22: 52P20548 | AB22: BCP | AE22: 0.7572338 | AF22: HONOR MODULO AREQUIPA | AG22: SCOTIABANK | AO22: =+AO21+1 -> 46102
A23: 1045649 | B23: VA | C23: A | D23: 46117 | E23: 46117 | G23: 677 | H23: PS0001 | I23: 1158 | J23: 775421 | L23: 447410******3703 | M23: Nac | N23: COM | O23: 46117 | P23: 89 | Q23: Abonado | R23: 2.57 | S23: 0.52 | T23: 0.09 | U23: 86.34 | V23: 0 | X23: 20260406 | Z23: CREDITO | AA23: 52P20548 | AB23: BFALABELLA | AE23: 0.46271991 | AF23: HONOR MODULO AREQUIPA | AG23: SCOTIABANK | AO23: =+AO22+1 -> 46103
A24: 1045649 | B24: VA | C24: A | D24: 46117 | E24: 46117 | G24: 677 | H24: PS0001 | I24: 1160 | J24: 689138 | L24: 455788******5386 | M24: Nac | N24: COM | O24: 46117 | P24: 210 | Q24: Abonado | R24: 6.07 | S24: 2.71 | T24: 0.49 | U24: 203.44 | V24: 0 | X24: 20260406 | Z24: DEBITO | AA24: 52P20548 | AB24: BCP | AE24: 0.65798611 | AF24: HONOR MODULO AREQUIPA | AG24: SCOTIABANK | AO24: =+AO23+1 -> 46104
A25: 1045649 | B25: VA | C25: A | D25: 46117 | E25: 46117 | G25: 677 | H25: PS0001 | I25: 1162 | J25: 155542 | L25: 483039******8189 | M25: Nac | N25: COM | O25: 46117 | P25: 1189 | Q25: Abonado | R25: 34.36 | S25: 9.39 | T25: 1.69 | U25: 1152.95 | V25: 0 | X25: 20260406 | Z25: DEBITO | AA25: 52P20548 | AB25: IBK PRIVADA | AE25: 0.66293981 | AF25: HONOR MODULO AREQUIPA | AG25: SCOTIABANK | AO25: =+AO24+1 -> 46105
A26: 1045649 | B26: VA | C26: A | D26: 46117 | E26: 46117 | G26: 677 | H26: PS0001 | I26: 1168 | J26: 234671 | L26: 455788******5390 | M26: Nac | N26: COM | O26: 46117 | P26: 49 | Q26: Abonado | R26: 1.42 | S26: 0.64 | T26: 0.12 | U26: 47.46 | V26: 1490.19 | W26: 46118 | X26: 20260406 | Z26: DEBITO | AA26: 52P20548 | AB26: BCP | AE26: 0.88177083 | AF26: HONOR MODULO AREQUIPA | AG26: SCOTIABANK | AO26: =+AO25+1 -> 46106
A27: 1045649 | B27: VH | C27: A | D27: 46117 | E27: 46117 | G27: 677 | H27: PS0001 | I27: 1166 | J27: 6D5101 | L27: 457339******2611 | M27: Nac | N27: COM | O27: 46117 | P27: 629 | Q27: Abonado | R27: 18.18 | S27: 8.12 | T27: 1.46 | U27: 609.36 | V27: 609.36 | W27: 46118 | X27: 20260406 | Z27: DEBITO | AA27: 52P20548 | AB27: SIP MC | AE27: 0.8578125 | AF27: HONOR MODULO AREQUIPA | AG27: SCOTIABANK | AO27: =+AO26+1 -> 46107
A28: 1045649 | B28: VA | C28: A | D28: 46118 | E28: 46118 | G28: 678 | H28: PS0001 | I28: 1173 | J28: 161412 | L28: 455788******2207 | M28: Nac | N28: COM | O28: 46118 | P28: 89 | Q28: Abonado | R28: 2.57 | S28: 1.15 | T28: 0.21 | U28: 86.22 | V28: 0 | X28: 20260407 | Z28: DEBITO | AA28: 52P20548 | AB28: BCP | AE28: 0.60207176 | AF28: HONOR MODULO AREQUIPA | AG28: SCOTIABANK | AO28: =+AO27+1 -> 46108
A29: 1045649 | B29: VA | C29: A | D29: 46118 | E29: 46118 | G29: 678 | H29: PS0001 | I29: 1175 | J29: 621268 | L29: 455788******0728 | M29: Nac | N29: COM | O29: 46118 | P29: 230 | Q29: Abonado | R29: 6.65 | S29: 2.97 | T29: 0.53 | U29: 222.82 | V29: 0 | X29: 20260407 | Z29: DEBITO | AA29: 52P20548 | AB29: BCP | AE29: 0.78784722 | AF29: HONOR MODULO AREQUIPA | AG29: SCOTIABANK | AO29: =+AO28+1 -> 46109
A30: 1045649 | B30: VA | C30: A | D30: 46118 | E30: 46118 | G30: 678 | H30: PS0001 | I30: 1177 | J30: 185717 | L30: 483039******8189 | M30: Nac | N30: COM | O30: 46118 | P30: 919 | Q30: Abonado | R30: 26.56 | S30: 7.26 | T30: 1.31 | U30: 891.13 | V30: 0 | X30: 20260407 | Z30: DEBITO | AA30: 52P20548 | AB30: IBK PRIVADA | AE30: 0.78905093 | AF30: HONOR MODULO AREQUIPA | AG30: SCOTIABANK | AO30: =+AO29+1 -> 46110
A31: 1045649 | B31: VA | C31: A | D31: 46118 | E31: 46118 | G31: 678 | H31: 65656565 | I31: 1179 | J31: 19220 | L31: 455788******2197 | M31: Nac | N31: COM | O31: 46118 | P31: 459 | Q31: Abonado | R31: 13.26 | S31: 5.92 | T31: 1.07 | U31: 444.67 | V31: 0 | X31: 20260407 | Z31: DEBITO | AA31: 52P20548 | AB31: BCP | AD31: Yape | AE31: 0.87340278 | AF31: HONOR MODULO AREQUIPA | AG31: SCOTIABANK | AO31: =+AO30+1 -> 46111
A32: 1045649 | B32: VA | C32: A | D32: 46118 | E32: 46118 | G32: 678 | H32: PS0001 | I32: 1183 | J32: 8400 | L32: 463402******5664 | M32: Nac | N32: COM | O32: 46118 | P32: 1149 | Q32: Abonado | R32: 33.21 | S32: 9.08 | T32: 1.63 | U32: 1114.16 | V32: 2759 | W32: 46119 | X32: 20260407 | Z32: CREDITO | AA32: 52P20548 | AB32: BCP | AE32: 0.88157407 | AF32: HONOR MODULO AREQUIPA | AG32: SCOTIABANK | AO32: =+AO31+1 -> 46112
A33: 1045649 | B33: VA | C33: A | D33: 46119 | E33: 46119 | G33: 679 | H33: PS0001 | I33: 1189 | J33: 80068 | L33: 454775******3452 | M33: Nac | N33: COM | O33: 46119 | P33: 580 | Q33: Abonado | R33: 16.76 | S33: 4.58 | T33: 0.82 | U33: 562.42 | V33: 0 | X33: 20260408 | Z33: CREDITO | AA33: 52P20548 | AB33: IBK PRIVADA | AE33: 0.4637963 | AF33: HONOR MODULO AREQUIPA | AG33: SCOTIABANK
A34: 1045649 | B34: VA | C34: A | D34: 46119 | E34: 46119 | G34: 679 | H34: PS0001 | I34: 1191 | J34: 5953 | L34: 463401******7822 | M34: Nac | N34: COM | O34: 46119 | P34: 119 | Q34: Abonado | R34: 3.44 | S34: 0.94 | T34: 0.17 | U34: 115.39 | V34: 0 | X34: 20260408 | Z34: CREDITO | AA34: 52P20548 | AB34: BCP | AE34: 0.4656713 | AF34: HONOR MODULO AREQUIPA | AG34: SCOTIABANK
A35: 1045649 | B35: VA | C35: A | D35: 46119 | E35: 46119 | G35: 679 | H35: PS0001 | I35: 1193 | J35: 469018 | L35: 455788******3454 | M35: Nac | N35: COM | O35: 46119 | P35: 189 | Q35: Abonado | R35: 5.46 | S35: 2.44 | T35: 0.44 | U35: 183.1 | V35: 860.91 | W35: 46120 | X35: 20260408 | Z35: DEBITO | AA35: 52P20548 | AB35: BCP | AE35: 0.88982639 | AF35: HONOR MODULO AREQUIPA | AG35: SCOTIABANK
A36: 1045649 | B36: VA | C36: A | D36: 46120 | E36: 46120 | G36: 681 | H36: PS0001 | I36: 1203 | J36: 35645 | L36: 455788******3483 | M36: Nac | N36: COM | O36: 46120 | P36: 129 | Q36: Abonado | R36: 3.73 | S36: 1.67 | T36: 0.3 | U36: 124.97 | V36: 0 | X36: 20260409 | Z36: DEBITO | AA36: 52P20548 | AB36: BCP | AE36: 0.44934028 | AF36: HONOR MODULO AREQUIPA | AG36: SCOTIABANK
A37: 1045649 | B37: VA | C37: A | D37: 46120 | E37: 46120 | G37: 681 | H37: PS0001 | I37: 1206 | J37: 905366 | L37: 455788******6649 | M37: Nac | N37: COM | O37: 46120 | P37: 179 | Q37: Abonado | R37: 5.17 | S37: 2.31 | T37: 0.42 | U37: 173.41 | V37: 0 | X37: 20260409 | Z37: DEBITO | AA37: 52P20548 | AB37: BCP | AE37: 0.82789352 | AF37: HONOR MODULO AREQUIPA | AG37: SCOTIABANK
A38: 1045649 | B38: VA | C38: A | D38: 46120 | E38: 46120 | G38: 681 | H38: 65656565 | I38: 1208 | J38: 4395 | L38: 455788******7902 | M38: Nac | N38: COM | O38: 46120 | P38: 47.25 | Q38: Abonado | R38: 1.36 | S38: 0.6 | T38: 0.11 | U38: 45.78 | V38: 0 | X38: 20260409 | Z38: DEBITO | AA38: 52P20548 | AB38: BCP | AD38: Yape | AE38: 0.8678588 | AF38: HONOR MODULO AREQUIPA | AG38: SCOTIABANK
A39: 1045649 | B39: VA | C39: A | D39: 46120 | E39: 46119 | G39: 680 | H39: PS0001 | I39: 1198 | J39: 1126 | K39: 4 | L39: 463401******6087 | M39: Nac | N39: COM | O39: 46119 | P39: 1399 | Q39: Abonado | R39: 40.43 | S39: 11.05 | T39: 1.99 | U39: 1356.58 | V39: 1700.74 | W39: 46121 | X39: 20260409 | Y39: Pendiente del 07/04 | Z39: CREDITO | AA39: 52P20548 | AB39: BCP | AC39: NO | AE39: 0.92101852 | AF39: HONOR MODULO AREQUIPA | AG39: SCOTIABANK
A40: 1045649 | B40: VA | C40: A | D40: 46121 | E40: 46121 | G40: 682 | H40: PS0001 | I40: 1215 | J40: 866408 | L40: 455788******8558 | M40: Nac | N40: COM | O40: 46121 | P40: 1149 | Q40: Abonado | R40: 33.21 | S40: 14.83 | T40: 2.67 | U40: 1113.12 | V40: 0 | X40: 20260410 | Z40: DEBITO | AA40: 52P20548 | AB40: BCP | AE40: 0.44587963 | AF40: HONOR MODULO AREQUIPA | AG40: SCOTIABANK
A41: 1045649 | B41: VA | C41: A | D41: 46121 | E41: 46121 | G41: 682 | H41: PS0001 | I41: 1217 | J41: 413876 | L41: 477289******0529 | M41: Nac | N41: COM | O41: 46121 | P41: 629 | Q41: Abonado | R41: 18.18 | S41: 2.45 | T41: 0.44 | U41: 610.38 | V41: 1723.5 | W41: 46122 | X41: 20260410 | Z41: CREDITO | AA41: 52P20548 | AB41: IBK PRIVADA | AE41: 0.69548611 | AF41: HONOR MODULO AREQUIPA | AG41: SCOTIABANK
A42: 1045649 | B42: VA | C42: A | D42: 46123 | E42: 46123 | G42: 683 | H42: PS0001 | I42: 1223 | J42: 185767 | L42: 477290******5918 | M42: Nac | N42: COM | O42: 46122 | P42: 688 | Q42: Abonado | R42: 19.88 | S42: 5.43 | T42: 0.98 | U42: 667.14 | V42: 0 | X42: 20260413 | Z42: CREDITO | AA42: 52P20548 | AB42: IBK PRIVADA | AE42: 0.47140046 | AF42: HONOR MODULO AREQUIPA | AG42: SCOTIABANK
A43: 1045649 | B43: VA | C43: A | D43: 46123 | E43: 46123 | G43: 683 | H43: 65656565 | I43: 1225 | J43: 565779 | L43: 421355******9795 | M43: Nac | N43: COM | O43: 46122 | P43: 450 | Q43: Abonado | R43: 13 | S43: 5.8 | T43: 1.04 | U43: 435.96 | V43: 0 | X43: 20260413 | Z43: DEBITO | AA43: 52P20548 | AB43: IBK PRIVADA | AD43: IBK Plin | AE43: 0.53274306 | AF43: HONOR MODULO AREQUIPA | AG43: SCOTIABANK
A44: 1045649 | B44: VA | C44: A | D44: 46123 | E44: 46123 | G44: 683 | H44: PS0001 | I44: 1228 | J44: 204493 | L44: 426153******4769 | M44: Nac | N44: COM | O44: 46122 | P44: 1099 | Q44: Abonado | R44: 31.76 | S44: 14.18 | T44: 2.55 | U44: 1064.69 | V44: 0 | X44: 20260413 | Z44: DEBITO | AA44: 52P20548 | AB44: CAJA AREQUIP | AE44: 0.79880787 | AF44: HONOR MODULO AREQUIPA | AG44: SCOTIABANK
A45: 1045649 | B45: VA | C45: A | D45: 46123 | E45: 46123 | G45: 683 | H45: PS0001 | I45: 1231 | J45: 478473 | L45: 455788******9306 | M45: Nac | N45: COM | O45: 46122 | P45: 298 | Q45: Abonado | R45: 8.61 | S45: 3.84 | T45: 0.69 | U45: 288.7 | V45: 0 | X45: 20260413 | Z45: DEBITO | AA45: 52P20548 | AB45: BCP | AE45: 0.86555556 | AF45: HONOR MODULO AREQUIPA | AG45: SCOTIABANK
A46: 1045649 | B46: VA | C46: A | D46: 46123 | E46: 46123 | G46: 684 | H46: PS0001 | I46: 1239 | J46: 9477 | K46: 5 | L46: 434925******1803 | M46: Nac | N46: COM | O46: 46123 | P46: 629 | Q46: Abonado | R46: 18.18 | S46: 4.97 | T46: 0.89 | U46: 609.93 | V46: 0 | X46: 20260413 | Z46: CREDITO | AA46: 52P20548 | AB46: BCP | AC46: NO | AE46: 0.45717593 | AF46: HONOR MODULO AREQUIPA | AG46: SCOTIABANK
A47: 1045649 | B47: VA | C47: A | D47: 46123 | E47: 46123 | G47: 684 | H47: 65656565 | I47: 1245 | J47: 481752 | L47: 455788******3467 | M47: Nac | N47: COM | O47: 46123 | P47: 139.9 | Q47: Abonado | R47: 4.04 | S47: 1.8 | T47: 0.32 | U47: 135.54 | V47: 0 | X47: 20260413 | Z47: DEBITO | AA47: 52P20548 | AB47: BCP | AD47: Yape | AE47: 0.70956019 | AF47: HONOR MODULO AREQUIPA | AG47: SCOTIABANK
A48: 1045649 | B48: VA | C48: A | D48: 46123 | E48: 46123 | G48: 684 | H48: PS0001 | I48: 1251 | J48: 572329 | L48: 455788******1535 | M48: Nac | N48: COM | O48: 46123 | P48: 173 | Q48: Abonado | R48: 5 | S48: 2.23 | T48: 0.4 | U48: 167.6 | V48: 0 | X48: 20260413 | Z48: DEBITO | AA48: 52P20548 | AB48: BCP | AE48: 0.78140046 | AF48: HONOR MODULO AREQUIPA | AG48: SCOTIABANK
A49: 1045649 | B49: VA | C49: A | D49: 46123 | E49: 46123 | G49: 684 | H49: PS0001 | I49: 1254 | J49: 184828 | L49: 483039******0986 | M49: Nac | N49: COM | O49: 46123 | P49: 976 | Q49: Abonado | R49: 28.21 | S49: 7.71 | T49: 1.39 | U49: 946.4 | V49: 0 | X49: 20260413 | Z49: DEBITO | AA49: 52P20548 | AB49: IBK PRIVADA | AE49: 0.78293981 | AF49: HONOR MODULO AREQUIPA | AG49: SCOTIABANK
A50: 1045649 | B50: VA | C50: A | D50: 46123 | E50: 46123 | G50: 684 | H50: PS0001 | I50: 1256 | J50: 62468 | L50: 455788******1512 | M50: Nac | N50: COM | O50: 46123 | P50: 1399 | Q50: Abonado | R50: 40.43 | S50: 18.05 | T50: 3.25 | U50: 1355.32 | V50: 5671.28 | W50: 46125 | X50: 20260413 | Z50: DEBITO | AA50: 52P20548 | AB50: BCP | AE50: 0.79873843 | AF50: HONOR MODULO AREQUIPA | AG50: SCOTIABANK
A51: 1045649 | B51: VA | C51: A | D51: 46124 | E51: 46124 | G51: 685 | H51: PS0001 | I51: 1266 | J51: 794518 | L51: 455170******5584 | M51: Nac | N51: COM | O51: 46124 | P51: 1799 | Q51: Abonado | R51: 51.99 | S51: 23.21 | T51: 4.18 | U51: 1742.83 | V51: 0 | X51: 20260413 | Z51: DEBITO | AA51: 52P20548 | AB51: BBVA | AE51: 0.47483796 | AF51: HONOR MODULO AREQUIPA | AG51: SCOTIABANK
A52: 1045649 | B52: VA | C52: A | D52: 46124 | E52: 46124 | G52: 685 | H52: PS0001 | I52: 1268 | J52: 819301 | L52: 455103******5471 | M52: Nac | N52: COM | O52: 46124 | P52: 1799 | Q52: Abonado | R52: 51.99 | S52: 23.21 | T52: 4.18 | U52: 1742.83 | V52: 0 | X52: 20260413 | Z52: DEBITO | AA52: 52P20548 | AB52: BBVA | AE52: 0.48023148 | AF52: HONOR MODULO AREQUIPA | AG52: SCOTIABANK
A53: 1045649 | B53: VA | C53: A | D53: 46124 | E53: 46124 | G53: 685 | H53: PS0001 | I53: 1270 | J53: 986614 | L53: 438466******5861 | M53: Nac | N53: COM | O53: 46124 | P53: 1008 | Q53: Abonado | R53: 29.13 | S53: 5.95 | T53: 1.07 | U53: 977.8 | V53: 0 | X53: 20260413 | Z53: CREDITO | AA53: 52P20548 | AB53: VISA LOC | AE53: 0.51530093 | AF53: HONOR MODULO AREQUIPA | AG53: SCOTIABANK
A54: 1045649 | B54: VA | C54: A | D54: 46124 | E54: 46124 | G54: 685 | H54: PS0001 | I54: 1272 | J54: 6266 | K54: 10 | L54: 447410******5554 | M54: Nac | N54: COM | O54: 46124 | P54: 1248 | Q54: Abonado | R54: 36.07 | S54: 7.37 | T54: 1.33 | U54: 1210.6 | V54: 0 | X54: 20260413 | Z54: CREDITO | AA54: 52P20548 | AB54: BFALABELLA | AC54: NO | AE54: 0.68888889 | AF54: HONOR MODULO AREQUIPA | AG54: SCOTIABANK
A55: 1045649 | B55: VA | C55: A | D55: 46124 | E55: 46124 | G55: 685 | H55: PS0001 | I55: 1274 | J55: 934393 | L55: 455788******8607 | M55: Nac | N55: COM | O55: 46124 | P55: 499 | Q55: Abonado | R55: 14.42 | S55: 6.44 | T55: 1.16 | U55: 483.42 | V55: 6157.48 | W55: 46125 | X55: 20260413 | Z55: DEBITO | AA55: 52P20548 | AB55: BCP | AE55: 0.71239583 | AF55: HONOR MODULO AREQUIPA | AG55: SCOTIABANK
A56: 1045649 | B56: VA | C56: A | D56: 46125 | E56: 46125 | G56: 686 | H56: PS0001 | I56: 1279 | J56: 162385 | L56: 447409******2698 | M56: Nac | N56: COM | O56: 46125 | P56: 1799 | Q56: Abonado | R56: 51.99 | S56: 14.21 | T56: 2.56 | U56: 1744.45 | V56: 0 | X56: 20260414 | Z56: CREDITO | AA56: 52P20548 | AB56: BFALABELLA | AE56: 0.43068287 | AF56: HONOR MODULO AREQUIPA | AG56: SCOTIABANK
A57: 1045649 | B57: VA | C57: A | D57: 46125 | E57: 46125 | G57: 686 | H57: PS0001 | I57: 1281 | J57: 756256 | L57: 455788******4290 | M57: Nac | N57: COM | O57: 46125 | P57: 1999 | Q57: Abonado | R57: 57.77 | S57: 25.79 | T57: 4.64 | U57: 1936.59 | V57: 0 | X57: 20260414 | Z57: DEBITO | AA57: 52P20548 | AB57: BCP | AE57: 0.44438657 | AF57: HONOR MODULO AREQUIPA | AG57: SCOTIABANK
A58: 1045649 | B58: VA | C58: A | D58: 46125 | E58: 46125 | G58: 686 | H58: PS0001 | I58: 1284 | J58: 700229 | L58: 428597******3525 | M58: Nac | N58: COM | O58: 46125 | P58: 688 | Q58: Abonado | R58: 19.88 | S58: 5.43 | T58: 0.98 | U58: 667.14 | V58: 0 | X58: 20260414 | Z58: DEBITO | AA58: 52P20548 | AB58: BBVA | AE58: 0.71746528 | AF58: HONOR MODULO AREQUIPA | AG58: SCOTIABANK
A59: 1045649 | B59: VA | C59: A | D59: 46125 | E59: 46125 | G59: 686 | H59: PS0001 | I59: 1288 | J59: 276635 | L59: 455170******9810 | M59: Nac | N59: COM | O59: 46125 | P59: 1000 | Q59: Abonado | R59: 28.9 | S59: 12.9 | T59: 2.32 | U59: 968.78 | V59: 0 | X59: 20260414 | Z59: DEBITO | AA59: 52P20548 | AB59: BBVA | AE59: 0.8228125 | AF59: HONOR MODULO AREQUIPA | AG59: SCOTIABANK
A60: 1045649 | B60: VA | C60: A | D60: 46125 | E60: 46125 | G60: 686 | H60: PS0001 | I60: 1290 | J60: 194622 | L60: 483039******8189 | M60: Nac | N60: COM | O60: 46125 | P60: 799 | Q60: Abonado | R60: 23.09 | S60: 6.31 | T60: 1.14 | U60: 774.77 | V60: 0 | X60: 20260414 | Z60: DEBITO | AA60: 52P20548 | AB60: IBK PRIVADA | AE60: 0.82314815 | AF60: HONOR MODULO AREQUIPA | AG60: SCOTIABANK
A61: 1045649 | B61: VA | C61: A | D61: 46125 | E61: 46125 | G61: 686 | H61: PS0001 | I61: 1292 | J61: 280803 | L61: 455170******9810 | M61: Nac | N61: COM | O61: 46125 | P61: 89 | Q61: Abonado | R61: 2.57 | S61: 1.15 | T61: 0.21 | U61: 86.22 | V61: 6177.95 | W61: 46126 | X61: 20260414 | Z61: DEBITO | AA61: 52P20548 | AB61: BBVA | AE61: 0.82358796 | AF61: HONOR MODULO AREQUIPA | AG61: SCOTIABANK
A62: 1045649 | B62: VA | C62: A | D62: 46126 | E62: 46126 | G62: 687 | H62: PS0001 | I62: 1298 | J62: 645709 | K62: 2 | L62: 414075******5948 | M62: Nac | N62: COM | O62: 46126 | P62: 299 | Q62: Abonado | R62: 13.87 | S62: 1.16 | T62: 0.21 | U62: 284.92 | V62: 0 | X62: 20260415 | Z62: CREDITO | AA62: 52P20548 | AB62: BBVA | AC62: SI | AE62: 0.4819213 | AF62: HONOR MODULO AREQUIPA | AG62: SCOTIABANK
A63: 1045649 | B63: VA | C63: A | D63: 46126 | E63: 46126 | G63: 687 | H63: PS0001 | I63: 1300 | J63: 423197 | L63: 455788******4356 | M63: Nac | N63: COM | O63: 46126 | P63: 1699 | Q63: Abonado | R63: 49.1 | S63: 21.92 | T63: 3.95 | U63: 1645.95 | V63: 0 | X63: 20260415 | Z63: DEBITO | AA63: 52P20548 | AB63: BCP | AE63: 0.50071759 | AF63: HONOR MODULO AREQUIPA | AG63: SCOTIABANK
A64: 1045649 | B64: VA | C64: A | D64: 46126 | E64: 46126 | G64: 687 | H64: 65656565 | I64: 1302 | J64: 554387 | L64: 455788******2508 | M64: Nac | N64: COM | O64: 46126 | P64: 89 | Q64: Abonado | R64: 2.57 | S64: 1.15 | T64: 0.21 | U64: 86.22 | V64: 0 | X64: 20260415 | Z64: DEBITO | AA64: 52P20548 | AB64: BCP | AD64: Yape | AE64: 0.55271991 | AF64: HONOR MODULO AREQUIPA | AG64: SCOTIABANK
A65: 1045649 | B65: VA | C65: A | D65: 46126 | E65: 46126 | G65: 687 | H65: PS0001 | I65: 1305 | J65: 3750 | L65: 463402******1821 | M65: Nac | N65: COM | O65: 46126 | P65: 688 | Q65: Abonado | R65: 19.88 | S65: 5.43 | T65: 0.98 | U65: 667.14 | V65: 2684.23 | W65: 46127 | X65: 20260415 | Z65: CREDITO | AA65: 52P20548 | AB65: BCP | AE65: 0.81037037 | AF65: HONOR MODULO AREQUIPA | AG65: SCOTIABANK
A66: 1045649 | B66: VA | C66: A | D66: 46127 | E66: 46127 | G66: 688 | H66: PS0001 | I66: 1310 | J66: 605630 | L66: 455788******3679 | M66: Nac | N66: COM | O66: 46127 | P66: 1799 | Q66: Abonado | R66: 51.99 | S66: 23.21 | T66: 4.18 | U66: 1742.83 | V66: 0 | X66: 20260416 | Z66: DEBITO | AA66: 52P20548 | AB66: BCP | AE66: 0.50868056 | AF66: HONOR MODULO AREQUIPA | AG66: SCOTIABANK
A67: 1045649 | B67: VA | C67: A | D67: 46127 | E67: 46127 | G67: 688 | H67: 65656565 | I67: 1312 | J67: 837823 | L67: 455788******2559 | M67: Nac | N67: COM | O67: 46127 | P67: 179.9 | Q67: Abonado | R67: 5.19 | S67: 2.31 | T67: 0.42 | U67: 174.29 | V67: 0 | X67: 20260416 | Z67: DEBITO | AA67: 52P20548 | AB67: BCP | AD67: Yape | AE67: 0.81826389 | AF67: HONOR MODULO AREQUIPA | AG67: SCOTIABANK
A68: 1045649 | B68: VA | C68: A | D68: 46127 | E68: 46127 | G68: 688 | H68: PS0001 | I68: 1315 | J68: 8930 | L68: 455788******9843 | M68: Nac | N68: COM | O68: 46127 | P68: 69 | Q68: Abonado | R68: 1.99 | S68: 0.89 | T68: 0.16 | U68: 66.85 | V68: 1983.97 | W68: 46128 | X68: 20260416 | Z68: DEBITO | AA68: 52P20548 | AB68: BCP | AE68: 0.88903935 | AF68: HONOR MODULO AREQUIPA | AG68: SCOTIABANK
A69: 1045649 | B69: VA | C69: A | D69: 46128 | E69: 46128 | G69: 689 | H69: PS0001 | I69: 1320 | J69: 117039 | L69: 455170******8481 | M69: Nac | N69: COM | O69: 46128 | P69: 69 | Q69: Abonado | R69: 1.99 | S69: 0.89 | T69: 0.16 | U69: 66.85 | V69: 0 | X69: 20260417 | Z69: DEBITO | AA69: 52P20548 | AB69: BBVA | AE69: 0.44806713 | AF69: HONOR MODULO AREQUIPA | AG69: SCOTIABANK
A70: 1045649 | B70: VA | C70: A | D70: 46128 | E70: 46128 | G70: 689 | H70: PS0001 | I70: 1322 | J70: 110752 | L70: 455788******9452 | M70: Nac | N70: COM | O70: 46128 | P70: 1699 | Q70: Abonado | R70: 49.1 | S70: 21.92 | T70: 3.95 | U70: 1645.95 | V70: 0 | X70: 20260417 | Z70: DEBITO | AA70: 52P20548 | AB70: BCP | AE70: 0.62247685 | AF70: HONOR MODULO AREQUIPA | AG70: SCOTIABANK
A71: 1045649 | B71: VA | C71: A | D71: 46128 | E71: 46128 | G71: 689 | H71: PS0001 | I71: 1324 | J71: 32947 | L71: 422224******4192 | M71: Nac | N71: COM | O71: 46128 | P71: 89 | Q71: Abonado | R71: 2.57 | S71: 0.52 | T71: 0.09 | U71: 86.34 | V71: 0 | X71: 20260417 | Z71: CREDITO | AA71: 52P20548 | AB71: IBK PRIVADA | AE71: 0.62732639 | AF71: HONOR MODULO AREQUIPA | AG71: SCOTIABANK
A72: 1045649 | B72: VA | C72: A | D72: 46128 | E72: 46128 | G72: 689 | H72: PS0001 | I72: 1327 | J72: 394256 | K72: 3 | L72: 491909******4880 | M72: Nac | N72: COM | O72: 46128 | P72: 1699 | Q72: Abonado | R72: 78.83 | S72: 13.42 | T72: 2.42 | U72: 1617.75 | V72: 0 | X72: 20260417 | Z72: CREDITO | AA72: 52P20548 | AB72: BBVA | AC72: SI | AE72: 0.71164352 | AF72: HONOR MODULO AREQUIPA | AG72: SCOTIABANK
A73: 1045649 | B73: VA | C73: A | D73: 46128 | E73: 46128 | G73: 689 | H73: PS0001 | I73: 1330 | J73: 899666 | L73: 455788******7070 | M73: Nac | N73: COM | O73: 46128 | P73: 149 | Q73: Abonado | R73: 4.31 | S73: 1.93 | T73: 0.35 | U73: 144.34 | V73: 3561.23 | W73: 46129 | X73: 20260417 | Z73: DEBITO | AA73: 52P20548 | AB73: BCP | AE73: 0.73954861 | AF73: HONOR MODULO AREQUIPA | AG73: SCOTIABANK
A74: 1045649 | B74: MC | C74: A | D74: 46130 | E74: 46130 | G74: 690 | H74: PS0001 | I74: 1346 | J74: 117800 | L74: 511842******9615 | M74: Nac | N74: COM | O74: 46130 | P74: 189 | Q74: Abonado | R74: 5.46 | S74: 2.15 | T74: 0.39 | U74: 183.15 | V74: 183.15 | W74: 46132 | X74: 20260420 | Z74: DEBITO | AA74: 52P20548 | AB74: SCOTIA DEBIT | AE74: 0.76960648 | AF74: HONOR MODULO AREQUIPA | AG74: SCOTIABANK
A75: 1045649 | B75: VA | C75: A | D75: 46130 | E75: 46130 | G75: 690 | H75: PS0001 | I75: 1337 | J75: 8338 | L75: 445330******6823 | M75: Nac | N75: COM | O75: 46130 | P75: 459 | Q75: Abonado | R75: 13.27 | S75: 2.71 | T75: 0.49 | U75: 445.24 | V75: 0 | X75: 20260420 | Z75: CREDITO | AA75: 52P20548 | AB75: BCP | AE75: 0.46384259 | AF75: HONOR MODULO AREQUIPA | AG75: SCOTIABANK
A76: 1045649 | B76: VA | C76: A | D76: 46130 | E76: 46130 | G76: 690 | H76: PS0001 | I76: 1341 | J76: 44001 | L76: 411539******6084 | M76: Nac | N76: COM | O76: 46130 | P76: 1248 | Q76: Abonado | R76: 36.07 | S76: 16.1 | T76: 2.9 | U76: 1209.03 | V76: 0 | X76: 20260420 | Z76: DEBITO | AA76: 52P20548 | AB76: VISA LOC | AE76: 0.67623843 | AF76: HONOR MODULO AREQUIPA | AG76: SCOTIABANK
A77: 1045649 | B77: VA | C77: A | D77: 46130 | E77: 46130 | G77: 690 | H77: PS0001 | I77: 1343 | J77: 1928 | L77: 463402******9387 | M77: Nac | N77: COM | O77: 46130 | P77: 1999 | Q77: Abonado | R77: 57.77 | S77: 15.79 | T77: 2.84 | U77: 1938.39 | V77: 3592.66 | W77: 46132 | X77: 20260420 | Z77: CREDITO | AA77: 52P20548 | AB77: BCP | AE77: 0.68582176 | AF77: HONOR MODULO AREQUIPA | AG77: SCOTIABANK
A78: 1045649 | B78: VH | C78: A | D78: 46130 | E78: 46130 | G78: 690 | H78: PS0001 | I78: 1339 | J78: 87C6D6 | L78: 457339******8459 | M78: Nac | N78: COM | O78: 46130 | P78: 629 | Q78: Abonado | R78: 18.18 | S78: 8.12 | T78: 1.46 | U78: 609.36 | V78: 609.36 | W78: 46132 | X78: 20260420 | Z78: DEBITO | AA78: 52P20548 | AB78: SIP MC | AE78: 0.59211806 | AF78: HONOR MODULO AREQUIPA | AG78: SCOTIABANK
A79: 1045649 | B79: VA | C79: A | D79: 46131 | E79: 46131 | G79: 691 | H79: PS0001 | I79: 1355 | J79: 191198 | L79: 455788******5296 | M79: Nac | N79: COM | O79: 46131 | P79: 179.9 | Q79: Abonado | R79: 5.2 | S79: 2.32 | T79: 0.42 | U79: 174.28 | V79: 0 | X79: 20260420 | Z79: DEBITO | AA79: 52P20548 | AB79: BCP | AE79: 0.45774306 | AF79: HONOR MODULO AREQUIPA | AG79: SCOTIABANK
A80: 1045649 | B80: VA | C80: A | D80: 46131 | E80: 46131 | G80: 691 | H80: 65656565 | I80: 1359 | J80: 151551 | L80: 455788******5723 | M80: Nac | N80: COM | O80: 46131 | P80: 62.9 | Q80: Abonado | R80: 1.81 | S80: 0.8 | T80: 0.14 | U80: 60.95 | V80: 0 | X80: 20260420 | Z80: DEBITO | AA80: 52P20548 | AB80: VISA LOC | AD80: Yape | AE80: 0.70517361 | AF80: HONOR MODULO AREQUIPA | AG80: SCOTIABANK
A81: 1045649 | B81: VA | C81: A | D81: 46131 | E81: 46131 | G81: 691 | H81: PS0001 | I81: 1363 | J81: 259797 | L81: 455788******0514 | M81: Nac | N81: COM | O81: 46131 | P81: 3199 | Q81: Abonado | R81: 92.45 | S81: 41.27 | T81: 7.43 | U81: 3099.12 | V81: 0 | X81: 20260420 | Z81: DEBITO | AA81: 52P20548 | AB81: BCP | AE81: 0.7550463 | AF81: HONOR MODULO AREQUIPA | AG81: SCOTIABANK
A82: 1045649 | B82: VA | C82: A | D82: 46131 | E82: 46131 | G82: 691 | H82: PS0001 | I82: 1367 | J82: 923930 | L82: 455788******7166 | M82: Nac | N82: COM | O82: 46131 | P82: 1000 | Q82: Abonado | R82: 28.9 | S82: 12.9 | T82: 2.32 | U82: 968.78 | V82: 0 | X82: 20260420 | Z82: DEBITO | AA82: 52P20548 | AB82: VISA LOC | AE82: 0.77840278 | AF82: HONOR MODULO AREQUIPA | AG82: SCOTIABANK
A83: 1045649 | B83: VA | C83: A | D83: 46131 | E83: 46131 | G83: 691 | H83: PS0001 | I83: 1369 | J83: 15387 | K83: 3 | L83: 447409******2004 | M83: Nac | N83: COM | O83: 46131 | P83: 799 | Q83: Abonado | R83: 23.09 | S83: 6.31 | T83: 1.14 | U83: 774.77 | V83: 0 | X83: 20260420 | Z83: CREDITO | AA83: 52P20548 | AB83: BFALABELLA | AC83: NO | AE83: 0.77903935 | AF83: HONOR MODULO AREQUIPA | AG83: SCOTIABANK
A84: 1045649 | B84: VA | C84: A | D84: 46131 | E84: 46131 | G84: 691 | H84: PS0001 | I84: 1371 | J84: 69723 | K84: 2 | L84: 447409******1889 | M84: Nac | N84: COM | O84: 46131 | P84: 359 | Q84: Abonado | R84: 10.38 | S84: 2.84 | T84: 0.51 | U84: 348.11 | V84: 5426.01 | W84: 46132 | X84: 20260420 | Z84: CREDITO | AA84: 52P20548 | AB84: BFALABELLA | AC84: NO | AE84: 0.86885417 | AF84: HONOR MODULO AREQUIPA | AG84: SCOTIABANK
A85: 1045649 | B85: VH | C85: A | D85: 46131 | E85: 46131 | G85: 691 | H85: PS0001 | I85: 1357 | J85: 29C772 | L85: 457339******0709 | M85: Nac | N85: COM | O85: 46131 | P85: 659 | Q85: Abonado | R85: 19.05 | S85: 8.51 | T85: 1.53 | U85: 638.42 | V85: 638.42 | W85: 46132 | X85: 20260420 | Z85: DEBITO | AA85: 52P20548 | AB85: SIP MC | AE85: 0.62313657 | AF85: HONOR MODULO AREQUIPA | AG85: SCOTIABANK
A86: 1045649 | B86: VA | C86: A | D86: 46132 | E86: 46132 | G86: 692 | H86: 65656565 | I86: 1376 | J86: 890388 | L86: 455788******6381 | M86: Nac | N86: COM | O86: 46132 | P86: 9 | Q86: Abonado | R86: 0.26 | S86: 0.12 | T86: 0.02 | U86: 8.72 | V86: 0 | X86: 20260421 | Z86: DEBITO | AA86: 52P20548 | AB86: VISA LOC | AD86: Yape | AE86: 0.51528935 | AF86: HONOR MODULO AREQUIPA | AG86: SCOTIABANK
A87: 1045649 | B87: VA | C87: A | D87: 46132 | E87: 46132 | G87: 692 | H87: PS0001 | I87: 1379 | J87: 832484 | L87: 491909******0563 | M87: Nac | N87: COM | O87: 46132 | P87: 629 | Q87: Abonado | R87: 18.18 | S87: 4.97 | T87: 0.89 | U87: 609.93 | V87: 0 | X87: 20260421 | Z87: CREDITO | AA87: 52P20548 | AB87: BBVA | AE87: 0.52053241 | AF87: HONOR MODULO AREQUIPA | AG87: SCOTIABANK
A88: 1045649 | B88: VA | C88: A | D88: 46132 | E88: 46132 | G88: 692 | H88: PS0001 | I88: 1386 | J88: 219132 | L88: 428582******4931 | M88: Nac | N88: COM | O88: 46132 | P88: 1749 | Q88: Abonado | R88: 50.55 | S88: 22.57 | T88: 4.06 | U88: 1694.39 | V88: 0 | X88: 20260421 | Z88: DEBITO | AA88: 52P20548 | AB88: SCOTIABANK | AE88: 0.66466435 | AF88: HONOR MODULO AREQUIPA | AG88: SCOTIABANK
A89: 1045649 | B89: VA | C89: A | D89: 46132 | E89: 46132 | G89: 692 | H89: PS0001 | I89: 1392 | J89: 622431 | L89: 455170******5939 | M89: Nac | N89: COM | O89: 46132 | P89: 19.9 | Q89: Abonado | R89: 0.58 | S89: 0.26 | T89: 0.05 | U89: 19.27 | V89: 0 | X89: 20260421 | Z89: DEBITO | AA89: 52P20548 | AB89: BBVA | AE89: 0.86741898 | AF89: HONOR MODULO AREQUIPA | AG89: SCOTIABANK
A90: 1045649 | B90: VA | C90: A | D90: 46132 | E90: 46132 | G90: 692 | H90: PS0001 | I90: 1394 | J90: 887884 | L90: 455788******4891 | M90: Nac | N90: COM | O90: 46132 | P90: 629 | Q90: Abonado | R90: 18.18 | S90: 8.12 | T90: 1.46 | U90: 609.36 | V90: 2941.67 | W90: 46133 | X90: 20260421 | Z90: DEBITO | AA90: 52P20548 | AB90: BCP | AE90: 0.87059028 | AF90: HONOR MODULO AREQUIPA | AG90: SCOTIABANK

Sheet AMEX
A1: Codigo | B1: Producto | C1: Tipo_Mov | D1: Fecha_Proceso | E1: Fecha_Lote | F1: Lote_Manual | G1: Lote_Pos | H1: Terminal | I1: Voucher | J1: Autorizacion | K1: Cuotas | L1: Tarjeta | M1: Origen | N1: Transaccion | O1: Fecha_Consumo | P1: Importe | Q1: Comision | R1: Comision_Merchant | S1: IGV | T1: Neto_Parcial | U1: Neto_Total | V1: Fecha_Abono | W1: Observaciones | X1: TIENDA | Y1: BANCOS | AB1: Etiquetas de fila | AC1: Suma de Importe
A2: 1045649 | C2: A | D2: 46087 | E2: 46087 | G2: 648 | H2: PS0001 | I2: 697 | J2: 481496 | K2: 2 | L2: 377892*****9959 | N2: COMPRA | O2: 46087 | P2: 1049 | Q2: 41.86 | R2: 8.37 | S2: 1.51 | T2: 1005.63 | U2: 0 | V2: 20260310 | X2: HONOR MODULO AREQUIPA | Y2: SCOTIABANK | AB2: (en blanco) | AC2: 0 | AF2: 46054
A3: 1045649 | C3: C | D3: 46087 | E3: 46087 | F3: 9996 | N3: S.E.A. | O3: 46087 | P3: 0 | Q3: -5 | R3: -5 | S3: -0.9 | T3: -5.9 | U3: 0 | V3: 20260310 | W3: Descuento Pendiente | X3: HONOR MODULO AREQUIPA | Y3: SCOTIABANK | AB3: 6-Mar | AC3: 1049 | AF3: =+AF2+1 -> 46055
A4: 1045649 | C4: A | D4: 46087 | P4: 0 | Q4: 0 | R4: 0 | S4: 0 | T4: -5.9 | U4: 999.73 | V4: 20260310 | W4: Descuentos Aplicados | X4: HONOR MODULO AREQUIPA | Y4: SCOTIABANK | AB4: 18-Mar | AC4: 1228 | AF4: =+AF3+1 -> 46056
A5: 1045649 | C5: A | D5: 46099 | E5: 46099 | G5: 659 | H5: PS0001 | I5: 899 | J5: 966492 | L5: 377898*****6462 | N5: COMPRA | O5: 46099 | P5: 1228 | Q5: 49 | R5: 9.8 | S5: 1.76 | T5: 1177.24 | U5: 1177.24 | V5: 20260320 | X5: HONOR MODULO AREQUIPA | Y5: SCOTIABANK | AB5: Total general | AC5: 2277 | AF5: =+AF4+1 -> 46057
AF6: =+AF5+1 -> 46058
AF7: =+AF6+1 -> 46059
AF8: =+AF7+1 -> 46060
AF9: =+AF8+1 -> 46061
AF10: =+AF9+1 -> 46062
AF11: =+AF10+1 -> 46063
AF12: =+AF11+1 -> 46064
AF13: =+AF12+1 -> 46065
AF14: =+AF13+1 -> 46066
AF15: =+AF14+1 -> 46067
AF16: =+AF15+1 -> 46068
AF17: =+AF16+1 -> 46069
... AF32: =+AF31+1 -> 46084

Sheet DINNERS
A1: Código de comercio | B1: Nombre del comercio | C1: Red | D1: Origen | E1: Tipo de transacción | F1: Fecha de recepción | G1: Fecha de proceso | H1: Marca | I1: N° de tarjeta | J1: Tipo de tarjeta | K1: Código de autorización | L1: Orden de pago | M1: Moneda | N1: Fecha de ticket | O1: N° ticket | P1: Estado de ticket | Q1: N° de cuotas | R1: Plazo de pago | S1: Fecha de pago | T1: Tipo de comisión | U1: Valor de comisión | V1: Importe del consumo | W1: Comisión del consumo | X1: IGV del consumo | Y1: Importe neto de pago | Z1: Producto | AB1: Etiquetas de fila | AC1: Suma de Importe del consumo
A2: 2000640121 | B2: HONOR MODULO AREQUIPA | C2: IZIPAY | E2: CONSUMO | F2: 46124 | G2: 46124 | H2: DINERS | I2: **** ****** 0270 | J2: LOCAL | K2: 59968 | L2: 2.60414e+15 | M2: SOLES | N2: 46123 | O2: 1258 | P2: PROCESADO | Q2: 3 | R2: 2 días | S2: 46126 | T2: PORCENTUAL | U2: 3.95 | V2: 149 | W2: 5.89 | X2: 1.06 | Y2: 142.05 | Z2: CUOTAS SIN INTERESES | AB2: (en blanco) | AF2: 46054
AB3: 46084 | AC3: 149 | AF3: =+AF2+1 -> 46055
AB4: Total general | AC4: 149 | AF4: =+AF3+1 -> 46056
AF5: =+AF4+1 -> 46057
AF6: =+AF5+1 -> 46058
AF7: =+AF6+1 -> 46059
AF8: =+AF7+1 -> 46060
AF9: =+AF8+1 -> 46061
AF10: =+AF9+1 -> 46062
AF11: =+AF10+1 -> 46063
AF12: =+AF11+1 -> 46064 | AG12: 149
AF13: =+AF12+1 -> 46065
AF14: =+AF13+1 -> 46066
AF15: =+AF14+1 -> 46067
AF16: =+AF15+1 -> 46068
AF17: =+AF16+1 -> 46069
AF18: =+AF17+1 -> 46070
AF19: =+AF18+1 -> 46071
AF20: =+AF19+1 -> 46072
AF21: =+AF20+1 -> 46073
AF22: =+AF21+1 -> 46074
AF23: =+AF22+1 -> 46075
AF24: =+AF23+1 -> 46076
... AF32: =+AF31+1 -> 46084
